Workbook

Sheet Overview
B2: Cross-Use Case Matrix (Weighted AveAgentice out of 5) | M2: Cross-Use Case Matrix (Average: Avg) | W2: Cross-Use Case Matrix (Average: StdDev)
B3: Use Case | C3: OpenAI | E3: Gemini | M3: Use Case | N3: OpenAI | Q3: Gemini | W3: Use Case | X3: OpenAI | AA3: Gemini
C4: Agentic | D4: Agentic | E4: Agentic | F4: Agentic | N4: RAG | O4: Agentic | P4: Total | Q4: RAG | R4: Agentic | S4: Total | T4: RAG Total | U4: Agentic Total | X4: RAG | Y4: Agentic | Z4: Total | AA4: RAG | AB4: Agentic | AC4: Total | AD4: RAG Total | AE4: Agentic Total
B5: Gifts & Entertainment | C5: ='OAI Agentic G+E'!I27 -> 3.721 | D5: ='OAI Agentic G+E'!I27 -> 3.721 | E5: ='Gemini Agentic G+E'!I27 -> 3.7368 | F5: ='Gemini Agentic G+E'!I27 -> 3.7368 | M5: Factual Acc | N5: =AVERAGE(D17,J17,P17,V17,AB17,AH17) -> 4.24 | O5: =AVERAGE(D35,J35,P35) -> 2.9928205 | P5: =AVERAGE(N5:O5) -> 3.6164103 | Q5: =AVERAGE(D26,J26,P26,V26,AB26,AH26) -> 4.4199821 | R5: =AVERAGE(D44,J44,P44) -> 3.8005128 | S5: =AVERAGE(Q5:R5) -> 4.1102475 | T5: =AVERAGE(Q5,N5) -> 4.3299911 | U5: =AVERAGE(R5,O5) -> 3.3966667 | W5: Factual Acc | X5: =AVERAGE(F17,L17,R17,X17,AD17,AJ17) -> 0.9188222 | Y5: =AVERAGE(F35,L35,R35) -> 0.82655426 | Z5: =AVERAGE(X5:Y5) -> 0.87268823 | AA5: =AVERAGE(F26,L26,R26,X26,AD26,AJ26) -> 0.78153684 | AB5: =AVERAGE(F44,L44,R44) -> 0.76846057 | AC5: =AVERAGE(AA5:AB5) -> 0.7749987 | AD5: =AVERAGE(AA5,X5) -> 0.85017952 | AE5: =AVERAGE(AB5,Y5) -> 0.79750742
B6: IT-Governance | C6: ='OAI Agentic IT-G'!I27 -> 3.3865 | D6: ='OAI Agentic IT-G'!I27 -> 3.3865 | E6: ='Gemini Agentic IT-G'!I27 -> 3.3312 | F6: ='Gemini Agentic IT-G'!I27 -> 3.3312 | M6: Relevance | N6: =AVERAGE(D18,J18,P18,V18,AB18,AH18) -> 4.7105128 | O6: =AVERAGE(D36,J36,P36) -> 3.9461538 | P6: =AVERAGE(N6:O6) -> 4.3283333 | Q6: =AVERAGE(D27,J27,P27,V27,AB27,AH27) -> 4.6677957 | R6: =AVERAGE(D45,J45,P45) -> 4.3328205 | S6: =AVERAGE(Q6:R6) -> 4.5003081 | T6: =AVERAGE(Q6,N6) -> 4.6891542 | U6: =AVERAGE(R6,O6) -> 4.1394872 | W6: Relevance | X6: =AVERAGE(F18,L18,R18,X18,AD18,AJ18) -> 0.72390257 | Y6: =AVERAGE(F36,L36,R36) -> 0.64216813 | Z6: =AVERAGE(X6:Y6) -> 0.68303535 | AA6: =AVERAGE(F27,L27,R27,X27,AD27,AJ27) -> 0.8251987 | AB6: =AVERAGE(F45,L45,R45) -> 0.72749219 | AC6: =AVERAGE(AA6:AB6) -> 0.77634545 | AD6: =AVERAGE(AA6,X6) -> 0.77455064 | AE6: =AVERAGE(AB6,Y6) -> 0.68483016
B7: New HQ v0 | C7: ='OAI RAG NHQ v0'!I131 -> 5 | D7: ='OAI Agentic NHQ'!I132 -> 2.6642308 | E7: ='Gemini RAG NHQ v0'!I132 -> 3.7521538 | F7: ='Gemini Agentic NHQ'!I132 -> 4.052 | M7: Completeness | N7: =AVERAGE(D19,J19,P19,V19,AB19,AH19) -> 3.8871795 | O7: =AVERAGE(D37,J37,P37) -> 2.9061538 | P7: =AVERAGE(N7:O7) -> 3.3966667 | Q7: =AVERAGE(D28,J28,P28,V28,AB28,AH28) -> 3.8959273 | R7: =AVERAGE(D46,J46,P46) -> 3.2948718 | S7: =AVERAGE(Q7:R7) -> 3.5953995 | T7: =AVERAGE(Q7,N7) -> 3.8915534 | U7: =AVERAGE(R7,O7) -> 3.1005128 | W7: Completeness | X7: =AVERAGE(F19,L19,R19,X19,AD19,AJ19) -> 0.84961744 | Y7: =AVERAGE(F37,L37,R37) -> 0.78243232 | Z7: =AVERAGE(X7:Y7) -> 0.81602488 | AA7: =AVERAGE(F28,L28,R28,X28,AD28,AJ28) -> 0.94834778 | AB7: =AVERAGE(F46,L46,R46) -> 0.90802778 | AC7: =AVERAGE(AA7:AB7) -> 0.92818778 | AD7: =AVERAGE(AA7,X7) -> 0.89898261 | AE7: =AVERAGE(AB7,Y7) -> 0.84523005
B8: New HQ v1 | C8: ='OAI RAG NHQ v1'!I132 -> 4.2584615 | E8: ='Gemini RAG NHQ v1'!I131 -> 3.8651163 | M8: Clarity | N8: =AVERAGE(D20,J20,P20,V20,AB20,AH20) -> 4.5233333 | O8: =AVERAGE(D38,J38,P38) -> 3.8307692 | P8: =AVERAGE(N8:O8) -> 4.1770513 | Q8: =AVERAGE(D29,J29,P29,V29,AB29,AH29) -> 4.6448678 | R8: =AVERAGE(D47,J47,P47) -> 4.4010256 | S8: =AVERAGE(Q8:R8) -> 4.5229467 | T8: =AVERAGE(Q8,N8) -> 4.5841006 | U8: =AVERAGE(R8,O8) -> 4.1158974 | W8: Clarity | X8: =AVERAGE(F20,L20,R20,X20,AD20,AJ20) -> 0.65391126 | Y8: =AVERAGE(F38,L38,R38) -> 0.6297461 | Z8: =AVERAGE(X8:Y8) -> 0.64182868 | AA8: =AVERAGE(F29,L29,R29,X29,AD29,AJ29) -> 0.75315685 | AB8: =AVERAGE(F47,L47,R47) -> 0.53213719 | AC8: =AVERAGE(AA8:AB8) -> 0.64264702 | AD8: =AVERAGE(AA8,X8) -> 0.70353406 | AE8: =AVERAGE(AB8,Y8) -> 0.58094165
B9: New HQ v2 | C9: ='OAI RAG NHQ v2'!I132 -> 4.1578846 | E9: ='Gemini RAG NHQ v2'!I132 -> 3.8461538 | M9: Citation Q. | N9: =AVERAGE(D21,J21,P21,V21,AB21,AH21) -> 3.2866667 | O9: =AVERAGE(D39,J39,P39) -> 1.9205128 | P9: =AVERAGE(N9:O9) -> 2.6035897 | Q9: =AVERAGE(D30,J30,P30,V30,AB30,AH30) -> 1.3682906 | R9: =AVERAGE(D48,J48,P48) -> 2.3605128 | S9: =AVERAGE(Q9:R9) -> 1.8644017 | T9: =AVERAGE(Q9,N9) -> 2.3274786 | U9: =AVERAGE(R9,O9) -> 2.1405128 | W9: Citation Q. | X9: =AVERAGE(F21,L21,R21,X21,AD21,AJ21) -> 0.91574173 | Y9: =AVERAGE(F39,L39,R39) -> 0.63586976 | Z9: =AVERAGE(X9:Y9) -> 0.77580574 | AA9: =AVERAGE(F30,L30,R30,X30,AD30,AJ30) -> 0.71937447 | AB9: =AVERAGE(F48,L48,R48) -> 0.85567967 | AC9: =AVERAGE(AA9:AB9) -> 0.78752707 | AD9: =AVERAGE(AA9,X9) -> 0.8175581 | AE9: =AVERAGE(AB9,Y9) -> 0.74577471
B10: New HQ v3 | C10: ='OAI RAG NHQ v3'!I132 -> 4.5844231 | E10: ='Gemini RAG NHQ v3'!I131 -> 4.0421705 | M10: Raw Total | N10: =AVERAGE(D22,J22,P22,V22,AB22,AH22) -> 20.647692 | O10: =AVERAGE(D40,J40,P40) -> 15.59641 | P10: =AVERAGE(N10:O10) -> 18.122051 | Q10: =AVERAGE(D31,J31,P31,V31,AB31,AH31) -> 18.996863 | R10: =AVERAGE(D49,J49,P49) -> 18.189744 | S10: =AVERAGE(Q10:R10) -> 18.593304 | T10: =AVERAGE(Q10,N10) -> 19.822278 | U10: =AVERAGE(R10,O10) -> 16.893077 | W10: Raw Total | X10: =AVERAGE(F22,L22,R22,X22,AD22,AJ22) -> 3.6712839 | Y10: =AVERAGE(F40,L40,R40) -> 3.1250289 | Z10: =AVERAGE(X10:Y10) -> 3.3981564 | AA10: =AVERAGE(F31,L31,R31,X31,AD31,AJ31) -> 3.241983 | AB10: =AVERAGE(F49,L49,R49) -> 2.9212235 | AC10: =AVERAGE(AA10:AB10) -> 3.0816032 | AD10: =AVERAGE(AA10,X10) -> 3.4566334 | AE10: =AVERAGE(AB10,Y10) -> 3.0231262
B11: TOTAL AVG | C11: =AVERAGE(C5:C10) -> 4.1847115 | D11: =AVERAGE(D5:D10) -> 3.2572436 | E11: =AVERAGE(E5:E10) -> 3.7622658 | F11: =AVERAGE(F5:F10) -> 3.7066667
B12: gemini vs openai | C12: =(C11-E11)/C11 -> 0.1009498 | D12: =(D11-F11)/D11 -> -0.1379765 | E12: =(E11-C11)/C11 -> -0.1009498 | F12: =(F11-D11)/D11 -> 0.1379765
B15: Gifts & Entertainment: OpenAI RAG Performance | H15: IT-Governance: OpenAI RAG Performance | N15: New HQ v0: OpenAI RAG Performance | T15: New HQ v1: OpenAI RAG Performance | Z15: New HQ v2: OpenAI RAG Performance | AF15: New HQ v3: OpenAI RAG Performance
B16: Metric | C16: Min | D16: AVG | E16: Max | F16: StdDev | H16: Metric | I16: Min | J16: AVG | K16: Max | L16: StdDev | N16: Metric | O16: Min | P16: AVG | Q16: Max | R16: StdDev | T16: Metric | U16: Min | V16: AVG | W16: Max | X16: StdDev | Z16: Metric | AA16: Min | AB16: AVG | AC16: Max | AD16: StdDev | AF16: Metric | AG16: Min | AH16: AVG | AI16: Max | AJ16: StdDev
B17: Factual Acc | C17: =MIN('OAI RAG G+E'!D:D) -> 3 | D17: =AVERAGE('OAI RAG G+E'!D:D) -> 4.36 | E17: =MAX('OAI RAG G+E'!D:D) -> 5 | F17: =_xlfn.STDEV.S('OAI RAG G+E'!D2:D26) -> 0.56862407 | H17: Factual Acc | I17: =MIN('OAI RAG IT-G'!D:D) -> 3 | J17: =AVERAGE('OAI RAG IT-G'!D:D) -> 4.28 | K17: =MAX('OAI RAG IT-G'!D:D) -> 5 | L17: =_xlfn.STDEV.S('OAI RAG IT-G'!D2:D26) -> 0.61373175 | N17: Factual Acc | O17: =MIN('OAI RAG NHQ v0'!D:D) -> 1 | P17: =AVERAGE('OAI RAG NHQ v0'!D:D) -> 3.6846154 | Q17: =MAX('OAI RAG NHQ v0'!D:D) -> 5 | R17: =_xlfn.STDEV.S('OAI RAG NHQ v0'!D2:D131) -> 1.4575897 | T17: Factual Acc | U17: =MIN('OAI RAG NHQ v1'!D:D) -> 1 | V17: =AVERAGE('OAI RAG NHQ v1'!D:D) -> 4.2769231 | W17: =MAX('OAI RAG NHQ v1'!D:D) -> 5 | X17: =_xlfn.STDEV.S('OAI RAG NHQ v1'!D2:D131) -> 1.0039873 | Z17: Factual Acc | AA17: =MIN('OAI RAG NHQ v2'!D:D) -> 1 | AB17: =AVERAGE('OAI RAG NHQ v2'!D:D) -> 4.1384615 | AC17: =MAX('OAI RAG NHQ v2'!D:D) -> 5 | AD17: =_xlfn.STDEV.S('OAI RAG NHQ v2'!D2:D131) -> 1.1049841 | AF17: Factual Acc | AG17: =MIN('OAI RAG NHQ v3'!D:D) -> 1 | AH17: =AVERAGE('OAI RAG NHQ v3'!D:D) -> 4.7 | AI17: =MAX('OAI RAG NHQ v3'!D:D) -> 5 | AJ17: =_xlfn.STDEV.S('OAI RAG NHQ v3'!D2:D131) -> 0.76401632
B18: Relevance | C18: =MIN('OAI RAG G+E'!E:E) -> 4 | D18: =AVERAGE('OAI RAG G+E'!E:E) -> 4.96 | E18: =MAX('OAI RAG G+E'!E:E) -> 5 | F18: =_xlfn.STDEV.S('OAI RAG G+E'!E2:E26) -> 0.2 | H18: Relevance | I18: =MIN('OAI RAG IT-G'!E:E) -> 3 | J18: =AVERAGE('OAI RAG IT-G'!E:E) -> 4.88 | K18: =MAX('OAI RAG IT-G'!E:E) -> 5 | L18: =_xlfn.STDEV.S('OAI RAG IT-G'!E2:E26) -> 0.43969687 | N18: Relevance | O18: =MIN('OAI RAG NHQ v0'!E:E) -> 1 | P18: =AVERAGE('OAI RAG NHQ v0'!E:E) -> 4.2461538 | Q18: =MAX('OAI RAG NHQ v0'!E:E) -> 5 | R18: =_xlfn.STDEV.S('OAI RAG NHQ v0'!E2:E131) -> 1.3414185 | T18: Relevance | U18: =MIN('OAI RAG NHQ v1'!E:E) -> 1 | V18: =AVERAGE('OAI RAG NHQ v1'!E:E) -> 4.7076923 | W18: =MAX('OAI RAG NHQ v1'!E:E) -> 5 | X18: =_xlfn.STDEV.S('OAI RAG NHQ v1'!E2:E131) -> 0.76194522 | Z18: Relevance | AA18: =MIN('OAI RAG NHQ v2'!E:E) -> 1 | AB18: =AVERAGE('OAI RAG NHQ v2'!E:E) -> 4.6076923 | AC18: =MAX('OAI RAG NHQ v2'!E:E) -> 5 | AD18: =_xlfn.STDEV.S('OAI RAG NHQ v2'!E2:E131) -> 0.96846521 | AF18: Relevance | AG18: =MIN('OAI RAG NHQ v3'!E:E) -> 1 | AH18: =AVERAGE('OAI RAG NHQ v3'!E:E) -> 4.8615385 | AI18: =MAX('OAI RAG NHQ v3'!E:E) -> 5 | AJ18: =_xlfn.STDEV.S('OAI RAG NHQ v3'!E2:E131) -> 0.63188958
B19: Completeness | C19: =MIN('OAI RAG G+E'!F:F) -> 3 | D19: =AVERAGE('OAI RAG G+E'!F:F) -> 4.28 | E19: =MAX('OAI RAG G+E'!F:F) -> 5 | F19: =_xlfn.STDEV.S('OAI RAG G+E'!F2:F26) -> 0.54160256 | H19: Completeness | I19: =MIN('OAI RAG IT-G'!F:F) -> 2 | J19: =AVERAGE('OAI RAG IT-G'!F:F) -> 4.12 | K19: =MAX('OAI RAG IT-G'!F:F) -> 5 | L19: =_xlfn.STDEV.S('OAI RAG IT-G'!F2:F26) -> 0.66583281 | N19: Completeness | O19: =MIN('OAI RAG NHQ v0'!F:F) -> 1 | P19: =AVERAGE('OAI RAG NHQ v0'!F:F) -> 3.2692308 | Q19: =MAX('OAI RAG NHQ v0'!F:F) -> 5 | R19: =_xlfn.STDEV.S('OAI RAG NHQ v0'!F2:F131) -> 1.2313002 | T19: Completeness | U19: =MIN('OAI RAG NHQ v1'!F:F) -> 1 | V19: =AVERAGE('OAI RAG NHQ v1'!F:F) -> 3.7923077 | W19: =MAX('OAI RAG NHQ v1'!F:F) -> 5 | X19: =_xlfn.STDEV.S('OAI RAG NHQ v1'!F2:F131) -> 0.85992747 | Z19: Completeness | AA19: =MIN('OAI RAG NHQ v2'!F:F) -> 1 | AB19: =AVERAGE('OAI RAG NHQ v2'!F:F) -> 3.7307692 | AC19: =MAX('OAI RAG NHQ v2'!F:F) -> 5 | AD19: =_xlfn.STDEV.S('OAI RAG NHQ v2'!F2:F131) -> 1.0175854 | AF19: Completeness | AG19: =MIN('OAI RAG NHQ v3'!F:F) -> 1 | AH19: =AVERAGE('OAI RAG NHQ v3'!F:F) -> 4.1307692 | AI19: =MAX('OAI RAG NHQ v3'!F:F) -> 5 | AJ19: =_xlfn.STDEV.S('OAI RAG NHQ v3'!F2:F131) -> 0.78145622
B20: Clarity | C20: =MIN('OAI RAG G+E'!G:G) -> 4 | D20: =AVERAGE('OAI RAG G+E'!G:G) -> 4.44 | E20: =MAX('OAI RAG G+E'!G:G) -> 5 | F20: =_xlfn.STDEV.S('OAI RAG G+E'!G2:G26) -> 0.50662281 | H20: Clarity | I20: =MIN('OAI RAG IT-G'!G:G) -> 4 | J20: =AVERAGE('OAI RAG IT-G'!G:G) -> 4.4 | K20: =MAX('OAI RAG IT-G'!G:G) -> 5 | L20: =_xlfn.STDEV.S('OAI RAG IT-G'!G2:G26) -> 0.5 | N20: Clarity | O20: =MIN('OAI RAG NHQ v0'!G:G) -> 2 | P20: =AVERAGE('OAI RAG NHQ v0'!G:G) -> 4.3538462 | Q20: =MAX('OAI RAG NHQ v0'!G:G) -> 5 | R20: =_xlfn.STDEV.S('OAI RAG NHQ v0'!G2:G131) -> 0.95529157 | T20: Clarity | U20: =MIN('OAI RAG NHQ v1'!G:G) -> 1 | V20: =AVERAGE('OAI RAG NHQ v1'!G:G) -> 4.6230769 | W20: =MAX('OAI RAG NHQ v1'!G:G) -> 5 | X20: =_xlfn.STDEV.S('OAI RAG NHQ v1'!G2:G131) -> 0.66198415 | Z20: Clarity | AA20: =MIN('OAI RAG NHQ v2'!G:G) -> 2 | AB20: =AVERAGE('OAI RAG NHQ v2'!G:G) -> 4.5076923 | AC20: =MAX('OAI RAG NHQ v2'!G:G) -> 5 | AD20: =_xlfn.STDEV.S('OAI RAG NHQ v2'!G2:G131) -> 0.75990772 | AF20: Clarity | AG20: =MIN('OAI RAG NHQ v3'!G:G) -> 2 | AH20: =AVERAGE('OAI RAG NHQ v3'!G:G) -> 4.8153846 | AI20: =MAX('OAI RAG NHQ v3'!G:G) -> 5 | AJ20: =_xlfn.STDEV.S('OAI RAG NHQ v3'!G2:G131) -> 0.53966133
B21: Citation Q. | C21: =MIN('OAI RAG G+E'!H:H) -> 2 | D21: =AVERAGE('OAI RAG G+E'!H:H) -> 3.32 | E21: =MAX('OAI RAG G+E'!H:H) -> 4 | F21: =_xlfn.STDEV.S('OAI RAG G+E'!H2:H26) -> 0.62716292 | H21: Citation Q. | I21: =MIN('OAI RAG IT-G'!H:H) -> 2 | J21: =AVERAGE('OAI RAG IT-G'!H:H) -> 3.2 | K21: =MAX('OAI RAG IT-G'!H:H) -> 4 | L21: =_xlfn.STDEV.S('OAI RAG IT-G'!H2:H26) -> 0.64549722 | N21: Citation Q. | O21: =MIN('OAI RAG NHQ v0'!H:H) -> 1 | P21: =AVERAGE('OAI RAG NHQ v0'!H:H) -> 2.8384615 | Q21: =MAX('OAI RAG NHQ v0'!H:H) -> 5 | R21: =_xlfn.STDEV.S('OAI RAG NHQ v0'!H2:H131) -> 1.2563257 | T21: Citation Q. | U21: =MIN('OAI RAG NHQ v1'!H:H) -> 1 | V21: =AVERAGE('OAI RAG NHQ v1'!H:H) -> 3.2307692 | W21: =MAX('OAI RAG NHQ v1'!H:H) -> 5 | X21: =_xlfn.STDEV.S('OAI RAG NHQ v1'!H2:H131) -> 0.92793395 | Z21: Citation Q. | AA21: =MIN('OAI RAG NHQ v2'!H:H) -> 1 | AB21: =AVERAGE('OAI RAG NHQ v2'!H:H) -> 3.2076923 | AC21: =MAX('OAI RAG NHQ v2'!H:H) -> 5 | AD21: =_xlfn.STDEV.S('OAI RAG NHQ v2'!H2:H131) -> 1.0761412 | AF21: Citation Q. | AG21: =MIN('OAI RAG NHQ v3'!H:H) -> 1 | AH21: =AVERAGE('OAI RAG NHQ v3'!H:H) -> 3.9230769 | AI21: =MAX('OAI RAG NHQ v3'!H:H) -> 5 | AJ21: =_xlfn.STDEV.S('OAI RAG NHQ v3'!H2:H131) -> 0.96138937
B22: Overall Score | C22: =MIN('OAI RAG G+E'!J:J) -> 16 | D22: =AVERAGE('OAI RAG G+E'!J:J) -> 21.36 | E22: =MAX('OAI RAG G+E'!J:J) -> 24 | F22: =_xlfn.STDEV.S('OAI RAG G+E'!J2:J26) -> 2.0792627 | H22: Overall Score | I22: =MIN('OAI RAG IT-G'!J:J) -> 15 | J22: =AVERAGE('OAI RAG IT-G'!J:J) -> 20.88 | K22: =MAX('OAI RAG IT-G'!J:J) -> 24 | L22: =_xlfn.STDEV.S('OAI RAG IT-G'!J2:J26) -> 2.2420229 | N22: Overall Score | O22: =MIN('OAI RAG NHQ v0'!J:J) -> 6 | P22: =AVERAGE('OAI RAG NHQ v0'!J:J) -> 18.392308 | Q22: =MAX('OAI RAG NHQ v0'!J:J) -> 25 | R22: =_xlfn.STDEV.S('OAI RAG NHQ v0'!J2:J131) -> 5.8832256 | T22: Overall Score | U22: =MIN('OAI RAG NHQ v1'!J:J) -> 5 | V22: =AVERAGE('OAI RAG NHQ v1'!J:J) -> 20.630769 | W22: =MAX('OAI RAG NHQ v1'!J:J) -> 25 | X22: =_xlfn.STDEV.S('OAI RAG NHQ v1'!J2:J131) -> 3.9140741 | Z22: Overall Score | AA22: =MIN('OAI RAG NHQ v2'!J:J) -> 6 | AB22: =AVERAGE('OAI RAG NHQ v2'!J:J) -> 20.192308 | AC22: =MAX('OAI RAG NHQ v2'!J:J) -> 25 | AD22: =_xlfn.STDEV.S('OAI RAG NHQ v2'!J2:J131) -> 4.6055177 | AF22: Overall Score | AG22: =MIN('OAI RAG NHQ v3'!J:J) -> 6 | AH22: =AVERAGE('OAI RAG NHQ v3'!J:J) -> 22.430769 | AI22: =MAX('OAI RAG NHQ v3'!J:J) -> 25 | AJ22: =_xlfn.STDEV.S('OAI RAG NHQ v3'!J2:J131) -> 3.3036002
B24: Gifts & Entertainment: Gemini RAG Performance | H24: IT-Governance: Gemini RAG Performance | N24: New HQ v0: Gemini RAG Performance | T24: New HQ v1: Gemini RAG Performance | Z24: New HQ v2: Gemini RAG Performance | AF24: New HQ v3: Gemini RAG Performance
B25: Metric | C25: Min | D25: AVG | E25: Max | F25: StdDev | H25: Metric | I25: Min | J25: AVG | K25: Max | L25: StdDev | N25: Metric | O25: Min | P25: AVG | Q25: Max | R25: StdDev | T25: Metric | U25: Min | V25: AVG | W25: Max | X25: StdDev | Z25: Metric | AA25: Min | AB25: AVG | AC25: Max | AD25: StdDev | AF25: Metric | AG25: Min | AH25: AVG | AI25: Max | AJ25: StdDev
B26: Factual Acc | C26: =MIN('Gemini RAG G+E'!D:D) -> 4 | D26: =AVERAGE('Gemini RAG G+E'!D:D) -> 4.48 | E26: =MAX('Gemini RAG G+E'!D:D) -> 5 | F26: =_xlfn.STDEV.S('Gemini RAG G+E'!D2:D26) -> 0.50990195 | H26: Factual Acc | I26: =MIN('Gemini RAG IT-G'!D:D) -> 2 | J26: =AVERAGE('Gemini RAG IT-G'!D:D) -> 4.2 | K26: =MAX('Gemini RAG IT-G'!D:D) -> 5 | L26: =_xlfn.STDEV.S('Gemini RAG IT-G'!D2:D26) -> 0.70710678 | N26: Factual Acc | O26: =MIN('Gemini RAG NHQ v0'!D:D) -> 1 | P26: =AVERAGE('Gemini RAG NHQ v0'!D:D) -> 4.2307692 | Q26: =MAX('Gemini RAG NHQ v0'!D:D) -> 5 | R26: =_xlfn.STDEV.S('Gemini RAG NHQ v0'!D2:D131) -> 1.1782161 | T26: Factual Acc | U26: =MIN('Gemini RAG NHQ v1'!D:D) -> 1 | V26: =AVERAGE('Gemini RAG NHQ v1'!D:D) -> 4.4108527 | W26: =MAX('Gemini RAG NHQ v1'!D:D) -> 5 | X26: =_xlfn.STDEV.S('Gemini RAG NHQ v1'!D2:D130) -> 0.83490646 | Z26: Factual Acc | AA26: =MIN('Gemini RAG NHQ v2'!D:D) -> 1 | AB26: =AVERAGE('Gemini RAG NHQ v2'!D:D) -> 4.4230769 | AC26: =MAX('Gemini RAG NHQ v2'!D:D) -> 5 | AD26: =_xlfn.STDEV.S('Gemini RAG NHQ v2'!D2:D131) -> 0.89672431 | AF26: Factual Acc | AG26: =MIN('Gemini RAG NHQ v3'!D:D) -> 1 | AH26: =AVERAGE('Gemini RAG NHQ v3'!D:D) -> 4.7751938 | AI26: =MAX('Gemini RAG NHQ v3'!D:D) -> 5 | AJ26: =_xlfn.STDEV.S('Gemini RAG NHQ v3'!D2:D130) -> 0.5623654
B27: Relevance | C27: =MIN('Gemini RAG G+E'!E:E) -> 4 | D27: =AVERAGE('Gemini RAG G+E'!E:E) -> 4.96 | E27: =MAX('Gemini RAG G+E'!E:E) -> 5 | F27: =_xlfn.STDEV.S('Gemini RAG G+E'!E2:E26) -> 0.2 | H27: Relevance | I27: =MIN('Gemini RAG IT-G'!E:E) -> 1 | J27: =AVERAGE('Gemini RAG IT-G'!E:E) -> 4.72 | K27: =MAX('Gemini RAG IT-G'!E:E) -> 5 | L27: =_xlfn.STDEV.S('Gemini RAG IT-G'!E2:E26) -> 0.84261498 | N27: Relevance | O27: =MIN('Gemini RAG NHQ v0'!E:E) -> 1 | P27: =AVERAGE('Gemini RAG NHQ v0'!E:E) -> 4.2461538 | Q27: =MAX('Gemini RAG NHQ v0'!E:E) -> 5 | R27: =_xlfn.STDEV.S('Gemini RAG NHQ v0'!E2:E131) -> 1.4200204 | T27: Relevance | U27: =MIN('Gemini RAG NHQ v1'!E:E) -> 1 | V27: =AVERAGE('Gemini RAG NHQ v1'!E:E) -> 4.6356589 | W27: =MAX('Gemini RAG NHQ v1'!E:E) -> 5 | X27: =_xlfn.STDEV.S('Gemini RAG NHQ v1'!E2:E130) -> 0.85639127 | Z27: Relevance | AA27: =MIN('Gemini RAG NHQ v2'!E:E) -> 1 | AB27: =AVERAGE('Gemini RAG NHQ v2'!E:E) -> 4.6 | AC27: =MAX('Gemini RAG NHQ v2'!E:E) -> 5 | AD27: =_xlfn.STDEV.S('Gemini RAG NHQ v2'!E2:E131) -> 0.97726085 | AF27: Relevance | AG27: =MIN('Gemini RAG NHQ v3'!E:E) -> 1 | AH27: =AVERAGE('Gemini RAG NHQ v3'!E:E) -> 4.8449612 | AI27: =MAX('Gemini RAG NHQ v3'!E:E) -> 5 | AJ27: =_xlfn.STDEV.S('Gemini RAG NHQ v3'!E2:E130) -> 0.65490472
B28: Completeness | C28: =MIN('Gemini RAG G+E'!F:F) -> 3 | D28: =AVERAGE('Gemini RAG G+E'!F:F) -> 4.2 | E28: =MAX('Gemini RAG G+E'!F:F) -> 5 | F28: =_xlfn.STDEV.S('Gemini RAG G+E'!F2:F26) -> 0.5 | H28: Completeness | I28: =MIN('Gemini RAG IT-G'!F:F) -> 1 | J28: =AVERAGE('Gemini RAG IT-G'!F:F) -> 3.76 | K28: =MAX('Gemini RAG IT-G'!F:F) -> 5 | L28: =_xlfn.STDEV.S('Gemini RAG IT-G'!F2:F26) -> 0.83066239 | N28: Completeness | O28: =MIN('Gemini RAG NHQ v0'!F:F) -> 1 | P28: =AVERAGE('Gemini RAG NHQ v0'!F:F) -> 3.5384615 | Q28: =MAX('Gemini RAG NHQ v0'!F:F) -> 5 | R28: =_xlfn.STDEV.S('Gemini RAG NHQ v0'!F2:F131) -> 1.3985255 | T28: Completeness | U28: =MIN('Gemini RAG NHQ v1'!F:F) -> 1 | V28: =AVERAGE('Gemini RAG NHQ v1'!F:F) -> 3.7984496 | W28: =MAX('Gemini RAG NHQ v1'!F:F) -> 5 | X28: =_xlfn.STDEV.S('Gemini RAG NHQ v1'!F2:F130) -> 0.97130586 | Z28: Completeness | AA28: =MIN('Gemini RAG NHQ v2'!F:F) -> 1 | AB28: =AVERAGE('Gemini RAG NHQ v2'!F:F) -> 3.8538462 | AC28: =MAX('Gemini RAG NHQ v2'!F:F) -> 5 | AD28: =_xlfn.STDEV.S('Gemini RAG NHQ v2'!F2:F131) -> 1.1214024 | AF28: Completeness | AG28: =MIN('Gemini RAG NHQ v3'!F:F) -> 1 | AH28: =AVERAGE('Gemini RAG NHQ v3'!F:F) -> 4.2248062 | AI28: =MAX('Gemini RAG NHQ v3'!F:F) -> 5 | AJ28: =_xlfn.STDEV.S('Gemini RAG NHQ v3'!F2:F130) -> 0.86819056
B29: Clarity | C29: =MIN('Gemini RAG G+E'!G:G) -> 4 | D29: =AVERAGE('Gemini RAG G+E'!G:G) -> 4.68 | E29: =MAX('Gemini RAG G+E'!G:G) -> 5 | F29: =_xlfn.STDEV.S('Gemini RAG G+E'!G2:G26) -> 0.47609523 | H29: Clarity | I29: =MIN('Gemini RAG IT-G'!G:G) -> 3 | J29: =AVERAGE('Gemini RAG IT-G'!G:G) -> 4.4 | K29: =MAX('Gemini RAG IT-G'!G:G) -> 5 | L29: =_xlfn.STDEV.S('Gemini RAG IT-G'!G2:G26) -> 0.57735027 | N29: Clarity | O29: =MIN('Gemini RAG NHQ v0'!G:G) -> 1 | P29: =AVERAGE('Gemini RAG NHQ v0'!G:G) -> 4.4923077 | Q29: =MAX('Gemini RAG NHQ v0'!G:G) -> 5 | R29: =_xlfn.STDEV.S('Gemini RAG NHQ v0'!G2:G131) -> 1.2590519 | T29: Clarity | U29: =MIN('Gemini RAG NHQ v1'!G:G) -> 1 | V29: =AVERAGE('Gemini RAG NHQ v1'!G:G) -> 4.7596899 | W29: =MAX('Gemini RAG NHQ v1'!G:G) -> 5 | X29: =_xlfn.STDEV.S('Gemini RAG NHQ v1'!G2:G130) -> 0.68208314 | Z29: Clarity | AA29: =MIN('Gemini RAG NHQ v2'!G:G) -> 1 | AB29: =AVERAGE('Gemini RAG NHQ v2'!G:G) -> 4.7 | AC29: =MAX('Gemini RAG NHQ v2'!G:G) -> 5 | AD29: =_xlfn.STDEV.S('Gemini RAG NHQ v2'!G2:G131) -> 0.87736392 | AF29: Clarity | AG29: =MIN('Gemini RAG NHQ v3'!G:G) -> 1 | AH29: =AVERAGE('Gemini RAG NHQ v3'!G:G) -> 4.8372093 | AI29: =MAX('Gemini RAG NHQ v3'!G:G) -> 5 | AJ29: =_xlfn.STDEV.S('Gemini RAG NHQ v3'!G2:G130) -> 0.64699664
B30: Citation Q. | C30: =MIN('Gemini RAG G+E'!H:H) -> 1 | D30: =AVERAGE('Gemini RAG G+E'!H:H) -> 1.8 | E30: =MAX('Gemini RAG G+E'!H:H) -> 4 | F30: =_xlfn.STDEV.S('Gemini RAG G+E'!H2:H26) -> 0.95742711 | H30: Citation Q. | I30: =MIN('Gemini RAG IT-G'!H:H) -> 1 | J30: =AVERAGE('Gemini RAG IT-G'!H:H) -> 1.52 | K30: =MAX('Gemini RAG IT-G'!H:H) -> 2 | L30: =_xlfn.STDEV.S('Gemini RAG IT-G'!H2:H26) -> 0.50990195 | N30: Citation Q. | O30: =MIN('Gemini RAG NHQ v0'!H:H) -> 1 | P30: =AVERAGE('Gemini RAG NHQ v0'!H:H) -> 1.1230769 | Q30: =MAX('Gemini RAG NHQ v0'!H:H) -> 5 | R30: =_xlfn.STDEV.S('Gemini RAG NHQ v0'!H2:H131) -> 0.57080637 | T30: Citation Q. | U30: =MIN('Gemini RAG NHQ v1'!H:H) -> 1 | V30: =AVERAGE('Gemini RAG NHQ v1'!H:H) -> 1.0775194 | W30: =MAX('Gemini RAG NHQ v1'!H:H) -> 3 | X30: =_xlfn.STDEV.S('Gemini RAG NHQ v1'!H2:H130) -> 0.3448823 | Z30: Citation Q. | AA30: =MIN('Gemini RAG NHQ v2'!H:H) -> 1 | AB30: =AVERAGE('Gemini RAG NHQ v2'!H:H) -> 1.1 | AC30: =MAX('Gemini RAG NHQ v2'!H:H) -> 5 | AD30: =_xlfn.STDEV.S('Gemini RAG NHQ v2'!H2:H131) -> 0.55475394 | AF30: Citation Q. | AG30: =MIN('Gemini RAG NHQ v3'!H:H) -> 1 | AH30: =AVERAGE('Gemini RAG NHQ v3'!H:H) -> 1.5891473 | AI30: =MAX('Gemini RAG NHQ v3'!H:H) -> 5 | AJ30: =_xlfn.STDEV.S('Gemini RAG NHQ v3'!H2:H130) -> 1.3784752
B31: Overall Score | C31: =MIN('Gemini RAG G+E'!J:J) -> 17 | D31: =AVERAGE('Gemini RAG G+E'!J:J) -> 20.12 | E31: =MAX('Gemini RAG G+E'!J:J) -> 23 | F31: =_xlfn.STDEV.S('Gemini RAG G+E'!J2:J26) -> 1.9 | H31: Overall Score | I31: =MIN('Gemini RAG IT-G'!J:J) -> 8 | J31: =AVERAGE('Gemini RAG IT-G'!J:J) -> 18.6 | K31: =MAX('Gemini RAG IT-G'!J:J) -> 21 | L31: =_xlfn.STDEV.S('Gemini RAG IT-G'!J2:J26) -> 2.7386128 | N31: Overall Score | O31: =MIN('Gemini RAG NHQ v0'!J:J) -> 5 | P31: =AVERAGE('Gemini RAG NHQ v0'!J:J) -> 17.630769 | Q31: =MAX('Gemini RAG NHQ v0'!J:J) -> 25 | R31: =_xlfn.STDEV.S('Gemini RAG NHQ v0'!J2:J131) -> 4.9323147 | T31: Overall Score | U31: =MIN('Gemini RAG NHQ v1'!J:J) -> 5 | V31: =AVERAGE('Gemini RAG NHQ v1'!J:J) -> 18.682171 | W31: =MAX('Gemini RAG NHQ v1'!J:J) -> 23 | X31: =_xlfn.STDEV.S('Gemini RAG NHQ v1'!J2:J130) -> 3.1023794 | Z31: Overall Score | AA31: =MIN('Gemini RAG NHQ v2'!J:J) -> 5 | AB31: =AVERAGE('Gemini RAG NHQ v2'!J:J) -> 18.676923 | AC31: =MAX('Gemini RAG NHQ v2'!J:J) -> 25 | AD31: =_xlfn.STDEV.S('Gemini RAG NHQ v2'!J2:J131) -> 3.7046281 | AF31: Overall Score | AG31: =MIN('Gemini RAG NHQ v3'!J:J) -> 5 | AH31: =AVERAGE('Gemini RAG NHQ v3'!J:J) -> 20.271318 | AI31: =MAX('Gemini RAG NHQ v3'!J:J) -> 25 | AJ31: =_xlfn.STDEV.S('Gemini RAG NHQ v3'!J2:J130) -> 3.0739631
B33: Gifts & Entertainment: OpenAI Agentic Performance | H33: IT-Governance: OpenAI Agentic Performance | N33: New HQ: OpenAI Agentic Performance
B34: Metric | C34: Min | D34: AVG | E34: Max | F34: StdDev | H34: Metric | I34: Min | J34: AVG | K34: Max | L34: StdDev | N34: Metric | O34: Min | P34: AVG | Q34: Max | R34: StdDev
B35: Factual Acc | C35: =MIN('OAI Agentic G+E'!D:D) -> 1 | D35: =AVERAGE('OAI Agentic G+E'!D:D) -> 3.56 | E35: =MAX('OAI Agentic G+E'!D:D) -> 5 | F35: =_xlfn.STDEV.S('OAI RAG G+E'!D2:D26) -> 0.56862407 | H35: Factual Acc | I35: =MIN('OAI Agentic IT-G'!D:D) -> 1 | J35: =AVERAGE('OAI Agentic IT-G'!D:D) -> 3.08 | K35: =MAX('OAI Agentic IT-G'!D:D) -> 4 | L35: =_xlfn.STDEV.S('OAI RAG IT-G'!D2:D26) -> 0.61373175 | N35: Factual Acc | O35: =MIN('OAI Agentic NHQ'!D:D) -> 1 | P35: =AVERAGE('OAI Agentic NHQ'!D:D) -> 2.3384615 | Q35: =MAX('OAI Agentic NHQ'!D:D) -> 5 | R35: =_xlfn.STDEV.S('OAI Agentic NHQ'!D2:D131) -> 1.297307
B36: Relevance | C36: =MIN('OAI Agentic G+E'!E:E) -> 1 | D36: =AVERAGE('OAI Agentic G+E'!E:E) -> 4.52 | E36: =MAX('OAI Agentic G+E'!E:E) -> 5 | F36: =_xlfn.STDEV.S('OAI RAG G+E'!E2:E26) -> 0.2 | H36: Relevance | I36: =MIN('OAI Agentic IT-G'!E:E) -> 1 | J36: =AVERAGE('OAI Agentic IT-G'!E:E) -> 4.08 | K36: =MAX('OAI Agentic IT-G'!E:E) -> 5 | L36: =_xlfn.STDEV.S('OAI RAG IT-G'!E2:E26) -> 0.43969687 | N36: Relevance | O36: =MIN('OAI Agentic NHQ'!E:E) -> 1 | P36: =AVERAGE('OAI Agentic NHQ'!E:E) -> 3.2384615 | Q36: =MAX('OAI Agentic NHQ'!E:E) -> 5 | R36: =_xlfn.STDEV.S('OAI Agentic NHQ'!E2:E131) -> 1.2868075
B37: Completeness | C37: =MIN('OAI Agentic G+E'!F:F) -> 1 | D37: =AVERAGE('OAI Agentic G+E'!F:F) -> 3.32 | E37: =MAX('OAI Agentic G+E'!F:F) -> 4 | F37: =_xlfn.STDEV.S('OAI RAG G+E'!F2:F26) -> 0.54160256 | H37: Completeness | I37: =MIN('OAI Agentic IT-G'!F:F) -> 1 | J37: =AVERAGE('OAI Agentic IT-G'!F:F) -> 3.16 | K37: =MAX('OAI Agentic IT-G'!F:F) -> 4 | L37: =_xlfn.STDEV.S('OAI RAG IT-G'!F2:F26) -> 0.66583281 | N37: Completeness | O37: =MIN('OAI Agentic NHQ'!F:F) -> 1 | P37: =AVERAGE('OAI Agentic NHQ'!F:F) -> 2.2384615 | Q37: =MAX('OAI Agentic NHQ'!F:F) -> 4 | R37: =_xlfn.STDEV.S('OAI Agentic NHQ'!F2:F131) -> 1.1398616
B38: Clarity | C38: =MIN('OAI Agentic G+E'!G:G) -> 2 | D38: =AVERAGE('OAI Agentic G+E'!G:G) -> 4.04 | E38: =MAX('OAI Agentic G+E'!G:G) -> 5 | F38: =_xlfn.STDEV.S('OAI RAG G+E'!G2:G26) -> 0.50662281 | H38: Clarity | I38: =MIN('OAI Agentic IT-G'!G:G) -> 2 | J38: =AVERAGE('OAI Agentic IT-G'!G:G) -> 3.96 | K38: =MAX('OAI Agentic IT-G'!G:G) -> 5 | L38: =_xlfn.STDEV.S('OAI RAG IT-G'!G2:G26) -> 0.5 | N38: Clarity | O38: =MIN('OAI Agentic NHQ'!G:G) -> 2 | P38: =AVERAGE('OAI Agentic NHQ'!G:G) -> 3.4923077 | Q38: =MAX('OAI Agentic NHQ'!G:G) -> 5 | R38: =_xlfn.STDEV.S('OAI Agentic NHQ'!G2:G131) -> 0.88261551
B39: Citation Q. | C39: =MIN('OAI Agentic G+E'!H:H) -> 1 | D39: =AVERAGE('OAI Agentic G+E'!H:H) -> 2.28 | E39: =MAX('OAI Agentic G+E'!H:H) -> 3 | F39: =_xlfn.STDEV.S('OAI RAG G+E'!H2:H26) -> 0.62716292 | H39: Citation Q. | I39: =MIN('OAI Agentic IT-G'!H:H) -> 1 | J39: =AVERAGE('OAI Agentic IT-G'!H:H) -> 1.92 | K39: =MAX('OAI Agentic IT-G'!H:H) -> 3 | L39: =_xlfn.STDEV.S('OAI RAG IT-G'!H2:H26) -> 0.64549722 | N39: Citation Q. | O39: =MIN('OAI Agentic NHQ'!H:H) -> 1 | P39: =AVERAGE('OAI Agentic NHQ'!H:H) -> 1.5615385 | Q39: =MAX('OAI Agentic NHQ'!H:H) -> 3 | R39: =_xlfn.STDEV.S('OAI Agentic NHQ'!H2:H131) -> 0.63494914
B40: Overall Score | C40: =MIN('OAI Agentic G+E'!J:J) -> 6 | D40: =AVERAGE('OAI Agentic G+E'!J:J) -> 17.72 | E40: =MAX('OAI Agentic G+E'!J:J) -> 22 | F40: =_xlfn.STDEV.S('OAI RAG G+E'!J2:J26) -> 2.0792627 | H40: Overall Score | I40: =MIN('OAI Agentic IT-G'!J:J) -> 6 | J40: =AVERAGE('OAI Agentic IT-G'!J:J) -> 16.2 | K40: =MAX('OAI Agentic IT-G'!J:J) -> 20 | L40: =_xlfn.STDEV.S('OAI RAG IT-G'!J2:J26) -> 2.2420229 | N40: Overall Score | O40: =MIN('OAI Agentic NHQ'!J:J) -> 6 | P40: =AVERAGE('OAI Agentic NHQ'!J:J) -> 12.869231 | Q40: =MAX('OAI Agentic NHQ'!J:J) -> 22 | R40: =_xlfn.STDEV.S('OAI Agentic NHQ'!J2:J131) -> 5.0538012
B42: Gifts & Entertainment: Gemini Agentic Performance | H42: IT-Governance: OpenAI Agentic Performance | N42: New HQ: OpenAI Agentic Performance
B43: Metric | C43: Min | D43: AVG | E43: Max | F43: StdDev | H43: Metric | I43: Min | J43: AVG | K43: Max | L43: StdDev | N43: Metric | O43: Min | P43: AVG | Q43: Max | R43: StdDev
B44: Factual Acc | C44: =MIN('Gemini Agentic G+E'!D:D) -> 1 | D44: =AVERAGE('Gemini Agentic G+E'!D:D) -> 3.84 | E44: =MAX('Gemini Agentic G+E'!D:D) -> 5 | F44: =_xlfn.STDEV.S('Gemini RAG G+E'!D2:D26) -> 0.50990195 | H44: Factual Acc | I44: =MIN('Gemini Agentic IT-G'!D:D) -> 1 | J44: =AVERAGE('Gemini Agentic IT-G'!D:D) -> 3.6 | K44: =MAX('Gemini Agentic IT-G'!D:D) -> 5 | L44: =_xlfn.STDEV.S('Gemini RAG IT-G'!D2:D26) -> 0.70710678 | N44: Factual Acc | O44: =MIN('Gemini Agentic NHQ'!D:D) -> 1 | P44: =AVERAGE('Gemini Agentic NHQ'!D:D) -> 3.9615385 | Q44: =MAX('Gemini Agentic NHQ'!D:D) -> 5 | R44: =_xlfn.STDEV.S('Gemini Agentic NHQ'!D2:D131) -> 1.088373
B45: Relevance | C45: =MIN('Gemini Agentic G+E'!E:E) -> 1 | D45: =AVERAGE('Gemini Agentic G+E'!E:E) -> 4.56 | E45: =MAX('Gemini Agentic G+E'!E:E) -> 5 | F45: =_xlfn.STDEV.S('Gemini RAG G+E'!E2:E26) -> 0.2 | H45: Relevance | I45: =MIN('Gemini Agentic IT-G'!E:E) -> 1 | J45: =AVERAGE('Gemini Agentic IT-G'!E:E) -> 4.2 | K45: =MAX('Gemini Agentic IT-G'!E:E) -> 5 | L45: =_xlfn.STDEV.S('Gemini RAG IT-G'!E2:E26) -> 0.84261498 | N45: Relevance | O45: =MIN('Gemini Agentic NHQ'!E:E) -> 1 | P45: =AVERAGE('Gemini Agentic NHQ'!E:E) -> 4.2384615 | Q45: =MAX('Gemini Agentic NHQ'!E:E) -> 5 | R45: =_xlfn.STDEV.S('Gemini Agentic NHQ'!E2:E131) -> 1.1398616
B46: Completeness | C46: =MIN('Gemini Agentic G+E'!F:F) -> 1 | D46: =AVERAGE('Gemini Agentic G+E'!F:F) -> 3.4 | E46: =MAX('Gemini Agentic G+E'!F:F) -> 5 | F46: =_xlfn.STDEV.S('Gemini RAG G+E'!F2:F26) -> 0.5 | H46: Completeness | I46: =MIN('Gemini Agentic IT-G'!F:F) -> 1 | J46: =AVERAGE('Gemini Agentic IT-G'!F:F) -> 3 | K46: =MAX('Gemini Agentic IT-G'!F:F) -> 4 | L46: =_xlfn.STDEV.S('Gemini RAG IT-G'!F2:F26) -> 0.83066239 | N46: Completeness | O46: =MIN('Gemini Agentic NHQ'!F:F) -> 1 | P46: =AVERAGE('Gemini Agentic NHQ'!F:F) -> 3.4846154 | Q46: =MAX('Gemini Agentic NHQ'!F:F) -> 5 | R46: =_xlfn.STDEV.S('Gemini Agentic NHQ'!F2:F131) -> 1.393421
B47: Clarity | C47: =MIN('Gemini Agentic G+E'!G:G) -> 1 | D47: =AVERAGE('Gemini Agentic G+E'!G:G) -> 4.4 | E47: =MAX('Gemini Agentic G+E'!G:G) -> 5 | F47: =_xlfn.STDEV.S('Gemini RAG G+E'!G2:G26) -> 0.47609523 | H47: Clarity | I47: =MIN('Gemini Agentic IT-G'!G:G) -> 1 | J47: =AVERAGE('Gemini Agentic IT-G'!G:G) -> 4.08 | K47: =MAX('Gemini Agentic IT-G'!G:G) -> 5 | L47: =_xlfn.STDEV.S('Gemini RAG IT-G'!G2:G26) -> 0.57735027 | N47: Clarity | O47: =MIN('Gemini Agentic NHQ'!G:G) -> 1 | P47: =AVERAGE('Gemini Agentic NHQ'!G:G) -> 4.7230769 | Q47: =MAX('Gemini Agentic NHQ'!G:G) -> 5 | R47: =_xlfn.STDEV.S('Gemini Agentic NHQ'!G2:G131) -> 0.54296608
B48: Citation Q. | C48: =MIN('Gemini Agentic G+E'!H:H) -> 1 | D48: =AVERAGE('Gemini Agentic G+E'!H:H) -> 2.76 | E48: =MAX('Gemini Agentic G+E'!H:H) -> 4 | F48: =_xlfn.STDEV.S('Gemini RAG G+E'!H2:H26) -> 0.95742711 | H48: Citation Q. | I48: =MIN('Gemini Agentic IT-G'!H:H) -> 1 | J48: =AVERAGE('Gemini Agentic IT-G'!H:H) -> 1.96 | K48: =MAX('Gemini Agentic IT-G'!H:H) -> 4 | L48: =_xlfn.STDEV.S('Gemini RAG IT-G'!H2:H26) -> 0.50990195 | N48: Citation Q. | O48: =MIN('Gemini Agentic NHQ'!H:H) -> 1 | P48: =AVERAGE('Gemini Agentic NHQ'!H:H) -> 2.3615385 | Q48: =MAX('Gemini Agentic NHQ'!H:H) -> 5 | R48: =_xlfn.STDEV.S('Gemini Agentic NHQ'!H2:H131) -> 1.0997099
B49: Overall Score | C49: =MIN('Gemini Agentic G+E'!J:J) -> 5 | D49: =AVERAGE('Gemini Agentic G+E'!J:J) -> 18.96 | E49: =MAX('Gemini Agentic G+E'!J:J) -> 23 | F49: =_xlfn.STDEV.S('Gemini RAG G+E'!J2:J26) -> 1.9 | H49: Overall Score | I49: =MIN('Gemini Agentic IT-G'!J:J) -> 5 | J49: =AVERAGE('Gemini Agentic IT-G'!J:J) -> 16.84 | K49: =MAX('Gemini Agentic IT-G'!J:J) -> 22 | L49: =_xlfn.STDEV.S('Gemini RAG IT-G'!J2:J26) -> 2.7386128 | N49: Overall Score | O49: =MIN('Gemini Agentic NHQ'!J:J) -> 5 | P49: =AVERAGE('Gemini Agentic NHQ'!J:J) -> 18.769231 | Q49: =MAX('Gemini Agentic NHQ'!J:J) -> 25 | R49: =_xlfn.STDEV.S('Gemini Agentic NHQ'!J2:J131) -> 4.1250576
B53: Publication_Table
B54: Dimension | C54: OpenAI Rag M(SD) | D54: OpenAI Agentic M(SD) | E54: Gemini Rag M(SD) | F54: Gemini Agentic M(SD) | G54: RAG p-value | H54: RAG Significance | I54: RAG Cohen's d | J54: RAG Effect | K54: Agentic p-value | L54: Agentic Significance | M54: Agentic Cohen's d | N54: Agentic Effect
B55: Factual Acc | C55: =ROUND(N5,2) & " (" & ROUND(X5,2) & ")" -> 4,24 (0,92) | D55: =ROUND(O5,2) & " (" & ROUND(Y5,2) & ")" -> 2,99 (0,83) | E55: =ROUND(Q5,2) & " (" & ROUND(AA5,2) & ")" -> 4,42 (0,78) | F55: =ROUND(R5,2) & " (" & ROUND(AB5,2) & ")" -> 3,8 (0,77) | G55: =_xlfn.T.TEST('OpenAI RAG RAW'!D:D, 'Gemini RAG RAW'!D:D, 2, 3) -> 8.142714e-05 | H55: =IF(G55<0.001,"***",IF(G55<0.01,"**",IF(G55<0.05,"*","ns"))) -> *** | I55: =ROUND((N5-Q5)/SQRT(((X5^2+AA5^2)/2)),5) -> -0.21101 | J55: =IF(ABS(I55)<0.2,"Negligible", IF(ABS(I55)<0.5,"Small", IF(ABS(I55)<0.8,"Medium","Large"))) -> Small | K55: =_xlfn.T.TEST('OpenAI Agentic RAW'!D:D, 'Gemini Agentic RAW'!D:D, 2, 3) -> 8.7955148e-23 | L55: =IF(K55<0.001,"***",IF(K55<0.01,"**",IF(K55<0.05,"*","ns"))) -> *** | M55: =ROUND((O5-R5)/SQRT(((Y5^2+AB5^2)/2)),5) -> -1.0121 | N55: =IF(ABS(M55)<0.2,"Negligible", IF(ABS(M55)<0.5,"Small", IF(ABS(M55)<0.8,"Medium","Large"))) -> Large
B56: Relevance | C56: =ROUND(N6,2) & " (" & ROUND(X6,2) & ")" -> 4,71 (0,72) | D56: =ROUND(O6,2) & " (" & ROUND(Y6,2) & ")" -> 3,95 (0,64) | E56: =ROUND(Q6,2) & " (" & ROUND(AA6,2) & ")" -> 4,67 (0,83) | F56: =ROUND(R6,2) & " (" & ROUND(AB6,2) & ")" -> 4,33 (0,73) | G56: =_xlfn.T.TEST('OpenAI RAG RAW'!E:E, 'Gemini RAG RAW'!E:E, 2, 3) -> 0.61278097 | H56: =IF(G56<0.001,"***",IF(G56<0.01,"**",IF(G56<0.05,"*","ns"))) -> ns | I56: =ROUND((N6-Q6)/SQRT(((X6^2+AA6^2)/2)),5) -> 0.05503 | J56: =IF(ABS(I56)<0.2,"Negligible", IF(ABS(I56)<0.5,"Small", IF(ABS(I56)<0.8,"Medium","Large"))) -> Negligible | K56: =_xlfn.T.TEST('OpenAI Agentic RAW'!E:E, 'Gemini Agentic RAW'!E:E, 2, 3) -> 7.0612721e-09 | L56: =IF(K56<0.001,"***",IF(K56<0.01,"**",IF(K56<0.05,"*","ns"))) -> *** | M56: =ROUND((O6-R6)/SQRT(((Y6^2+AB6^2)/2)),5) -> -0.56352 | N56: =IF(ABS(M56)<0.2,"Negligible", IF(ABS(M56)<0.5,"Small", IF(ABS(M56)<0.8,"Medium","Large"))) -> Medium
B57: Completeness | C57: =ROUND(N7,2) & " (" & ROUND(X7,2) & ")" -> 3,89 (0,85) | D57: =ROUND(O7,2) & " (" & ROUND(Y7,2) & ")" -> 2,91 (0,78) | E57: =ROUND(Q7,2) & " (" & ROUND(AA7,2) & ")" -> 3,9 (0,95) | F57: =ROUND(R7,2) & " (" & ROUND(AB7,2) & ")" -> 3,29 (0,91) | G57: =_xlfn.T.TEST('OpenAI RAG RAW'!F:F, 'Gemini RAG RAW'!F:F, 2, 3) -> 0.14019173 | H57: =IF(G57<0.001,"***",IF(G57<0.01,"**",IF(G57<0.05,"*","ns"))) -> ns | I57: =ROUND((N7-Q7)/SQRT(((X7^2+AA7^2)/2)),5) -> -0.00972 | J57: =IF(ABS(I57)<0.2,"Negligible", IF(ABS(I57)<0.5,"Small", IF(ABS(I57)<0.8,"Medium","Large"))) -> Negligible | K57: =_xlfn.T.TEST('OpenAI Agentic RAW'!F:F, 'Gemini Agentic RAW'!F:F, 2, 3) -> 2.2086632e-11 | L57: =IF(K57<0.001,"***",IF(K57<0.01,"**",IF(K57<0.05,"*","ns"))) -> *** | M57: =ROUND((O7-R7)/SQRT(((Y7^2+AB7^2)/2)),5) -> -0.45863 | N57: =IF(ABS(M57)<0.2,"Negligible", IF(ABS(M57)<0.5,"Small", IF(ABS(M57)<0.8,"Medium","Large"))) -> Small
B58: Clarity | C58: =ROUND(N8,2) & " (" & ROUND(X8,2) & ")" -> 4,52 (0,65) | D58: =ROUND(O8,2) & " (" & ROUND(Y8,2) & ")" -> 3,83 (0,63) | E58: =ROUND(Q8,2) & " (" & ROUND(AA8,2) & ")" -> 4,64 (0,75) | F58: =ROUND(R8,2) & " (" & ROUND(AB8,2) & ")" -> 4,4 (0,53) | G58: =_xlfn.T.TEST('OpenAI RAG RAW'!G:G, 'Gemini RAG RAW'!G:G, 2, 3) -> 0.01199091 | H58: =IF(G58<0.001,"***",IF(G58<0.01,"**",IF(G58<0.05,"*","ns"))) -> * | I58: =ROUND((N8-Q8)/SQRT(((X8^2+AA8^2)/2)),5) -> -0.17232 | J58: =IF(ABS(I58)<0.2,"Negligible", IF(ABS(I58)<0.5,"Small", IF(ABS(I58)<0.8,"Medium","Large"))) -> Negligible | K58: =_xlfn.T.TEST('OpenAI Agentic RAW'!G:G, 'Gemini Agentic RAW'!G:G, 2, 3) -> 8.5249249e-27 | L58: =IF(K58<0.001,"***",IF(K58<0.01,"**",IF(K58<0.05,"*","ns"))) -> *** | M58: =ROUND((O8-R8)/SQRT(((Y8^2+AB8^2)/2)),5) -> -0.97816 | N58: =IF(ABS(M58)<0.2,"Negligible", IF(ABS(M58)<0.5,"Small", IF(ABS(M58)<0.8,"Medium","Large"))) -> Large
B59: Citation Q. | C59: =ROUND(N9,2) & " (" & ROUND(X9,2) & ")" -> 3,29 (0,92) | D59: =ROUND(O9,2) & " (" & ROUND(Y9,2) & ")" -> 1,92 (0,64) | E59: =ROUND(Q9,2) & " (" & ROUND(AA9,2) & ")" -> 1,37 (0,72) | F59: =ROUND(R9,2) & " (" & ROUND(AB9,2) & ")" -> 2,36 (0,86) | G59: =_xlfn.T.TEST('OpenAI RAG RAW'!H:H, 'Gemini RAG RAW'!H:H, 2, 3) -> 1.6346823e-180 | H59: =IF(G59<0.001,"***",IF(G59<0.01,"**",IF(G59<0.05,"*","ns"))) -> *** | I59: =ROUND((N9-Q9)/SQRT(((X9^2+AA9^2)/2)),5) -> 2.32973 | J59: =IF(ABS(I59)<0.2,"Negligible", IF(ABS(I59)<0.5,"Small", IF(ABS(I59)<0.8,"Medium","Large"))) -> Large | K59: =_xlfn.T.TEST('OpenAI Agentic RAW'!H:H, 'Gemini Agentic RAW'!H:H, 2, 3) -> 1.1209866e-11 | L59: =IF(K59<0.001,"***",IF(K59<0.01,"**",IF(K59<0.05,"*","ns"))) -> *** | M59: =ROUND((O9-R9)/SQRT(((Y9^2+AB9^2)/2)),5) -> -0.58369 | N59: =IF(ABS(M59)<0.2,"Negligible", IF(ABS(M59)<0.5,"Small", IF(ABS(M59)<0.8,"Medium","Large"))) -> Medium
B60: Overall Score | C60: =ROUND(N10,2) & " (" & ROUND(X10,2) & ")" -> 20,65 (3,67) | D60: =ROUND(O10,2) & " (" & ROUND(Y10,2) & ")" -> 15,6 (3,13) | E60: =ROUND(Q10,2) & " (" & ROUND(AA10,2) & ")" -> 19 (3,24) | F60: =ROUND(R10,2) & " (" & ROUND(AB10,2) & ")" -> 18,19 (2,92) | G60: =_xlfn.T.TEST('OpenAI RAG RAW'!J:J, 'Gemini RAG RAW'!J:J, 2, 3) -> 1.3752521e-10 | H60: =IF(G60<0.001,"***",IF(G60<0.01,"**",IF(G60<0.05,"*","ns"))) -> *** | I60: =ROUND((N10-Q10)/SQRT(((X10^2+AA10^2)/2)),5) -> 0.47666 | J60: =IF(ABS(I60)<0.2,"Negligible", IF(ABS(I60)<0.5,"Small", IF(ABS(I60)<0.8,"Medium","Large"))) -> Small | K60: =_xlfn.T.TEST('OpenAI Agentic RAW'!J:J, 'Gemini Agentic RAW'!J:J, 2, 3) -> 6.6495553e-19 | L60: =IF(K60<0.001,"***",IF(K60<0.01,"**",IF(K60<0.05,"*","ns"))) -> *** | M60: =ROUND((O10-R10)/SQRT(((Y10^2+AB10^2)/2)),5) -> -0.85734 | N60: =IF(ABS(M60)<0.2,"Negligible", IF(ABS(M60)<0.5,"Small", IF(ABS(M60)<0.8,"Medium","Large"))) -> Large
B62: OpenAI vs. Gemini | H62: RAG vs. Agentic | N62: Inter-judge reliability: Correlation between OpenAI vs. Gemini
B63: Dimension | C63: p-value | D63: Significance | E63: Cohen's d | F63: Effect | H63: Dimension | I63: p-value | J63: Significance | K63: Cohen's d | L63: Effect | N63: Dimension | O63: Pearson | P63: Cohen's Kappa (Po) | Q63: OpenAI Score 1 | R63: Gemini Score 1 | S63: Score 1 | T63: Sum PE | U63: Cohen's Kappa | V63: Interpretation
B64: Factual Acc | C64: =_xlfn.T.TEST('OpenAI RAW'!D:D, 'Gemini RAW'!D:D, 2, 3) -> 1.2276919e-15 | D64: =IF(C64<0.001,"***",IF(C64<0.01,"**",IF(C64<0.05,"*","ns"))) -> *** | E64: =ABS(ROUND((P5-S5)/SQRT(((Z5^2+AC5^2)/2)),5)) -> 0.59838 | F64: =IF(ABS(E64)<0.2,"Negligible", IF(ABS(E64)<0.5,"Small", IF(ABS(E64)<0.8,"Medium","Large"))) -> Medium | H64: Factual Acc | I64: =_xlfn.T.TEST('RAG RAW'!D:D, 'Agentic RAW'!D:D, 2, 3) -> 9.8742655e-39 | J64: =IF(I64<0.001,"***",IF(I64<0.01,"**",IF(I64<0.05,"*","ns"))) -> *** | K64: =ABS(ROUND((T5-U5)/SQRT(((AD5^2+AE5^2)/2)),5)) -> 1.13231 | L64: =IF(ABS(K64)<0.2,"Negligible", IF(ABS(K64)<0.5,"Small", IF(ABS(K64)<0.8,"Medium","Large"))) -> Large | N64: Factual Acc | O64: =CORREL('OpenAI RAW'!D:D, 'Gemini RAW'!D:D) -> 0.33229261 | P64: {=SUMPRODUCT(('OpenAI RAW'!D2:D10000='Gemini RAW'!D2:D10000)*1)/COUNT('OpenAI RAW'!D2:D10000)} -> 12.784 | Q64: =COUNTIF('OpenAI RAW'!D2:D10000,1)/COUNT('OpenAI RAW'!D2:D10000) -> 0.11866667 | R64: =COUNTIF('Gemini RAW'!D2:D10000,1)/COUNT('Gemini RAW'!D2:D10000) -> 0.037433155 | S64: =Q64*R64 -> 0.0044420677 | T64: =SUM( (COUNTIF('OpenAI RAW'!D2:D10000,1)/COUNT('OpenAI RAW'!D2:D10000))*(COUNTIF('Gemini RAW'!D2:D10000,1)/COUNT('Gemini RAW'!D2:D10000)) + (COUNTIF('OpenAI RAW'!D2:D10000,2)/COUNT('OpenAI RAW'!D2:D10000))*(COUNTIF('Gemini RAW'!D2:D10000,2)/COUNT('Gemini RAW'!D2:D10000)) + (COUNTIF('OpenAI RAW'!D2:D10000,3)/COUNT('OpenAI RAW'!D2:D10000))*(COUNTIF('Gemini RAW'!D2:D10000,3)/COUNT('Gemini RAW'!D2:D10000)) + (COUNTIF('OpenAI RAW'!D2:D10000,4)/COUNT('OpenAI RAW'!D2:D10000))*(COUNTIF('Gemini RAW'!D2:D10000,4)/COUNT('Gemini RAW'!D2:D10000)) + (COUNTIF('OpenAI RAW'!D2:D10000,5)/COUNT('OpenAI RAW'!D2:D10000))*(COUNTIF('Gemini RAW'!D2:D10000,5)/COUNT('Gemini RAW'!D2:D10000)) ) -> 0.33101961 | U64: =(S64-T64)/(1-T64) -> -0.48817207 | V64: =IF(U64<0.2,"Poor", IF(U64<0.4,"Fair", IF(U64<0.6,"Moderate", IF(U64<0.8,"Substantial", "Almost perfect")))) -> Poor
B65: Relevance | C65: =_xlfn.T.TEST('OpenAI RAW'!E:E, 'Gemini RAW'!E:E, 2, 3) -> 0.0057065328 | D65: =IF(C65<0.001,"***",IF(C65<0.01,"**",IF(C65<0.05,"*","ns"))) -> ** | E65: =ABS(ROUND((P6-S6)/SQRT(((Z6^2+AC6^2)/2)),5)) -> 0.2352 | F65: =IF(ABS(E65)<0.2,"Negligible", IF(ABS(E65)<0.5,"Small", IF(ABS(E65)<0.8,"Medium","Large"))) -> Small | H65: Relevance | I65: =_xlfn.T.TEST('RAG RAW'!E:E, 'Agentic RAW'!E:E, 2, 3) -> 2.3029059e-21 | J65: =IF(I65<0.001,"***",IF(I65<0.01,"**",IF(I65<0.05,"*","ns"))) -> *** | K65: =ABS(ROUND((T6-U6)/SQRT(((AD6^2+AE6^2)/2)),5)) -> 0.75187 | L65: =IF(ABS(K65)<0.2,"Negligible", IF(ABS(K65)<0.5,"Small", IF(ABS(K65)<0.8,"Medium","Large"))) -> Medium | N65: Relevance | O65: =CORREL('OpenAI RAW'!E:E, 'Gemini RAW'!E:E) -> 0.37708517 | P65: {=SUMPRODUCT(('OpenAI RAW'!E2:E10000='Gemini RAW'!E2:E10000)*1)/COUNT('OpenAI RAW'!E2:E10000)} -> 12.98 | Q65: =COUNTIF('OpenAI RAW'!E2:E10000,1)/COUNT('OpenAI RAW'!E2:E10000) -> 0.050666667 | R65: =COUNTIF('Gemini RAW'!E2:E10000,1)/COUNT('Gemini RAW'!E2:E10000) -> 0.056149733 | S65: =Q65*R65 -> 0.0028449198 | U65: =(S65-T65)/(1-T65) -> 0.0028449198 | V65: =IF(U65<0.2,"Poor", IF(U65<0.4,"Fair", IF(U65<0.6,"Moderate", IF(U65<0.8,"Substantial", "Almost perfect")))) -> Poor
B66: Completeness | C66: =_xlfn.T.TEST('OpenAI RAW'!F:F, 'Gemini RAW'!F:F, 2, 3) -> 2.9928463e-06 | D66: =IF(C66<0.001,"***",IF(C66<0.01,"**",IF(C66<0.05,"*","ns"))) -> *** | E66: =ABS(ROUND((P7-S7)/SQRT(((Z7^2+AC7^2)/2)),5)) -> 0.22741 | F66: =IF(ABS(E66)<0.2,"Negligible", IF(ABS(E66)<0.5,"Small", IF(ABS(E66)<0.8,"Medium","Large"))) -> Small | H66: Completeness | I66: =_xlfn.T.TEST('RAG RAW'!F:F, 'Agentic RAW'!F:F, 2, 3) -> 5.1196884e-27 | J66: =IF(I66<0.001,"***",IF(I66<0.01,"**",IF(I66<0.05,"*","ns"))) -> *** | K66: =ABS(ROUND((T7-U7)/SQRT(((AD7^2+AE7^2)/2)),5)) -> 0.90662 | L66: =IF(ABS(K66)<0.2,"Negligible", IF(ABS(K66)<0.5,"Small", IF(ABS(K66)<0.8,"Medium","Large"))) -> Large | N66: Completeness | O66: =CORREL('OpenAI RAW'!F:F, 'Gemini RAW'!F:F) -> 0.28034312 | P66: {=SUMPRODUCT(('OpenAI RAW'!F2:F10000='Gemini RAW'!F2:F10000)*1)/COUNT('OpenAI RAW'!F2:F10000)} -> 12.729333 | Q66: =COUNTIF('OpenAI RAW'!F2:F10000,1)/COUNT('OpenAI RAW'!F2:F10000) -> 0.11866667 | R66: =COUNTIF('Gemini RAW'!F2:F10000,1)/COUNT('Gemini RAW'!F2:F10000) -> 0.077540107 | S66: =Q66*R66 -> 0.009201426 | U66: =(S66-T66)/(1-T66) -> 0.009201426 | V66: =IF(U66<0.2,"Poor", IF(U66<0.4,"Fair", IF(U66<0.6,"Moderate", IF(U66<0.8,"Substantial", "Almost perfect")))) -> Poor
B67: Clarity | C67: =_xlfn.T.TEST('OpenAI RAW'!G:G, 'Gemini RAW'!G:G, 2, 3) -> 4.7929644e-13 | D67: =IF(C67<0.001,"***",IF(C67<0.01,"**",IF(C67<0.05,"*","ns"))) -> *** | E67: =ABS(ROUND((P8-S8)/SQRT(((Z8^2+AC8^2)/2)),5)) -> 0.53858 | F67: =IF(ABS(E67)<0.2,"Negligible", IF(ABS(E67)<0.5,"Small", IF(ABS(E67)<0.8,"Medium","Large"))) -> Medium | H67: Clarity | I67: =_xlfn.T.TEST('RAG RAW'!G:G, 'Agentic RAW'!G:G, 2, 3) -> 5.8972607e-20 | J67: =IF(I67<0.001,"***",IF(I67<0.01,"**",IF(I67<0.05,"*","ns"))) -> *** | K67: =ABS(ROUND((T8-U8)/SQRT(((AD8^2+AE8^2)/2)),5)) -> 0.72572 | L67: =IF(ABS(K67)<0.2,"Negligible", IF(ABS(K67)<0.5,"Small", IF(ABS(K67)<0.8,"Medium","Large"))) -> Medium | N67: Clarity | O67: =CORREL('OpenAI RAW'!G:G, 'Gemini RAW'!G:G) -> 0.34127715 | P67: {=SUMPRODUCT(('OpenAI RAW'!G2:G10000='Gemini RAW'!G2:G10000)*1)/COUNT('OpenAI RAW'!G2:G10000)} -> 12.868 | Q67: =COUNTIF('OpenAI RAW'!G2:G10000,1)/COUNT('OpenAI RAW'!G2:G10000) -> 0.0013333333 | R67: =COUNTIF('Gemini RAW'!G2:G10000,1)/COUNT('Gemini RAW'!G2:G10000) -> 0.038770053 | S67: =Q67*R67 -> 5.1693405e-05 | U67: =(S67-T67)/(1-T67) -> 5.1693405e-05 | V67: =IF(U67<0.2,"Poor", IF(U67<0.4,"Fair", IF(U67<0.6,"Moderate", IF(U67<0.8,"Substantial", "Almost perfect")))) -> Poor
B68: Citation Q. | C68: =_xlfn.T.TEST('OpenAI RAW'!H:H, 'Gemini RAW'!H:H, 2, 3) -> 3.2890426e-108 | D68: =IF(C68<0.001,"***",IF(C68<0.01,"**",IF(C68<0.05,"*","ns"))) -> *** | E68: =ABS(ROUND((P9-S9)/SQRT(((Z9^2+AC9^2)/2)),5)) -> 0.94563 | F68: =IF(ABS(E68)<0.2,"Negligible", IF(ABS(E68)<0.5,"Small", IF(ABS(E68)<0.8,"Medium","Large"))) -> Large | H68: Citation Q. | I68: =_xlfn.T.TEST('RAG RAW'!H:H, 'Agentic RAW'!H:H, 2, 3) -> 0.00016058943 | J68: =IF(I68<0.001,"***",IF(I68<0.01,"**",IF(I68<0.05,"*","ns"))) -> *** | K68: =ABS(ROUND((T9-U9)/SQRT(((AD9^2+AE9^2)/2)),5)) -> 0.23894 | L68: =IF(ABS(K68)<0.2,"Negligible", IF(ABS(K68)<0.5,"Small", IF(ABS(K68)<0.8,"Medium","Large"))) -> Small | N68: Citation Q. | O68: =CORREL('OpenAI RAW'!H:H, 'Gemini RAW'!H:H) -> -0.23068223 | P68: {=SUMPRODUCT(('OpenAI RAW'!H2:H10000='Gemini RAW'!H2:H10000)*1)/COUNT('OpenAI RAW'!H2:H10000)} -> 12.478667 | Q68: =COUNTIF('OpenAI RAW'!H2:H10000,1)/COUNT('OpenAI RAW'!H2:H10000) -> 0.164 | R68: =COUNTIF('Gemini RAW'!H2:H10000,1)/COUNT('Gemini RAW'!H2:H10000) -> 0.73930481 | S68: =Q68*R68 -> 0.12124599 | U68: =(S68-T68)/(1-T68) -> 0.12124599 | V68: =IF(U68<0.2,"Poor", IF(U68<0.4,"Fair", IF(U68<0.6,"Moderate", IF(U68<0.8,"Substantial", "Almost perfect")))) -> Poor
B69: Overall Score | C69: =_xlfn.T.TEST('OpenAI RAW'!J:J, 'Gemini RAW'!J:J, 2, 3) -> 0.56348757 | D69: =IF(C69<0.001,"***",IF(C69<0.01,"**",IF(C69<0.05,"*","ns"))) -> ns | E69: =ABS(ROUND((P10-S10)/SQRT(((Z10^2+AC10^2)/2)),5)) -> 0.14528 | F69: =IF(ABS(E69)<0.2,"Negligible", IF(ABS(E69)<0.5,"Small", IF(ABS(E69)<0.8,"Medium","Large"))) -> Negligible | H69: Overall Score | I69: =_xlfn.T.TEST('RAG RAW'!J:J, 'Agentic RAW'!J:J, 2, 3) -> 2.0790828e-27 | J69: =IF(I69<0.001,"***",IF(I69<0.01,"**",IF(I69<0.05,"*","ns"))) -> *** | K69: =ABS(ROUND((T10-U10)/SQRT(((AD10^2+AE10^2)/2)),5)) -> 0.90209 | L69: =IF(ABS(K69)<0.2,"Negligible", IF(ABS(K69)<0.5,"Small", IF(ABS(K69)<0.8,"Medium","Large"))) -> Large | N69: Overall Score | O69: =CORREL('OpenAI RAW'!J:J, 'Gemini RAW'!J:J) -> 0.28668323 | P69: {=SUMPRODUCT(('OpenAI RAW'!J2:J10000='Gemini RAW'!J2:J10000)*1)/COUNT('OpenAI RAW'!J2:J10000)} -> 12.405333 | Q69: =COUNTIF('OpenAI RAW'!J2:J10000,1)/COUNT('OpenAI RAW'!J2:J10000) -> 0 | R69: =COUNTIF('Gemini RAW'!J2:J10000,1)/COUNT('Gemini RAW'!J2:J10000) -> 0 | S69: =Q69*R69 -> 0 | U69: =(S69-T69)/(1-T69) -> 0 | V69: =IF(U69<0.2,"Poor", IF(U69<0.4,"Fair", IF(U69<0.6,"Moderate", IF(U69<0.8,"Substantial", "Almost perfect")))) -> Poor
B71: The results clearly demonstrate a significant evaluator effect. The choice of LLM judge systematically alters the outcome of the evaluation. Cohen's d Direction: The negative d values for most dimensions mean that the first group (OpenAI RAW) consistently provided lower scores than the second group (Gemini RAW). Conclusion: The Gemini judge is a "harsher" or "stricter" grader than the OpenAI judge. This effect is Medium for Factual Accuracy (d=-0.60) and Clarity (d=-0.54). It is Small but significant for Relevance and Completeness. The Exception: Citation Quality: Here, the effect is Large and positive (d=0.95). This means the OpenAI judge is much stricter on citations than the Gemini judge. This is a fascinating and highly publishable finding, suggesting the models have different internal rubrics for what constitutes a good citation. Raw Total: The non-significant result (ns) with a negligible effect size (d=-0.15) is deceptive. It does not mean the judges agree overall. Rather, the large, opposing effect on Citation Quality is likely "canceling out" the smaller, consistent effects on other dimensions. This is a classic example of why looking only at the total score can be misleading. | H71: Your data tells a compelling and unambiguous story: The RAG architecture is substantially superior to the Agentic architecture across every measured dimension. Statistical Significance: The p-values are all exceptionally low (e.g., 9.87E-39), indicating that these differences are not due to random chance. The *** notation is appropriate. Practical Significance (Effect Size): The performance gap is Large for Factual Accuracy (d=1.13), Completeness (d=0.91), and the Raw Total score (d=0.90). This implies the RAG system is demonstrably and consistently better in these crucial areas. The advantage is Medium for Relevance (d=0.75) and Clarity (d=0.73), which is still a very meaningful difference. The advantage is Small but still significant for Citation Quality (d=0.24). This is your most interesting nuanced finding: while RAG is better, the performance gap for citations is the narrowest.
B87: Final Verdict and Path to Publication Acknowledge the Confound: You must address the confound in your thesis. Frame it as a limitation of the study. For example: "A limitation of this study is the potential for a model-affinity bias, as the RAG system was developed using Gemini architecture and the Agentic system with OpenAI. Future work should aim to decouple the system's base model from the evaluator's model to eliminate this confound." Refine Your Narrative: Your primary story is strong, but it should be told with this caveat. Chapter 1 (RAG vs. Agentic): "The RAG system, which is based on Gemini, demonstrated superior performance when evaluated by both OpenAI and Gemini judges. However, the effect was..." Chapter 2 (Evaluator Bias): "A significant evaluator effect was observed. The Gemini judge was systematically stricter on content-based metrics, while the OpenAI judge was stricter on citation quality. This highlights the critical importance of evaluator selection and the potential for model-specific biases in LLM-as-a-judge methodologies." ## Key Findings ### Judge Model Comparison (OpenAI vs. Gemini) OpenAI demonstrated significantly more lenient evaluation patterns compared to Gemini across five of six dimensions (all p < 0.01). The largest discrepancy occurred in Citation Quality (d = 0.95, Large effect), where OpenAI assigned substantially higher scores. Despite dimensional differences, Overall Scores showed no significant difference (p = 0.563, d = 0.15), suggesting that judge-specific biases may cancel out in aggregate evaluations. ### Architecture Comparison (RAG vs. Agentic) RAG architecture demonstrated superior performance across all evaluated dimensions (all p < 0.001). The largest advantages occurred in Factual Accuracy (d = 1.13) and Completeness (d = 0.91), both representing Large effects. Overall performance favored RAG with a Large effect size (d = 0.90, p < 0.001), indicating substantial practical superiority over the Agentic approach. For Immediate Use: ✅ Report both comparisons - they answer different questions ✅ Emphasize RAG superiority - it's your strongest finding ✅ Acknowledge judge bias - important for methodology ✅ Focus on effect sizes - more meaningful than p-values For Future Research: 📈 Qualitative analysis: Why does RAG outperform Agentic? Independent samples t-tests revealed significant differences between RAG and Agentic architectures across all dimensions (all p < 0.001, Bonferroni corrected α = 0.0083). Effect sizes ranged from Small (Citation Quality, d = 0.24) to Large (Factual Accuracy, d = 1.13), with an overall Large effect favoring RAG (d = 0.90).
B117: import matplotlib.pyplot as plt # Create side-by-side bar charts fig, (ax1, ax2) = plt.subplots(1, 2, figsize=(15, 6)) # Chart 1: Judge Model Comparison dimensions = ['Factual', 'Relevance', 'Complete', 'Clarity', 'Citation'] effects = [0.60, 0.24, 0.23, 0.54, 0.95] ax1.bar(dimensions, effects, color=['red' if e > 0.5 else 'orange' if e > 0.2 else 'gray' for e in effects]) ax1.set_title('OpenAI vs Gemini Judge Bias\n(Positive = OpenAI more lenient)') ax1.set_ylabel("Cohen's d") # Chart 2: Architecture Comparison effects_arch = [1.13, 0.75, 0.91, 0.73, 0.90] ax2.bar(dimensions, effects_arch, color=['red' if e > 0.8 else 'orange' if e > 0.5 else 'gray' for e in effects_arch]) ax2.set_title('RAG vs Agentic Performance\n(Positive = RAG better)') ax2.set_ylabel("Cohen's d")

Sheet Sheet1
A1: OpenAI Raw_Total | B1: Gemini Raw_Total | C1: Mean | D1: Diff | E1: Abs Diff
A2: 20 | B2: 21 | C2: =(A2/B2)/2 -> 0.47619048 | D2: =A2-B2 -> -1 | E2: =ABS(A2-B2) -> 1 | L2: Summary:
A3: 24 | B3: 21 | C3: =(A3/B3)/2 -> 0.57142857 | D3: =A3-B3 -> 3 | E3: =ABS(A3-B3) -> 3 | L3: Bland‑Altman summary stats
A4: 24 | B4: 22 | C4: =(A4/B4)/2 -> 0.54545455 | D4: =A4-B4 -> 2 | E4: =ABS(A4-B4) -> 2 | L4: Mean_of_diffs | M4: =AVERAGE(C:C) -> 0.59720575
A5: 23 | B5: 18 | C5: =(A5/B5)/2 -> 0.63888889 | D5: =A5-B5 -> 5 | E5: =ABS(A5-B5) -> 5 | L5: SD_of_diffs | M5: =_xlfn.STDEV.S(C:C) -> 0.36633186
A6: 20 | B6: 23 | C6: =(A6/B6)/2 -> 0.43478261 | D6: =A6-B6 -> -3 | E6: =ABS(A6-B6) -> 3 | L6: Upper_Limit | M6: =M4 + 1.96*M5 -> 1.3152162
A7: 24 | B7: 23 | C7: =(A7/B7)/2 -> 0.52173913 | D7: =A7-B7 -> 1 | E7: =ABS(A7-B7) -> 1 | L7: Lower_Limit | M7: =M4 - 1.96*M5 -> -0.1208047
A8: 24 | B8: 18 | C8: =(A8/B8)/2 -> 0.66666667 | D8: =A8-B8 -> 6 | E8: =ABS(A8-B8) -> 6 | L8: ±1‑point agreement & exact agreement
A9: 20 | B9: 18 | C9: =(A9/B9)/2 -> 0.55555556 | D9: =A9-B9 -> 2 | E9: =ABS(A9-B9) -> 2 | L9: Exact_Agreement | M9: {=SUMPRODUCT((A2:A1000=B2:B1000)*1)/COUNT(A2:A1000)} -> 0.408
A10: 24 | B10: 18 | C10: =(A10/B10)/2 -> 0.66666667 | D10: =A10-B10 -> 6 | E10: =ABS(A10-B10) -> 6 | L10: Within_1pt | M10: {=SUMPRODUCT((ABS(A2:A1000-B2:B1000)<=1)*1)/COUNT(A2:A1000)} -> 0.58266667
A11: 20 | B11: 19 | C11: =(A11/B11)/2 -> 0.52631579 | D11: =A11-B11 -> 1 | E11: =ABS(A11-B11) -> 1
A12: 20 | B12: 21 | C12: =(A12/B12)/2 -> 0.47619048 | D12: =A12-B12 -> -1 | E12: =ABS(A12-B12) -> 1
A13: 20 | B13: 20 | C13: =(A13/B13)/2 -> 0.5 | D13: =A13-B13 -> 0 | E13: =ABS(A13-B13) -> 0
A14: 23 | B14: 22 | C14: =(A14/B14)/2 -> 0.52272727 | D14: =A14-B14 -> 1 | E14: =ABS(A14-B14) -> 1
A15: 20 | B15: 18 | C15: =(A15/B15)/2 -> 0.55555556 | D15: =A15-B15 -> 2 | E15: =ABS(A15-B15) -> 2
A16: 20 | B16: 18 | C16: =(A16/B16)/2 -> 0.55555556 | D16: =A16-B16 -> 2 | E16: =ABS(A16-B16) -> 2
A17: 24 | B17: 21 | C17: =(A17/B17)/2 -> 0.57142857 | D17: =A17-B17 -> 3 | E17: =ABS(A17-B17) -> 3
A18: 23 | B18: 22 | C18: =(A18/B18)/2 -> 0.52272727 | D18: =A18-B18 -> 1 | E18: =ABS(A18-B18) -> 1
A19: 20 | B19: 23 | C19: =(A19/B19)/2 -> 0.43478261 | D19: =A19-B19 -> -3 | E19: =ABS(A19-B19) -> 3
A20: 20 | B20: 22 | C20: =(A20/B20)/2 -> 0.45454545 | D20: =A20-B20 -> -2 | E20: =ABS(A20-B20) -> 2
A21: 20 | B21: 17 | C21: =(A21/B21)/2 -> 0.58823529 | D21: =A21-B21 -> 3 | E21: =ABS(A21-B21) -> 3
A22: 21 | B22: 20 | C22: =(A22/B22)/2 -> 0.525 | D22: =A22-B22 -> 1 | E22: =ABS(A22-B22) -> 1
... A751: 13 | B751: 21 | C751: =(A751/B751)/2 -> 0.30952381 | D751: =A751-B751 -> -8 | E751: =ABS(A751-B751) -> 8

Sheet Sheet2
B3: Type | C3: Values
B4: Gemini | C4: Gemini | D4: OpenAI | E4: OpenAI
A5: System_Type | B5: Average of Raw_Total2 | C5: Average of Weighted_Total | D5: Average of Raw_Total2 | E5: Average of Weighted_Total
A6: agentic | B6: 18.527778 | C6: 3.9081111 | D6: 14.005556 | E6: 2.9113194
A7: rag | B7: 18.860915 | C7: 3.8561444 | D7: 20.473684 | E7: 4.2110307

Sheet RAW
A1: Question ID | B1: Question | C1: OpenAI Answer | D1: OpenAI System_Type | E1: OpenAI Factual_Accuracy | F1: OpenAI Relevance | G1: OpenAI Completeness | H1: OpenAI Clarity | I1: OpenAI Citation_Quality | J1: OpenAI Weighted_Total | K1: OpenAI Raw_Total | L1: OpenAI Snippet_Grounding_Score | M1: OpenAI Snippet_Count | N1: OpenAI Overall_Assessment | O1: OpenAI Fallback_Used | P1: OpenAI Fallback_Merge_Applied | Q1: OpenAI Original_Internal_Answer_Length | R1: OpenAI Web_Fallback_Length | S1: Gemini Answer | T1: Gemini System_Type | U1: Gemini Factual_Accuracy | V1: Gemini Relevance | W1: Gemini Completeness | X1: Gemini Clarity | Y1: Gemini Citation_Quality | Z1: Gemini Weighted_Total | AA1: Gemini Raw_Total | AB1: Gemini Snippet_Grounding_Score | AC1: Gemini Snippet_Count | AD1: Gemini Overall_Assessment | AE1: Gemini Fallback_Used | AF1: Gemini Fallback_Merge_Applied | AG1: Gemini Original_Internal_Answer_Length | AH1: Gemini Web_Fallback_Length
A2: 1 | B2: Am I allowed to accept a gift from a client worth €15? | C2: In principle, you are not allowed to accept gifts from clients. However, gifts to or from clients of up to EUR 20 (gross) are permissible, provided the client is not a public official. Accepting gifts in the form of cash or cash equivalents is prohibited. Gifts with a gross value of more than EUR 20 from a client to employees must be declined in principle. If declining a gift is not possible, it may be permissible if no "K.O." criteria exist, negative indicators do not outweigh positive ones, and recommendations are followed. A gift is defined as the voluntary transfer of ownership without requiring consideration. Examples include wine, books, and theater tickets. If you accept a gift over EUR 20, you should inform the giver that you should not receive gifts in the future. Analysts may not accept any gifts, including low-value ones, from issuers. The acceptance of cash or cash equivalent gifts is never permitted. Research Analysts and Corporate Finance employees are never permitted to receive gifts. If the gift is over EUR 250 (gross), the bank does not consider it usual and appropriate. If refusing a gift may cause significant offense or embarrassment, the gift may be accepted but should be donated to a charity or put to another use in the Bank's interests, in consultation with AFC Compliance. If you accept a gift, you must notify your line manager. Cases of doubt must always be agreed with AFC Compliance in advance. The acceptance of gifts from customers up to EUR 20 (gross) is always permitted (exception: public officials). For employees taxable in Germany, gifts must be reported to AFC Compliance to assess acceptability and forwarded to Human Resources to check taxation as a non-cash benefit. For employees taxable outside of Germany, AFC Compliance London and Human Resources London must be notified to check for tax deductions. | D2: rag | E2: 4 | F2: 5 | G2: 4 | H2: 4 | I2: 3 | J2: 4.1625 | K2: 20 | L2: 0.29402336 | M2: 6 | N2: The AI response effectively addresses the user's query about accepting a gift worth €15, providing relevant and mostly accurate information. While it demonstrates a good understanding of the guidelines, it could benefit from more explicit references to the snippets and a more comprehensive coverage of compliance requirements for higher-value gifts. Overall, it meets high academic standards but has room for improvement in citation quality and completeness. | O2: FALSE | S2: =VLOOKUP($B2,'Gemini RAW'!$A:$Q,2,FALSE) -> In principle, you are not allowed to accept gifts from clients. However, gifts to or from clients of up to EUR 20 (gross) are permissible, provided the client is not a public official. Accepting gifts in the form of cash or cash equivalents is prohibited. Gifts with a gross value of more than EUR 20 from a client to employees must be declined in principle. If declining a gift is not possible, it may be permissible if no "K.O." criteria exist, negative indicators do not outweigh positive ones, and recommendations are followed. A gift is defined as the voluntary transfer of ownership without requiring consideration. Examples include wine, books, and theater tickets. If you accept a gift over EUR 20, you should inform the giver that you should not receive gifts in the future. Analysts may not accept any gifts, including low-value ones, from issuers. The acceptance of cash or cash equivalent gifts is never permitted. Research Analysts and Corporate Finance employees are never permitted to receive gifts. If the gift is over EUR 250 (gross), the bank does not consider it usual and appropriate. If refusing a gift may cause significant offense or embarrassment, the gift may be accepted but should be donated to a charity or put to another use in the Bank's interests, in consultation with AFC Compliance. If you accept a gift, you must notify your line manager. Cases of doubt must always be agreed with AFC Compliance in advance. The acceptance of gifts from customers up to EUR 20 (gross) is always permitted (exception: public officials). For employees taxable in Germany, gifts must be reported to AFC Compliance to assess acceptability and forwarded to Human Resources to check taxation as a non-cash benefit. For employees taxable outside of Germany, AFC Compliance London and Human Resources London must be notified to check for tax deductions. | T2: =VLOOKUP($B2,'Gemini RAW'!$A:$Q,3,FALSE) -> rag | U2: =VLOOKUP($B2,'Gemini RAW'!$A:$Q,4,FALSE) -> 5 | V2: =VLOOKUP($B2,'Gemini RAW'!$A:$Q,5,FALSE) -> 5 | W2: =VLOOKUP($B2,'Gemini RAW'!$A:$Q,6,FALSE) -> 5 | X2: =VLOOKUP($B2,'Gemini RAW'!$A:$Q,7,FALSE) -> 5 | Y2: =VLOOKUP($B2,'Gemini RAW'!$A:$Q,8,FALSE) -> 1 | Z2: =VLOOKUP($B2,'Gemini RAW'!$A:$Q,9,FALSE) -> 3.64 | AA2: =VLOOKUP($B2,'Gemini RAW'!$A:$Q,10,FALSE) -> 21 | AB2: =VLOOKUP($B2,'Gemini RAW'!$A:$Q,11,FALSE) -> 0.29402336 | AC2: =VLOOKUP($B2,'Gemini RAW'!$A:$Q,12,FALSE) -> 6 | AD2: =VLOOKUP($B2,'Gemini RAW'!$A:$Q,13,FALSE) -> The response provides a factually accurate, relevant, complete, and clear answer to the user's query. However, it lacks proper citations and does not address GDPR compliance, EU AI Act alignment, or audit trail quality. The content quality is excellent, but the source utilization and citation mechanics are poor. | AE2: =VLOOKUP($B2,'Gemini RAW'!$A:$Q,14,FALSE) -> FALSE | AF2: =VLOOKUP($B2,'Gemini RAW'!$A:$Q,15,FALSE) -> 0 | AG2: =VLOOKUP($B2,'Gemini RAW'!$A:$Q,16,FALSE) -> 0 | AH2: =VLOOKUP($B2,'Gemini RAW'!$A:$Q,17,FALSE) -> 0
A3: 2 | B3: Can I give a gift to a client worth €20 exactly? | C3: You are allowed to give a gift to a client worth up to EUR 20 (gross) or equivalent, provided the client is not a public official. Gifts in the form of cash or cash equivalents, such as vouchers for cash payment, are prohibited in all cases and without exception. A gift is defined as the voluntary transfer of ownership, e.g., of an item or a right, without requiring consideration. Examples of gifts include wine, books, and theater tickets. The bank also gives gifts such as wine, calendars, and promotional items like pens and golf balls. Vouchers that cannot be redeemed for cash, such as those for a perfumery, bookstore, or restaurant, are treated as gifts. If you are an employee taxable outside Germany and accept a gift exceeding EUR 20 (gross) in connection with your work for the Bank, you must notify Compliance London and Human Resources London by e-mail. This notification should include the name and address of the company/person from whom the gift originated, a description of the gift and its value, and your name. This is so Human Resources can check if a tax deduction is required. Employees must refuse all gifts received in connection with their work for the Bank whose value exceeds EUR 20 (gross). If refusal is not possible for reasons of politeness, employees taxable in Germany must report all gifts received whose value exceeds EUR 20 (gross). This should be done without delay using the form “Notification to AFC Compliance and Human Resources regarding the acceptance of taxable benefits in kind (gifts exceeding EUR 20 (gross) or equivalent) by an employee”. The form is submitted to AFC Compliance, who will assess whether the gift can be accepted or rejected, inform the employee, and then forward the form to Human Resources. If you give or expect to receive a gift, you should inform the person that all Berenberg Group employees are subject to highly restrictive regulations. Gifts may only be given or accepted under very specific, narrowly defined conditions. The Bank does not consider gifts of more than EUR 250 (gross) to be usual and appropriate. If refusing a gift may cause significant offense or embarrassment, the gift may be accepted but should be donated to a charity of the Bank's choosing or put to another use in the Bank's interests, in consultation with AFC Compliance. If you accept a gift, you must notify your line manager appropriately. Cases of doubt must always be agreed with AFC Compliance in advance but in any case without delay. | D3: rag | E3: 5 | F3: 5 | G3: 5 | H3: 5 | I3: 4 | J3: 4.9125 | K3: 24 | L3: 0.26204663 | M3: 7 | N3: The AI response is highly accurate, relevant, complete, and clear, effectively addressing the user's query about gift-giving limits. While it lacks explicit citations, the grounding in the provided snippets is strong, justifying a high score in citation quality despite the absence of direct references. | O3: FALSE | S3: =VLOOKUP($B3,'Gemini RAW'!$A:$Q,2,FALSE) -> You are allowed to give a gift to a client worth up to EUR 20 (gross) or equivalent, provided the client is not a public official. Gifts in the form of cash or cash equivalents, such as vouchers for cash payment, are prohibited in all cases and without exception. A gift is defined as the voluntary transfer of ownership, e.g., of an item or a right, without requiring consideration. Examples of gifts include wine, books, and theater tickets. The bank also gives gifts such as wine, calendars, and promotional items like pens and golf balls. Vouchers that cannot be redeemed for cash, such as those for a perfumery, bookstore, or restaurant, are treated as gifts. If you are an employee taxable outside Germany and accept a gift exceeding EUR 20 (gross) in connection with your work for the Bank, you must notify Compliance London and Human Resources London by e-mail. This notification should include the name and address of the company/person from whom the gift originated, a description of the gift and its value, and your name. This is so Human Resources can check if a tax deduction is required. Employees must refuse all gifts received in connection with their work for the Bank whose value exceeds EUR 20 (gross). If refusal is not possible for reasons of politeness, employees taxable in Germany must report all gifts received whose value exceeds EUR 20 (gross). This should be done without delay using the form “Notification to AFC Compliance and Human Resources regarding the acceptance of taxable benefits in kind (gifts exceeding EUR 20 (gross) or equivalent) by an employee”. The form is submitted to AFC Compliance, who will assess whether the gift can be accepted or rejected, inform the employee, and then forward the form to Human Resources. If you give or expect to receive a gift, you should inform the person that all Berenberg Group employees are subject to highly restrictive regulations. Gifts may only be given or accepted under very specific, narrowly defined conditions. The Bank does not consider gifts of more than EUR 250 (gross) to be usual and appropriate. If refusing a gift may cause significant offense or embarrassment, the gift may be accepted but should be donated to a charity of the Bank's choosing or put to another use in the Bank's interests, in consultation with AFC Compliance. If you accept a gift, you must notify your line manager appropriately. Cases of doubt must always be agreed with AFC Compliance in advance but in any case without delay. | T3: =VLOOKUP($B3,'Gemini RAW'!$A:$Q,3,FALSE) -> rag | U3: =VLOOKUP($B3,'Gemini RAW'!$A:$Q,4,FALSE) -> 5 | V3: =VLOOKUP($B3,'Gemini RAW'!$A:$Q,5,FALSE) -> 5 | W3: =VLOOKUP($B3,'Gemini RAW'!$A:$Q,6,FALSE) -> 5 | X3: =VLOOKUP($B3,'Gemini RAW'!$A:$Q,7,FALSE) -> 5 | Y3: =VLOOKUP($B3,'Gemini RAW'!$A:$Q,8,FALSE) -> 1 | Z3: =VLOOKUP($B3,'Gemini RAW'!$A:$Q,9,FALSE) -> 4.48 | AA3: =VLOOKUP($B3,'Gemini RAW'!$A:$Q,10,FALSE) -> 21 | AB3: =VLOOKUP($B3,'Gemini RAW'!$A:$Q,11,FALSE) -> 0.26204663 | AC3: =VLOOKUP($B3,'Gemini RAW'!$A:$Q,12,FALSE) -> 7 | AD3: =VLOOKUP($B3,'Gemini RAW'!$A:$Q,13,FALSE) -> The response is excellent in terms of content quality, providing accurate, relevant, complete, and clear information about gift-giving policies. However, it lacks proper citation and audit trail information, which significantly reduces its academic rigor. The response effectively answers the user's question but fails to provide transparency regarding its sources. | AE3: =VLOOKUP($B3,'Gemini RAW'!$A:$Q,14,FALSE) -> FALSE | AF3: =VLOOKUP($B3,'Gemini RAW'!$A:$Q,15,FALSE) -> 0 | AG3: =VLOOKUP($B3,'Gemini RAW'!$A:$Q,16,FALSE) -> 0 | AH3: =VLOOKUP($B3,'Gemini RAW'!$A:$Q,17,FALSE) -> 0
A4: 3 | B4: What should I do if I receive a gift worth €30 from a business partner? | C4: If you receive a gift worth €30 from a business partner, here's what you should do, based on Berenberg's guidelines: * **General Rule:** In principle, gifts with a gross value of more than EUR 20 from a (potential) client/business partner to employees must be declined. * **Declining the Gift:** You should take a tactful approach in each specific case. * **If Refusal is Not Possible:** If a refusal is not possible, for reasons of politeness, the following applies: * **Employees taxable in Germany:** Report the gift using the form “Notification to AFC Compliance and Human Resources regarding the acceptance of taxable benefits in kind (gifts exceeding EUR 20 (gross) or equivalent) by an employee” (Appendix 2). Complete and submit this form to AFC Compliance. AFC Compliance will assess whether the gift can be accepted or should be rejected, informs the employee accordingly, and then forwards the form to the Human Resources department. * **Employees taxable outside Germany (especially in the UK):** Notify Compliance London and Human Resources London by e-mail. Include the name and address of the company/person from whom the gift originated, a description of the gift and its value (plausible estimate), and your name. This allows Human Resources to check the extent to which a tax deduction is required. * **Additional Steps:** * Give feedback to the gift giver that they should refrain from giving gifts in the future. * Notify your line manager appropriately if you accept the gift. * **Important Considerations:** * The acceptance of cash or cash equivalents, such as vouchers for cash payment, is prohibited in all cases and without exception. * If you are in any doubt as to whether you can accept a gift, consult with AFC Compliance. * If you believe that any bribery, corruption or other breach of policy has occurred or may occur, you must refuse it and report it immediately to your manager and AFC Compliance. * **Gifts to family members:** Gifts offered to family members, relatives or close associates of Berenberg employees may not be accepted. * **Gifts during bidding process:** During the bidding or pitch process for a new transaction, business mandate, product, service or relationship the receipt of gifts (of any value) is strictly prohibited. | D4: rag | E4: 5 | F4: 5 | G4: 5 | H4: 5 | I4: 4 | J4: 4.9125 | K4: 24 | L4: 0.4411629 | M4: 6 | N4: The AI response is exemplary in addressing the user's query with high factual accuracy, relevance, completeness, and clarity. It effectively synthesizes information from the snippets, although it lacks explicit citations which would enhance citation quality. Overall, it meets and exceeds academic standards. | O4: FALSE | S4: =VLOOKUP($B4,'Gemini RAW'!$A:$Q,2,FALSE) -> If you receive a gift worth €30 from a business partner, here's what you should do, based on Berenberg's guidelines: * **General Rule:** In principle, gifts with a gross value of more than EUR 20 from a (potential) client/business partner to employees must be declined. * **Declining the Gift:** You should take a tactful approach in each specific case. * **If Refusal is Not Possible:** If a refusal is not possible, for reasons of politeness, the following applies: * **Employees taxable in Germany:** Report the gift using the form “Notification to AFC Compliance and Human Resources regarding the acceptance of taxable benefits in kind (gifts exceeding EUR 20 (gross) or equivalent) by an employee” (Appendix 2). Complete and submit this form to AFC Compliance. AFC Compliance will assess whether the gift can be accepted or should be rejected, informs the employee accordingly, and then forwards the form to the Human Resources department. * **Employees taxable outside Germany (especially in the UK):** Notify Compliance London and Human Resources London by e-mail. Include the name and address of the company/person from whom the gift originated, a description of the gift and its value (plausible estimate), and your name. This allows Human Resources to check the extent to which a tax deduction is required. * **Additional Steps:** * Give feedback to the gift giver that they should refrain from giving gifts in the future. * Notify your line manager appropriately if you accept the gift. * **Important Considerations:** * The acceptance of cash or cash equivalents, such as vouchers for cash payment, is prohibited in all cases and without exception. * If you are in any doubt as to whether you can accept a gift, consult with AFC Compliance. * If you believe that any bribery, corruption or other breach of policy has occurred or may occur, you must refuse it and report it immediately to your manager and AFC Compliance. * **Gifts to family members:** Gifts offered to family members, relatives or close associates of Berenberg employees may not be accepted. * **Gifts during bidding process:** During the bidding or pitch process for a new transaction, business mandate, product, service or relationship the receipt of gifts (of any value) is strictly prohibited. | T4: =VLOOKUP($B4,'Gemini RAW'!$A:$Q,3,FALSE) -> rag | U4: =VLOOKUP($B4,'Gemini RAW'!$A:$Q,4,FALSE) -> 4 | V4: =VLOOKUP($B4,'Gemini RAW'!$A:$Q,5,FALSE) -> 5 | W4: =VLOOKUP($B4,'Gemini RAW'!$A:$Q,6,FALSE) -> 4 | X4: =VLOOKUP($B4,'Gemini RAW'!$A:$Q,7,FALSE) -> 5 | Y4: =VLOOKUP($B4,'Gemini RAW'!$A:$Q,8,FALSE) -> 4 | Z4: =VLOOKUP($B4,'Gemini RAW'!$A:$Q,9,FALSE) -> 3.46 | AA4: =VLOOKUP($B4,'Gemini RAW'!$A:$Q,10,FALSE) -> 22 | AB4: =VLOOKUP($B4,'Gemini RAW'!$A:$Q,11,FALSE) -> 0.4411629 | AC4: =VLOOKUP($B4,'Gemini RAW'!$A:$Q,12,FALSE) -> 6 | AD4: =VLOOKUP($B4,'Gemini RAW'!$A:$Q,13,FALSE) -> The response provides a relevant and clear answer to the user's query, offering practical advice based on Berenberg's guidelines. The content is generally accurate and comprehensive, although it could benefit from acknowledging the specific context of the guidelines. The citation quality is acceptable but could be improved with a more explicit reference. The response completely fails to address GDPR, EU AI Act, and audit trail considerations. | AE4: =VLOOKUP($B4,'Gemini RAW'!$A:$Q,14,FALSE) -> FALSE | AF4: =VLOOKUP($B4,'Gemini RAW'!$A:$Q,15,FALSE) -> 0 | AG4: =VLOOKUP($B4,'Gemini RAW'!$A:$Q,16,FALSE) -> 0 | AH4: =VLOOKUP($B4,'Gemini RAW'!$A:$Q,17,FALSE) -> 0
A5: 4 | B5: Are cash or gift vouchers ever acceptable as gifts? | C5: The acceptance of cash or cash equivalent gifts, such as gift certificates or vouchers, is never permitted. This prohibition is without exception. Vouchers that do not allow for cash payment are treated as gifts. In principle, you are not allowed to accept gifts from or give gifts to clients. However, this does not include gifts to or from clients of up to EUR 20 (gross) or equivalent, provided the client is not a public official. Gifts with a gross value of more than EUR 20 from a (potential) client/business partner to employees must be declined. Gifts offered to family members, relatives or close associates of Berenberg employees may not be accepted. | D5: rag | E5: 5 | F5: 5 | G5: 4 | H5: 5 | I5: 4 | J5: 4.725 | K5: 23 | L5: 0.46329244 | M5: 4 | N5: The AI response effectively addresses the user query with high factual accuracy and relevance. It is clear and well-structured, though it could improve in completeness by elaborating on the exceptions to the rules regarding gift acceptance. The lack of explicit citations does not detract significantly from the response, but clearer attribution would enhance citation quality. | O5: FALSE | S5: =VLOOKUP($B5,'Gemini RAW'!$A:$Q,2,FALSE) -> The acceptance of cash or cash equivalent gifts, such as gift certificates or vouchers, is never permitted. This prohibition is without exception. Vouchers that do not allow for cash payment are treated as gifts. In principle, you are not allowed to accept gifts from or give gifts to clients. However, this does not include gifts to or from clients of up to EUR 20 (gross) or equivalent, provided the client is not a public official. Gifts with a gross value of more than EUR 20 from a (potential) client/business partner to employees must be declined. Gifts offered to family members, relatives or close associates of Berenberg employees may not be accepted. | T5: =VLOOKUP($B5,'Gemini RAW'!$A:$Q,3,FALSE) -> rag | U5: =VLOOKUP($B5,'Gemini RAW'!$A:$Q,4,FALSE) -> 4 | V5: =VLOOKUP($B5,'Gemini RAW'!$A:$Q,5,FALSE) -> 5 | W5: =VLOOKUP($B5,'Gemini RAW'!$A:$Q,6,FALSE) -> 4 | X5: =VLOOKUP($B5,'Gemini RAW'!$A:$Q,7,FALSE) -> 4 | Y5: =VLOOKUP($B5,'Gemini RAW'!$A:$Q,8,FALSE) -> 1 | Z5: =VLOOKUP($B5,'Gemini RAW'!$A:$Q,9,FALSE) -> 3.16 | AA5: =VLOOKUP($B5,'Gemini RAW'!$A:$Q,10,FALSE) -> 18 | AB5: =VLOOKUP($B5,'Gemini RAW'!$A:$Q,11,FALSE) -> 0.46329244 | AC5: =VLOOKUP($B5,'Gemini RAW'!$A:$Q,12,FALSE) -> 4 | AD5: =VLOOKUP($B5,'Gemini RAW'!$A:$Q,13,FALSE) -> The response is generally good in terms of content quality, providing a relevant and mostly accurate answer to the user's query. However, it lacks citations and does not address GDPR, EU AI Act, or audit trail considerations. The response is also specific to Berenberg employees, which limits its general applicability. | AE5: =VLOOKUP($B5,'Gemini RAW'!$A:$Q,14,FALSE) -> FALSE | AF5: =VLOOKUP($B5,'Gemini RAW'!$A:$Q,15,FALSE) -> 0 | AG5: =VLOOKUP($B5,'Gemini RAW'!$A:$Q,16,FALSE) -> 0 | AH5: =VLOOKUP($B5,'Gemini RAW'!$A:$Q,17,FALSE) -> 0
A6: 5 | B6: Can I accept a bottle of wine from a client if it is under €20? | C6: In principle, you are not allowed to accept gifts from clients. However, gifts to or from clients of up to EUR 20 (gross) are permissible, provided the client is not a public official. If a gift exceeds EUR 20 (gross), it should be declined. If declining the gift is not possible, you must report it. For employees taxable in Germany, you must report the gift using form Anlage 2 to AFC Compliance for assessment and forwarding to Human Resources to check taxation as a non-cash benefit. For employees taxable outside of Germany, you must report the gift via email to AFC Compliance London and Human Resources London, including the name and address of the gift giver, description and value of the gift, and your name, to check for tax deductions. If the gift is over 20 EUR (gross), you should inform the giver that you should not receive gifts in the future. Analyst (Research) are not allowed to accept any gifts. Accepting gifts in the form of cash or cash equivalents is prohibited. | D6: rag | E6: 4 | F6: 5 | G6: 4 | H6: 4 | I6: 3 | J6: 4.1625 | K6: 20 | L6: 0.20945005 | M6: 6 | N6: The AI response effectively addresses the user's query with relevant and mostly accurate information regarding gift acceptance policies. While it is clear and well-structured, it could benefit from more explicit grounding in the provided snippets and a more comprehensive coverage of the policy implications for different employee categories. | O6: FALSE | S6: =VLOOKUP($B6,'Gemini RAW'!$A:$Q,2,FALSE) -> In principle, you are not allowed to accept gifts from clients. However, gifts to or from clients of up to EUR 20 (gross) are permissible, provided the client is not a public official. If a gift exceeds EUR 20 (gross), it should be declined. If declining the gift is not possible, you must report it. For employees taxable in Germany, you must report the gift using form Anlage 2 to AFC Compliance for assessment and forwarding to Human Resources to check taxation as a non-cash benefit. For employees taxable outside of Germany, you must report the gift via email to AFC Compliance London and Human Resources London, including the name and address of the gift giver, description and value of the gift, and your name, to check for tax deductions. If the gift is over 20 EUR (gross), you should inform the giver that you should not receive gifts in the future. Analyst (Research) are not allowed to accept any gifts. Accepting gifts in the form of cash or cash equivalents is prohibited. | T6: =VLOOKUP($B6,'Gemini RAW'!$A:$Q,3,FALSE) -> rag | U6: =VLOOKUP($B6,'Gemini RAW'!$A:$Q,4,FALSE) -> 5 | V6: =VLOOKUP($B6,'Gemini RAW'!$A:$Q,5,FALSE) -> 5 | W6: =VLOOKUP($B6,'Gemini RAW'!$A:$Q,6,FALSE) -> 5 | X6: =VLOOKUP($B6,'Gemini RAW'!$A:$Q,7,FALSE) -> 5 | Y6: =VLOOKUP($B6,'Gemini RAW'!$A:$Q,8,FALSE) -> 3 | Z6: =VLOOKUP($B6,'Gemini RAW'!$A:$Q,9,FALSE) -> 4.88 | AA6: =VLOOKUP($B6,'Gemini RAW'!$A:$Q,10,FALSE) -> 23 | AB6: =VLOOKUP($B6,'Gemini RAW'!$A:$Q,11,FALSE) -> 0.20945005 | AC6: =VLOOKUP($B6,'Gemini RAW'!$A:$Q,12,FALSE) -> 6 | AD6: =VLOOKUP($B6,'Gemini RAW'!$A:$Q,13,FALSE) -> The response is excellent in terms of content quality, providing a factually accurate, relevant, complete, and clear answer to the user's query. The source utilization is adequate, as the information is grounded in the provided snippets, but the lack of explicit citations reduces the overall score. The response also demonstrates good compliance with GDPR and the EU AI Act. | AE6: =VLOOKUP($B6,'Gemini RAW'!$A:$Q,14,FALSE) -> FALSE | AF6: =VLOOKUP($B6,'Gemini RAW'!$A:$Q,15,FALSE) -> 0 | AG6: =VLOOKUP($B6,'Gemini RAW'!$A:$Q,16,FALSE) -> 0 | AH6: =VLOOKUP($B6,'Gemini RAW'!$A:$Q,17,FALSE) -> 0
A7: 6 | B7: Do I need to record a gift of €10 received from a client? | C7: You are required to keep a written record of all hospitality and gifts given or received, so that this can be reviewed by AFC Compliance. You must submit all expenses claims relating to hospitality, gifts or payments to third parties and record the reason for expenditure, in accordance with Berenberg's expenses policy. All accounts, invoices, and other records relating to dealings with third parties including suppliers and customers should be prepared with strict accuracy and completeness. Accounts must not be kept "off-book" to facilitate or conceal improper payments. In principle, you are not allowed to accept gifts from or give gifts to clients. This does not include gifts to or from clients of up to EUR 20 (gross) or equivalent, which are always permissible, provided the client is not a public official. Accepting and giving gifts in the form of cash or cash equivalents, such as vouchers for cash payment, is prohibited in all cases and without exception. If you are taxable outside Germany, and you accept a gift whose value exceeds EUR 20 (gross) or equivalent in connection with your work for the Bank, you must notify Compliance London and Human Resources London by e-mail, giving the name and address of the company/person from whom the gift originated, a description of the gift and its value and your name, so that Human Resources can check the extent to which a tax deduction is required. If a refusal of a gift over EUR 20 (gross) is not possible, for reasons of politeness, for instance, and you are taxable in Germany, you must report all gifts received whose value exceeds EUR 20 (gross), without delay, for the purpose of taxation as a “non-cash benefit in kind”, using the form “Notification to AFC Compliance and Human Resources regarding the acceptance of taxable benefits in kind (gifts exceeding EUR 20 (gross) or equivalent) by an employee”. This form is to be completed and submitted to AFC Compliance. AFC Compliance will assess whether the gift can be accepted or should be rejected, informs the employee accordingly, and then forwards the form to the Human Resources department. If you accept a gift over 20 EUR (gross), you should also inform the giver that they should refrain from giving gifts in the future. Gifts given to family members may not be accepted and perishable items (i.e.: food) must be shared internally with the London branch. | D7: rag | E7: 5 | F7: 5 | G7: 5 | H7: 5 | I7: 4 | J7: 4.9125 | K7: 24 | L7: 0.44583142 | M7: 4 | N7: The AI response is highly accurate, relevant, complete, and clear, effectively addressing the user's query about recording a gift. It demonstrates strong implicit grounding in the provided snippets, although it would benefit from explicit citations to enhance citation quality. | O7: FALSE | S7: =VLOOKUP($B7,'Gemini RAW'!$A:$Q,2,FALSE) -> You are required to keep a written record of all hospitality and gifts given or received, so that this can be reviewed by AFC Compliance. You must submit all expenses claims relating to hospitality, gifts or payments to third parties and record the reason for expenditure, in accordance with Berenberg's expenses policy. All accounts, invoices, and other records relating to dealings with third parties including suppliers and customers should be prepared with strict accuracy and completeness. Accounts must not be kept "off-book" to facilitate or conceal improper payments. In principle, you are not allowed to accept gifts from or give gifts to clients. This does not include gifts to or from clients of up to EUR 20 (gross) or equivalent, which are always permissible, provided the client is not a public official. Accepting and giving gifts in the form of cash or cash equivalents, such as vouchers for cash payment, is prohibited in all cases and without exception. If you are taxable outside Germany, and you accept a gift whose value exceeds EUR 20 (gross) or equivalent in connection with your work for the Bank, you must notify Compliance London and Human Resources London by e-mail, giving the name and address of the company/person from whom the gift originated, a description of the gift and its value and your name, so that Human Resources can check the extent to which a tax deduction is required. If a refusal of a gift over EUR 20 (gross) is not possible, for reasons of politeness, for instance, and you are taxable in Germany, you must report all gifts received whose value exceeds EUR 20 (gross), without delay, for the purpose of taxation as a “non-cash benefit in kind”, using the form “Notification to AFC Compliance and Human Resources regarding the acceptance of taxable benefits in kind (gifts exceeding EUR 20 (gross) or equivalent) by an employee”. This form is to be completed and submitted to AFC Compliance. AFC Compliance will assess whether the gift can be accepted or should be rejected, informs the employee accordingly, and then forwards the form to the Human Resources department. If you accept a gift over 20 EUR (gross), you should also inform the giver that they should refrain from giving gifts in the future. Gifts given to family members may not be accepted and perishable items (i.e.: food) must be shared internally with the London branch. | T7: =VLOOKUP($B7,'Gemini RAW'!$A:$Q,3,FALSE) -> rag | U7: =VLOOKUP($B7,'Gemini RAW'!$A:$Q,4,FALSE) -> 5 | V7: =VLOOKUP($B7,'Gemini RAW'!$A:$Q,5,FALSE) -> 5 | W7: =VLOOKUP($B7,'Gemini RAW'!$A:$Q,6,FALSE) -> 5 | X7: =VLOOKUP($B7,'Gemini RAW'!$A:$Q,7,FALSE) -> 5 | Y7: =VLOOKUP($B7,'Gemini RAW'!$A:$Q,8,FALSE) -> 3 | Z7: =VLOOKUP($B7,'Gemini RAW'!$A:$Q,9,FALSE) -> 4.88 | AA7: =VLOOKUP($B7,'Gemini RAW'!$A:$Q,10,FALSE) -> 23 | AB7: =VLOOKUP($B7,'Gemini RAW'!$A:$Q,11,FALSE) -> 0.44583142 | AC7: =VLOOKUP($B7,'Gemini RAW'!$A:$Q,12,FALSE) -> 4 | AD7: =VLOOKUP($B7,'Gemini RAW'!$A:$Q,13,FALSE) -> The response is excellent in terms of content quality, providing accurate, relevant, complete, and clear information. The response directly addresses the user's query and offers comprehensive guidance on gift recording and reporting. The citation quality is satisfactory, as the response does not explicitly cite the source snippets, but the information is grounded in the provided text. | AE7: =VLOOKUP($B7,'Gemini RAW'!$A:$Q,14,FALSE) -> FALSE | AF7: =VLOOKUP($B7,'Gemini RAW'!$A:$Q,15,FALSE) -> 0 | AG7: =VLOOKUP($B7,'Gemini RAW'!$A:$Q,16,FALSE) -> 0 | AH7: =VLOOKUP($B7,'Gemini RAW'!$A:$Q,17,FALSE) -> 0
A8: 7 | B8: Where do I log gifts or hospitality that I give or receive? | C8: You are required to keep a written record of all hospitality and gifts given or received, so that this can be reviewed by AFC Compliance. You must also submit all expenses claims relating to hospitality, gifts or payments to third parties and record the reason for expenditure, in accordance with Berenberg's expenses policy. Employees who accept a gift whose value exceeds EUR 20 (gross) or equivalent in connection with their work for the Bank must notify Compliance London and Human Resources London by e-mail. The email should include the name and address of the company/person from whom the gift originated, a description of the gift and its value (plausible estimate) and the name of the employee, so that Human Resources can check the extent to which a tax deduction is required. Employees who are taxable outside Germany and, in connection with their work for the Bank, take part for free in an event without a predominant business character whose value exceeds EUR 20 (gross) or equivalent, must also report this to Human Resources so that the latter can check the extent to which a tax deduction is required. Tax must also be notified of events and hospitality services that the Bank offers and provides for the benefit of individual clients or business partners. The relevant department or company is responsible for the notification, which must be made in good time before the event takes place or the hospitality is provided. | D8: rag | E8: 5 | F8: 5 | G8: 5 | H8: 5 | I8: 4 | J8: 4.9125 | K8: 24 | L8: 0.39263081 | M8: 3 | N8: The AI response is exemplary in addressing the user query with high factual accuracy, relevance, completeness, and clarity. It effectively synthesizes information from the snippets, although the lack of explicit citations slightly detracts from the citation quality score. Overall, it meets and exceeds academic standards. | O8: FALSE | S8: =VLOOKUP($B8,'Gemini RAW'!$A:$Q,2,FALSE) -> You are required to keep a written record of all hospitality and gifts given or received, so that this can be reviewed by AFC Compliance. You must also submit all expenses claims relating to hospitality, gifts or payments to third parties and record the reason for expenditure, in accordance with Berenberg's expenses policy. Employees who accept a gift whose value exceeds EUR 20 (gross) or equivalent in connection with their work for the Bank must notify Compliance London and Human Resources London by e-mail. The email should include the name and address of the company/person from whom the gift originated, a description of the gift and its value (plausible estimate) and the name of the employee, so that Human Resources can check the extent to which a tax deduction is required. Employees who are taxable outside Germany and, in connection with their work for the Bank, take part for free in an event without a predominant business character whose value exceeds EUR 20 (gross) or equivalent, must also report this to Human Resources so that the latter can check the extent to which a tax deduction is required. Tax must also be notified of events and hospitality services that the Bank offers and provides for the benefit of individual clients or business partners. The relevant department or company is responsible for the notification, which must be made in good time before the event takes place or the hospitality is provided. | T8: =VLOOKUP($B8,'Gemini RAW'!$A:$Q,3,FALSE) -> rag | U8: =VLOOKUP($B8,'Gemini RAW'!$A:$Q,4,FALSE) -> 4 | V8: =VLOOKUP($B8,'Gemini RAW'!$A:$Q,5,FALSE) -> 5 | W8: =VLOOKUP($B8,'Gemini RAW'!$A:$Q,6,FALSE) -> 4 | X8: =VLOOKUP($B8,'Gemini RAW'!$A:$Q,7,FALSE) -> 4 | Y8: =VLOOKUP($B8,'Gemini RAW'!$A:$Q,8,FALSE) -> 1 | Z8: =VLOOKUP($B8,'Gemini RAW'!$A:$Q,9,FALSE) -> 3.16 | AA8: =VLOOKUP($B8,'Gemini RAW'!$A:$Q,10,FALSE) -> 18 | AB8: =VLOOKUP($B8,'Gemini RAW'!$A:$Q,11,FALSE) -> 0.39263081 | AC8: =VLOOKUP($B8,'Gemini RAW'!$A:$Q,12,FALSE) -> 3 | AD8: =VLOOKUP($B8,'Gemini RAW'!$A:$Q,13,FALSE) -> The response is relevant and mostly accurate, providing useful information about logging gifts and hospitality. However, it lacks explicit citations and fails to address important aspects such as GDPR compliance, EU AI Act alignment, and audit trail quality. The absence of citations significantly reduces the trustworthiness and verifiability of the information. | AE8: =VLOOKUP($B8,'Gemini RAW'!$A:$Q,14,FALSE) -> FALSE | AF8: =VLOOKUP($B8,'Gemini RAW'!$A:$Q,15,FALSE) -> 0 | AG8: =VLOOKUP($B8,'Gemini RAW'!$A:$Q,16,FALSE) -> 0 | AH8: =VLOOKUP($B8,'Gemini RAW'!$A:$Q,17,FALSE) -> 0
A9: 8 | B9: Do business meals with clients count as hospitality that must be recorded? | C9: Business meals with clients can be considered hospitality that must be recorded. Business meals must take place within a usual and appropriate setting. Local conditions must be taken into account, which means that comparable circumstances may be assessed differently according to the location of the business meal. If the hospitality costs less than EUR 50 (gross) per person, the circumstances for the business meal are generally considered to be usual and appropriate. This amount is the guide cost for ordinary business meals (e.g., lunch meeting for mutual exchange, short update with business partners). For business meals for a special occasion (e.g., detailed strategy talks with clients, discussion of investment opportunities), the guide cost is EUR 100 (gross) per person. These limits are not absolute. In individual cases, costs of between EUR 100 and EUR 250 (gross) per person may also be usual and appropriate (e.g., closing dinner in the context of a capital market transaction). If the cost of the business meal invitation exceeds EUR 250 (gross), AFC Compliance must always examine the individual case. If necessary, AFC Compliance will coordinate internally with the Legal department. Multiple business meals with the same person must be proportionate. If in doubt, you should consult AFC Compliance. Invitations to private clients or company owners for business meals are generally permitted, but you must always ensure that the costs are proportionate to the reason for the hospitality. Examples of reasonable and proportionate entertainment deemed to be acceptable (provided its value falls below the limit of GBP 500 (gross) per head) include invitations to a business lunch or dinner (which would generally be considered to be reasonable and proportionate where the value is less than GBP 100 (gross) per head). For it to be considered entertainment, the third party must be in attendance, otherwise the invitation will be considered a gift. Berenberg-hosted entertainment/events and 'normal course of business' hospitality - such as one-on-one third-party lunches and dinners - are permissible provided that the cost of the entertainment/event or hospitality does not exceed GBP 500 (gross) per head. Even if the overall cost per head is below GBP 500 (gross), the provision of entertainment and hospitality is only permitted if it is reasonable and proportionate (for example, for a business lunch or dinner it would generally be considered to be reasonable and proportionate where the value is less than GBP 100 (gross) per head) such that it is unlikely to have any influence on any invitee(s) in consideration of their individual circumstances (such as their professional position and financial circumstances), and does not appear improper. You are required to keep a written record of all hospitality and gifts given or received, so that this can be reviewed by AFC Compliance. You must submit all expenses claims relating to hospitality, gifts or payments to third parties and record the reason for expenditure, in accordance with our expenses policy. | D9: rag | E9: 4 | F9: 5 | G9: 4 | H9: 4 | I9: 3 | J9: 4.1625 | K9: 20 | L9: 0.40686522 | M9: 6 | N9: The AI response effectively addresses the user's query with relevant and accurate information regarding business meals as hospitality. While it demonstrates good clarity and relevance, the lack of explicit citations and some minor gaps in completeness prevent it from achieving a higher score in citation quality. Overall, it meets high academic standards but could benefit from improved sourcing. | O9: FALSE | S9: =VLOOKUP($B9,'Gemini RAW'!$A:$Q,2,FALSE) -> Business meals with clients can be considered hospitality that must be recorded. Business meals must take place within a usual and appropriate setting. Local conditions must be taken into account, which means that comparable circumstances may be assessed differently according to the location of the business meal. If the hospitality costs less than EUR 50 (gross) per person, the circumstances for the business meal are generally considered to be usual and appropriate. This amount is the guide cost for ordinary business meals (e.g., lunch meeting for mutual exchange, short update with business partners). For business meals for a special occasion (e.g., detailed strategy talks with clients, discussion of investment opportunities), the guide cost is EUR 100 (gross) per person. These limits are not absolute. In individual cases, costs of between EUR 100 and EUR 250 (gross) per person may also be usual and appropriate (e.g., closing dinner in the context of a capital market transaction). If the cost of the business meal invitation exceeds EUR 250 (gross), AFC Compliance must always examine the individual case. If necessary, AFC Compliance will coordinate internally with the Legal department. Multiple business meals with the same person must be proportionate. If in doubt, you should consult AFC Compliance. Invitations to private clients or company owners for business meals are generally permitted, but you must always ensure that the costs are proportionate to the reason for the hospitality. Examples of reasonable and proportionate entertainment deemed to be acceptable (provided its value falls below the limit of GBP 500 (gross) per head) include invitations to a business lunch or dinner (which would generally be considered to be reasonable and proportionate where the value is less than GBP 100 (gross) per head). For it to be considered entertainment, the third party must be in attendance, otherwise the invitation will be considered a gift. Berenberg-hosted entertainment/events and 'normal course of business' hospitality - such as one-on-one third-party lunches and dinners - are permissible provided that the cost of the entertainment/event or hospitality does not exceed GBP 500 (gross) per head. Even if the overall cost per head is below GBP 500 (gross), the provision of entertainment and hospitality is only permitted if it is reasonable and proportionate (for example, for a business lunch or dinner it would generally be considered to be reasonable and proportionate where the value is less than GBP 100 (gross) per head) such that it is unlikely to have any influence on any invitee(s) in consideration of their individual circumstances (such as their professional position and financial circumstances), and does not appear improper. You are required to keep a written record of all hospitality and gifts given or received, so that this can be reviewed by AFC Compliance. You must submit all expenses claims relating to hospitality, gifts or payments to third parties and record the reason for expenditure, in accordance with our expenses policy. | T9: =VLOOKUP($B9,'Gemini RAW'!$A:$Q,3,FALSE) -> rag | U9: =VLOOKUP($B9,'Gemini RAW'!$A:$Q,4,FALSE) -> 4 | V9: =VLOOKUP($B9,'Gemini RAW'!$A:$Q,5,FALSE) -> 5 | W9: =VLOOKUP($B9,'Gemini RAW'!$A:$Q,6,FALSE) -> 4 | X9: =VLOOKUP($B9,'Gemini RAW'!$A:$Q,7,FALSE) -> 4 | Y9: =VLOOKUP($B9,'Gemini RAW'!$A:$Q,8,FALSE) -> 1 | Z9: =VLOOKUP($B9,'Gemini RAW'!$A:$Q,9,FALSE) -> 3.16 | AA9: =VLOOKUP($B9,'Gemini RAW'!$A:$Q,10,FALSE) -> 18 | AB9: =VLOOKUP($B9,'Gemini RAW'!$A:$Q,11,FALSE) -> 0.40686522 | AC9: =VLOOKUP($B9,'Gemini RAW'!$A:$Q,12,FALSE) -> 6 | AD9: =VLOOKUP($B9,'Gemini RAW'!$A:$Q,13,FALSE) -> The response is relevant and generally accurate in addressing the user's query. It provides useful information about business meals and hospitality, including cost limits and the need for recording. However, it lacks citations and does not address GDPR, EU AI Act, or audit trail requirements. The absence of citations is a significant weakness. | AE9: =VLOOKUP($B9,'Gemini RAW'!$A:$Q,14,FALSE) -> FALSE | AF9: =VLOOKUP($B9,'Gemini RAW'!$A:$Q,15,FALSE) -> 0 | AG9: =VLOOKUP($B9,'Gemini RAW'!$A:$Q,16,FALSE) -> 0 | AH9: =VLOOKUP($B9,'Gemini RAW'!$A:$Q,17,FALSE) -> 0
A10: 9 | B10: Can I accept hospitality during a tender process? | C10: You must not give or accept a gift or hospitality during any commercial negotiations or tender process, if this could be perceived as intending or likely to influence the outcome. Accepting entertainment or hospitality during the normal course of business is permitted, subject to requirements. The true value of the entertainment or hospitality must not exceed GBP 500 (gross) per head. The invitation must be sent to you at your Berenberg business address. The nature of the entertainment or hospitality must be reasonable and proportionate in relation to your position as a Berenberg employee and must not give rise to any improper performance of your duties with respect to the third party. For a business lunch or dinner it would generally be considered to be reasonable and proportionate where the value is less than GBP 100 (gross) per head. The invitation must not be extended to your family members or close associates outside of Berenberg. You must not accept an offer to reimburse your travel and/or accommodation expenses without prior authorisation from AFC Compliance. Research Analysts are never permitted to accept any travel or accommodation. If Research Analysts accept entertainment or attend events hosted by third parties, all associated costs must be borne by Berenberg. All entertainment and hospitality must comply with any applicable local law. For it to be considered entertainment, the third party must be in attendance, otherwise the invitation will be considered a gift. All entertainment/events and hospitality exceeding GBP 500 (gross) per head require prior approval by the Head of the London Branch and AFC Compliance. | D10: rag | E10: 5 | F10: 5 | G10: 5 | H10: 5 | I10: 4 | J10: 4.9125 | K10: 24 | L10: 0.38018325 | M10: 7 | N10: The AI response is highly accurate, relevant, complete, and clear, effectively addressing the user's query about hospitality during a tender process. While it lacks explicit citations, it demonstrates strong implicit grounding in the provided snippets, particularly in outlining the rules and conditions for accepting hospitality. | O10: FALSE | S10: =VLOOKUP($B10,'Gemini RAW'!$A:$Q,2,FALSE) -> You must not give or accept a gift or hospitality during any commercial negotiations or tender process, if this could be perceived as intending or likely to influence the outcome. Accepting entertainment or hospitality during the normal course of business is permitted, subject to requirements. The true value of the entertainment or hospitality must not exceed GBP 500 (gross) per head. The invitation must be sent to you at your Berenberg business address. The nature of the entertainment or hospitality must be reasonable and proportionate in relation to your position as a Berenberg employee and must not give rise to any improper performance of your duties with respect to the third party. For a business lunch or dinner it would generally be considered to be reasonable and proportionate where the value is less than GBP 100 (gross) per head. The invitation must not be extended to your family members or close associates outside of Berenberg. You must not accept an offer to reimburse your travel and/or accommodation expenses without prior authorisation from AFC Compliance. Research Analysts are never permitted to accept any travel or accommodation. If Research Analysts accept entertainment or attend events hosted by third parties, all associated costs must be borne by Berenberg. All entertainment and hospitality must comply with any applicable local law. For it to be considered entertainment, the third party must be in attendance, otherwise the invitation will be considered a gift. All entertainment/events and hospitality exceeding GBP 500 (gross) per head require prior approval by the Head of the London Branch and AFC Compliance. | T10: =VLOOKUP($B10,'Gemini RAW'!$A:$Q,3,FALSE) -> rag | U10: =VLOOKUP($B10,'Gemini RAW'!$A:$Q,4,FALSE) -> 4 | V10: =VLOOKUP($B10,'Gemini RAW'!$A:$Q,5,FALSE) -> 5 | W10: =VLOOKUP($B10,'Gemini RAW'!$A:$Q,6,FALSE) -> 4 | X10: =VLOOKUP($B10,'Gemini RAW'!$A:$Q,7,FALSE) -> 4 | Y10: =VLOOKUP($B10,'Gemini RAW'!$A:$Q,8,FALSE) -> 1 | Z10: =VLOOKUP($B10,'Gemini RAW'!$A:$Q,9,FALSE) -> 3.16 | AA10: =VLOOKUP($B10,'Gemini RAW'!$A:$Q,10,FALSE) -> 18 | AB10: =VLOOKUP($B10,'Gemini RAW'!$A:$Q,11,FALSE) -> 0.38018325 | AC10: =VLOOKUP($B10,'Gemini RAW'!$A:$Q,12,FALSE) -> 7 | AD10: =VLOOKUP($B10,'Gemini RAW'!$A:$Q,13,FALSE) -> The response is relevant and generally accurate, providing useful guidelines on accepting hospitality during a tender process. However, it lacks any form of citation or referencing, which significantly reduces its academic value. Furthermore, it fails to address GDPR compliance, EU AI Act alignment, or audit trail quality, indicating a lack of consideration for these important aspects of AI system assessment. | AE10: =VLOOKUP($B10,'Gemini RAW'!$A:$Q,14,FALSE) -> FALSE | AF10: =VLOOKUP($B10,'Gemini RAW'!$A:$Q,15,FALSE) -> 0 | AG10: =VLOOKUP($B10,'Gemini RAW'!$A:$Q,16,FALSE) -> 0 | AH10: =VLOOKUP($B10,'Gemini RAW'!$A:$Q,17,FALSE) -> 0
A11: 10 | B11: Is it okay to offer a gift if I do not expect anything in return? | C11: Gifts are a mark of friendship and appreciation, provided without expectation of consideration or value in return. There should be 'no strings attached', either implicit or explicit. Being clear about the intention is key in determining whether accepting or receiving gifts is reasonable, proportionate and not improper. Gifts should have no other purpose than either establishing, maintaining, or enhancing a business relationship, improving or maintaining image or reputation or marketing or presenting goods and services effectively. However, Berenberg employees are subject to highly restrictive regulations regarding the acceptance and giving of gifts. You should inform anyone giving or expecting to receive a gift of these restrictions. Gifts may only be given or accepted under very specific, narrowly defined conditions. Generally, you are not allowed to accept gifts from or give gifts to clients. This does not include gifts to or from clients of up to EUR 20 (gross) or equivalent, which are always permissible, provided the client is not a public official. Gifts with a gross value of more than EUR 20 from a (potential) client/business partner to employees must be declined. Gifts offered to family members, relatives or close associates of Berenberg employees may not be accepted. Gifts must be given openly, not secretly. All gifts must comply with any applicable local law. The value of the gift is a key consideration, as the greater the expense the greater the scope for potential improper influence. Berenberg applies specific value limits on permissible gifts, above which AFC Compliance determination will be required. Even when the value threshold is not met, AFC Compliance will still determine that the gift is improper. The Bank does not consider gifts of more than EUR 250 (gross) to be usual and appropriate. The timing of the gift will also be a key factor in determining whether there is anything improper at play. For example, the provision or receipt of gifts shortly before a key decision by a customer or Berenberg may give rise to suspicions. If refusing a gift may cause significant offense or embarrassment, the gift may be accepted. In such instances, it should then, in consultation with AFC Compliance, be donated without delay, for instance to a charity of the Bank's choosing or put to another use in the Bank's interests. If you accept a gift, you must notify your line manager appropriately. Cases of doubt must always be agreed with AFC Compliance in advance but in any case without delay. The giving of gifts to third parties is generally not permitted unless, in consultation with AFC Compliance and senior management, a reasonable business justification is determined and the gift is considered appropriate in the circumstances. In such case, the requirements under sections 7.2 and 7.3 must be complied with and the gift must be given in the name of Berenberg and not from you personally. | D11: rag | E11: 4 | F11: 5 | G11: 4 | H11: 4 | I11: 3 | J11: 4.1625 | K11: 20 | L11: 0.35627282 | M11: 4 | N11: The AI response effectively addresses the user's query about gift-giving, providing relevant information about the regulations that govern such actions in a business context. While it demonstrates a strong understanding of the topic, it could improve by incorporating explicit citations and enhancing clarity in some areas. Overall, it meets high academic standards but has room for improvement in citation quality and completeness. | O11: FALSE | S11: =VLOOKUP($B11,'Gemini RAW'!$A:$Q,2,FALSE) -> Gifts are a mark of friendship and appreciation, provided without expectation of consideration or value in return. There should be 'no strings attached', either implicit or explicit. Being clear about the intention is key in determining whether accepting or receiving gifts is reasonable, proportionate and not improper. Gifts should have no other purpose than either establishing, maintaining, or enhancing a business relationship, improving or maintaining image or reputation or marketing or presenting goods and services effectively. However, Berenberg employees are subject to highly restrictive regulations regarding the acceptance and giving of gifts. You should inform anyone giving or expecting to receive a gift of these restrictions. Gifts may only be given or accepted under very specific, narrowly defined conditions. Generally, you are not allowed to accept gifts from or give gifts to clients. This does not include gifts to or from clients of up to EUR 20 (gross) or equivalent, which are always permissible, provided the client is not a public official. Gifts with a gross value of more than EUR 20 from a (potential) client/business partner to employees must be declined. Gifts offered to family members, relatives or close associates of Berenberg employees may not be accepted. Gifts must be given openly, not secretly. All gifts must comply with any applicable local law. The value of the gift is a key consideration, as the greater the expense the greater the scope for potential improper influence. Berenberg applies specific value limits on permissible gifts, above which AFC Compliance determination will be required. Even when the value threshold is not met, AFC Compliance will still determine that the gift is improper. The Bank does not consider gifts of more than EUR 250 (gross) to be usual and appropriate. The timing of the gift will also be a key factor in determining whether there is anything improper at play. For example, the provision or receipt of gifts shortly before a key decision by a customer or Berenberg may give rise to suspicions. If refusing a gift may cause significant offense or embarrassment, the gift may be accepted. In such instances, it should then, in consultation with AFC Compliance, be donated without delay, for instance to a charity of the Bank's choosing or put to another use in the Bank's interests. If you accept a gift, you must notify your line manager appropriately. Cases of doubt must always be agreed with AFC Compliance in advance but in any case without delay. The giving of gifts to third parties is generally not permitted unless, in consultation with AFC Compliance and senior management, a reasonable business justification is determined and the gift is considered appropriate in the circumstances. In such case, the requirements under sections 7.2 and 7.3 must be complied with and the gift must be given in the name of Berenberg and not from you personally. | T11: =VLOOKUP($B11,'Gemini RAW'!$A:$Q,3,FALSE) -> rag | U11: =VLOOKUP($B11,'Gemini RAW'!$A:$Q,4,FALSE) -> 4 | V11: =VLOOKUP($B11,'Gemini RAW'!$A:$Q,5,FALSE) -> 5 | W11: =VLOOKUP($B11,'Gemini RAW'!$A:$Q,6,FALSE) -> 4 | X11: =VLOOKUP($B11,'Gemini RAW'!$A:$Q,7,FALSE) -> 4 | Y11: =VLOOKUP($B11,'Gemini RAW'!$A:$Q,8,FALSE) -> 2 | Z11: =VLOOKUP($B11,'Gemini RAW'!$A:$Q,9,FALSE) -> 3.22 | AA11: =VLOOKUP($B11,'Gemini RAW'!$A:$Q,10,FALSE) -> 19 | AB11: =VLOOKUP($B11,'Gemini RAW'!$A:$Q,11,FALSE) -> 0.35627282 | AC11: =VLOOKUP($B11,'Gemini RAW'!$A:$Q,12,FALSE) -> 4 | AD11: =VLOOKUP($B11,'Gemini RAW'!$A:$Q,13,FALSE) -> The response is relevant and generally accurate, providing a nuanced answer to the user's query. However, it lacks explicit citations and does not address GDPR or EU AI Act compliance. The inclusion of specific company policies (Berenberg) adds detail but could reduce clarity for a general audience. The response effectively uses the provided snippets to ground its claims, but the absence of explicit citations is a significant weakness. | AE11: =VLOOKUP($B11,'Gemini RAW'!$A:$Q,14,FALSE) -> FALSE | AF11: =VLOOKUP($B11,'Gemini RAW'!$A:$Q,15,FALSE) -> 0 | AG11: =VLOOKUP($B11,'Gemini RAW'!$A:$Q,16,FALSE) -> 0 | AH11: =VLOOKUP($B11,'Gemini RAW'!$A:$Q,17,FALSE) -> 0
A12: 11 | B12: What if a gift could be seen as influencing business decisions? | C12: Gifts, entertainment, or hospitality should have no strings attached, either implicit or explicit. Being clear about the intention is key in determining whether accepting or receiving gifts, entertainment or hospitality is reasonable, proportionate and not improper. Gifts and entertainment must not be designed to influence the recipient. You must ensure that there is never any actual impropriety, or appearance of impropriety. Particular corruption risks arise when employees take part in or are invited by third parties (e.g. clients or business partners) to events, and give or accept hospitality or gifts (e.g. as a sign of recognition and gratitude). You are not permitted to accept or give gifts, invitations or hospitality if the purpose is to explicitly or implicitly induce the recipient to perform or behave in a particular way in return. The timing of the gift, hospitality or entertainment will also be a key factor in determining whether there is anything improper at play. For example, the provision or receipt of gifts, hospitality or entertainment shortly before a key decision by a customer or Berenberg may give rise to suspicions. Any surrounding circumstances which may render the gift or entertainment improper, such as pending business relationships, must be taken into account. | D12: rag | E12: 4 | F12: 5 | G12: 4 | H12: 4 | I12: 3 | J12: 4.1625 | K12: 20 | L12: 0.46752434 | M12: 5 | N12: The AI response effectively addresses the user's query about the influence of gifts on business decisions, demonstrating a strong understanding of the ethical implications involved. While it is factually accurate and relevant, it lacks explicit citations and could improve in completeness by incorporating specific compliance processes mentioned in the snippets. Overall, the response meets high academic standards but has room for improvement in citation quality and completeness. | O12: FALSE | S12: =VLOOKUP($B12,'Gemini RAW'!$A:$Q,2,FALSE) -> Gifts, entertainment, or hospitality should have no strings attached, either implicit or explicit. Being clear about the intention is key in determining whether accepting or receiving gifts, entertainment or hospitality is reasonable, proportionate and not improper. Gifts and entertainment must not be designed to influence the recipient. You must ensure that there is never any actual impropriety, or appearance of impropriety. Particular corruption risks arise when employees take part in or are invited by third parties (e.g. clients or business partners) to events, and give or accept hospitality or gifts (e.g. as a sign of recognition and gratitude). You are not permitted to accept or give gifts, invitations or hospitality if the purpose is to explicitly or implicitly induce the recipient to perform or behave in a particular way in return. The timing of the gift, hospitality or entertainment will also be a key factor in determining whether there is anything improper at play. For example, the provision or receipt of gifts, hospitality or entertainment shortly before a key decision by a customer or Berenberg may give rise to suspicions. Any surrounding circumstances which may render the gift or entertainment improper, such as pending business relationships, must be taken into account. | T12: =VLOOKUP($B12,'Gemini RAW'!$A:$Q,3,FALSE) -> rag | U12: =VLOOKUP($B12,'Gemini RAW'!$A:$Q,4,FALSE) -> 5 | V12: =VLOOKUP($B12,'Gemini RAW'!$A:$Q,5,FALSE) -> 5 | W12: =VLOOKUP($B12,'Gemini RAW'!$A:$Q,6,FALSE) -> 4 | X12: =VLOOKUP($B12,'Gemini RAW'!$A:$Q,7,FALSE) -> 5 | Y12: =VLOOKUP($B12,'Gemini RAW'!$A:$Q,8,FALSE) -> 2 | Z12: =VLOOKUP($B12,'Gemini RAW'!$A:$Q,9,FALSE) -> 4.68 | AA12: =VLOOKUP($B12,'Gemini RAW'!$A:$Q,10,FALSE) -> 21 | AB12: =VLOOKUP($B12,'Gemini RAW'!$A:$Q,11,FALSE) -> 0.46752434 | AC12: =VLOOKUP($B12,'Gemini RAW'!$A:$Q,12,FALSE) -> 5 | AD12: =VLOOKUP($B12,'Gemini RAW'!$A:$Q,13,FALSE) -> The response provides a factually accurate and relevant answer to the user's query. The content is clear and well-organized. However, the lack of explicit citations is a significant weakness. The response effectively uses the provided snippets to support its claims, but the absence of direct attribution detracts from its academic rigor. | AE12: =VLOOKUP($B12,'Gemini RAW'!$A:$Q,14,FALSE) -> FALSE | AF12: =VLOOKUP($B12,'Gemini RAW'!$A:$Q,15,FALSE) -> 0 | AG12: =VLOOKUP($B12,'Gemini RAW'!$A:$Q,16,FALSE) -> 0 | AH12: =VLOOKUP($B12,'Gemini RAW'!$A:$Q,17,FALSE) -> 0
A13: 12 | B13: Can I pay for a client’s travel or hotel as hospitality? | C13: Berenberg employees may be invited to attend external events by third parties. However, invitations must be sent to the employee's Berenberg business address. You must not accept an offer to reimburse your travel and/or accommodation expenses without prior authorization from AFC Compliance. If a Berenberg research analyst is invited to an event organized by a sell-side company, they are never permitted to accept travel or accommodation. If research analysts attend entertainment or events hosted by third parties, all associated costs must be borne by Berenberg. Berenberg-hosted entertainment/events and 'normal course of business' hospitality - such as one-on-one third-party lunches and dinners - are permissible provided that the cost does not exceed GBP 500 (gross) per head and other requirements are met. Third party expenses such as travel and/or accommodation may only be paid for/reimbursed by Berenberg where such costs are genuine, reasonable and necessary. For example, this may be the case where a conference is run over two days or as a result of the location, traveling on the day of the event is impractical. Acceptance of travel or accommodation reimbursement must not result in the third party receiving more than their reasonable costs, with prior approval from AFC Compliance. Approval from AFC Compliance is not required for pre-arranged shuttle services to/from an event location which are reasonable, for example, Berenberg conference locations which are difficult to reach by public transport alone. As a general rule, third party expenses for pure client entertainment (such as organised shoots) should not be paid by the Bank as such costs are not considered to be necessary, reasonable or proportionate. Exceptions may be approved by AFC Compliance on a case by case basis. All entertainment and hospitality must comply with any applicable local law where the event is taking place or which applies for any reason that you become aware of. Business meals must take place within a usual and appropriate setting. If the hospitality costs less than EUR 50 (gross) per person, the circumstances for the business meal are generally considered to be usual and appropriate. This amount is the guide cost for ordinary business meals (e.g. lunch meeting for mutual exchange, short update with business partners). For business meals for a special occasion (e.g. detailed strategy talks with clients, discussion of investment opportunities), the guide cost is EUR 100 (gross) per person. In individual cases, costs of between EUR 100 and EUR 250 (gross) per person may also be usual and appropriate (e.g. closing dinner in the context of a capital market transaction). The nature of the entertainment or hospitality must be reasonable and proportionate in relation to your position as a Berenberg employee and must not give rise to any improper performance of your duties with respect to the third party. For example, for a business lunch or dinner it would generally be considered to be reasonable and proportionate where the value is less than GBP 100 (gross) per head. The invitation must not be extended to your family members or close associates outside of Berenberg. No gifts may be offered or given to public officials. Likewise, no gifts may be accepted from such persons. Invitations to events and the provision of hospitality are only permitted under strict conditions. The amount of the benefit may not exceed EUR 20 (gross) per person. In all cases, you must obtain the employer's permission or written confirmation from the public official that the necessary employer's permission has been obtained. You must specifically state the amount of the benefit per person, otherwise the employer's permission cannot be effectively granted due to lack of transparency. | D13: rag | E13: 4 | F13: 5 | G13: 4 | H13: 4 | I13: 3 | J13: 4.1625 | K13: 20 | L13: 0.41458523 | M13: 5 | N13: The AI response effectively addresses the user's query with a high degree of relevance and factual accuracy. It provides a clear and organized overview of Berenberg's hospitality policies, although it lacks explicit citations to the snippets. Overall, it meets high academic standards but could improve in citation quality and completeness by integrating more specific examples. | O13: FALSE | S13: =VLOOKUP($B13,'Gemini RAW'!$A:$Q,2,FALSE) -> Berenberg employees may be invited to attend external events by third parties. However, invitations must be sent to the employee's Berenberg business address. You must not accept an offer to reimburse your travel and/or accommodation expenses without prior authorization from AFC Compliance. If a Berenberg research analyst is invited to an event organized by a sell-side company, they are never permitted to accept travel or accommodation. If research analysts attend entertainment or events hosted by third parties, all associated costs must be borne by Berenberg. Berenberg-hosted entertainment/events and 'normal course of business' hospitality - such as one-on-one third-party lunches and dinners - are permissible provided that the cost does not exceed GBP 500 (gross) per head and other requirements are met. Third party expenses such as travel and/or accommodation may only be paid for/reimbursed by Berenberg where such costs are genuine, reasonable and necessary. For example, this may be the case where a conference is run over two days or as a result of the location, traveling on the day of the event is impractical. Acceptance of travel or accommodation reimbursement must not result in the third party receiving more than their reasonable costs, with prior approval from AFC Compliance. Approval from AFC Compliance is not required for pre-arranged shuttle services to/from an event location which are reasonable, for example, Berenberg conference locations which are difficult to reach by public transport alone. As a general rule, third party expenses for pure client entertainment (such as organised shoots) should not be paid by the Bank as such costs are not considered to be necessary, reasonable or proportionate. Exceptions may be approved by AFC Compliance on a case by case basis. All entertainment and hospitality must comply with any applicable local law where the event is taking place or which applies for any reason that you become aware of. Business meals must take place within a usual and appropriate setting. If the hospitality costs less than EUR 50 (gross) per person, the circumstances for the business meal are generally considered to be usual and appropriate. This amount is the guide cost for ordinary business meals (e.g. lunch meeting for mutual exchange, short update with business partners). For business meals for a special occasion (e.g. detailed strategy talks with clients, discussion of investment opportunities), the guide cost is EUR 100 (gross) per person. In individual cases, costs of between EUR 100 and EUR 250 (gross) per person may also be usual and appropriate (e.g. closing dinner in the context of a capital market transaction). The nature of the entertainment or hospitality must be reasonable and proportionate in relation to your position as a Berenberg employee and must not give rise to any improper performance of your duties with respect to the third party. For example, for a business lunch or dinner it would generally be considered to be reasonable and proportionate where the value is less than GBP 100 (gross) per head. The invitation must not be extended to your family members or close associates outside of Berenberg. No gifts may be offered or given to public officials. Likewise, no gifts may be accepted from such persons. Invitations to events and the provision of hospitality are only permitted under strict conditions. The amount of the benefit may not exceed EUR 20 (gross) per person. In all cases, you must obtain the employer's permission or written confirmation from the public official that the necessary employer's permission has been obtained. You must specifically state the amount of the benefit per person, otherwise the employer's permission cannot be effectively granted due to lack of transparency. | T13: =VLOOKUP($B13,'Gemini RAW'!$A:$Q,3,FALSE) -> rag | U13: =VLOOKUP($B13,'Gemini RAW'!$A:$Q,4,FALSE) -> 5 | V13: =VLOOKUP($B13,'Gemini RAW'!$A:$Q,5,FALSE) -> 5 | W13: =VLOOKUP($B13,'Gemini RAW'!$A:$Q,6,FALSE) -> 4 | X13: =VLOOKUP($B13,'Gemini RAW'!$A:$Q,7,FALSE) -> 5 | Y13: =VLOOKUP($B13,'Gemini RAW'!$A:$Q,8,FALSE) -> 1 | Z13: =VLOOKUP($B13,'Gemini RAW'!$A:$Q,9,FALSE) -> 4.62 | AA13: =VLOOKUP($B13,'Gemini RAW'!$A:$Q,10,FALSE) -> 20 | AB13: =VLOOKUP($B13,'Gemini RAW'!$A:$Q,11,FALSE) -> 0.41458523 | AC13: =VLOOKUP($B13,'Gemini RAW'!$A:$Q,12,FALSE) -> 5 | AD13: =VLOOKUP($B13,'Gemini RAW'!$A:$Q,13,FALSE) -> The response provides a highly relevant, accurate, and clear answer to the user's query. It effectively outlines Berenberg's policies on hospitality and travel expenses. The main weakness is the lack of explicit citations to the source snippets. However, the content quality is strong enough to warrant a high overall assessment. | AE13: =VLOOKUP($B13,'Gemini RAW'!$A:$Q,14,FALSE) -> FALSE | AF13: =VLOOKUP($B13,'Gemini RAW'!$A:$Q,15,FALSE) -> 0 | AG13: =VLOOKUP($B13,'Gemini RAW'!$A:$Q,16,FALSE) -> 0 | AH13: =VLOOKUP($B13,'Gemini RAW'!$A:$Q,17,FALSE) -> 0
... A585: 584 | B585: Can I invite a public official to lunch and pay for it? | C585: Based on my search of the Gifts & Entertainment database for 'Can I invite a public official to lunch and pay for it?': No, you cannot invite a public official to lunch and pay for it, as it is prohibited to give gifts or accept gifts from government or public officials, which includes paying for accommodation and/or travel expenses. Sources: 1. #50228 Attachment 05 London Branch Anti-Bribery and Corruption Policy.pdf 2. #50228 Attachment 07 London Branch_GE_Guidance and Practical Scenarios.pdf 3. #50228 Guidelines for the prevention of all forms of corruption.pdf | D585: agentic | E585: 3 | F585: 4 | G585: 3 | H585: 4 | I585: 2 | J585: 3.325 | K585: 16 | L585: 0.27364486 | M585: 1 | N585: The AI response provides a relevant and clear answer to the user's query about inviting a public official to lunch. However, it lacks explicit grounding in the provided snippets and does not fully explore the implications of the prohibition, which affects its overall completeness and citation quality. Improvements in these areas would enhance the response's academic rigor. | O585: FALSE | S585: =VLOOKUP($B585,'Gemini RAW'!$A:$Q,2,FALSE) -> You can invite a public official to lunch and pay for it, but there are strict conditions. No gifts may be offered or given to public officials. Invitations to events and the provision of hospitality are only permitted under strict conditions. The amount of the benefit may not exceed EUR 20 (gross) per person. You must obtain the employer's permission or written confirmation from the public official that the necessary employer's permission has been obtained. You must specifically state the amount of the benefit per person, otherwise the employer's permission cannot be effectively granted due to lack of transparency. You should assume that benefits exceeding EUR 20 (gross) per person will not be approved. Criminal liability would not, therefore, cease to exist, despite the employer's permission. The respective department must already check at the business initiation stage (contact acquisition) whether the person is a public official in order to avoid an inadmissible invitation. Approaching a public official in their capacity of private client, i.e.: detached from his/her office, is possible in principle and does not invoke the strict rules relating to public officials. However, you must establish that Berenberg has no connection whatsoever with the official duties exercised by that person. According to German law, a public official is someone who is a civil servant or judge, is in a public-law official relationship, or is otherwise appointed to perform tasks of public administration. Foreign public officials as well as foreign and international employees can be equated with German public officials for the purposes of German criminal law, which require an official capacity. Conversely, persons who are not public officials under German law (e.g. members of parliament) may be public officials under foreign law. Examples of public officials include senators, mayors, and all employees and members of governing bodies of public-law institutions such as state banks, savings banks, professional pension funds, supplementary pension funds or chambers of industry and commerce, as well as municipal energy supply companies. Invitations to public officials, even to specialist events, are generally inadmissible. A service permit is a positive criterion, but can only be granted within the scope of the powers. It is questionable for amounts greater than EUR 20 (gross). If you are unsure whether a person is a public official, you must contact the Legal department, involving AFC Compliance if necessary. This must be established positively and not simply assumed. You must immediately contact the Legal department in all cases, involving AFC Compliance if necessary. Pending final clarification, the person must be treated as a public official. For employees in Research departments, to avoid conflicts of interest, analysts may not accept any gifts (including low-value ones) from issuers. Analysts may not allow issuers to pay or reimburse any travel and/or accommodation expenses. The same applies to the free provision of means of transport (e.g. travelling in the company's own aircraft). For employees who are not in the Research department, business meals are generally permitted for private clients or company owners, but you must always ensure that the costs are proportionate to the reason for the hospitality. If the cost of the business meal invitation exceeds EUR 250 (gross), AFC Compliance must always examine the individual case. If necessary, AFC Compliance will coordinate internally with the Legal department. You must always take into account the frequency of invitations in a calendar year. Multiple business meals with the same person must be proportionate. If in doubt, you should consult AFC Compliance. Reasonable and proportionate entertainment deemed to be acceptable (provided its value falls below the limit of GBP 500 (gross) per head) include invitations to a business lunch or dinner (which would generally be considered to be reasonable and proportionate where the value is less than GBP 100 (gross) per head). For it to be considered entertainment, the third party must be in attendance, otherwise the invitation will be considered a gift. Business lunches/dinners are defined as business meals (breakfast, lunch, dinner; even just drinks) with a focus on business character. The invitation should be made in advance, e.g. by business email or telephone, or spontaneously on the occasion of a business meeting. If the sketched format is observed, it is regularly permissible if there are no or predominantly no negative indications. Positive criteria include the format of the invitation and the amount of the allowance are in adequate proportion to the position or responsibility of the invitee in his company and/or to his financial circumstances. A bank-related, business reason for the business meal, pure "relationship management" is allowed. The costs of the catering are less than EUR 50 (gross) per person for ordinary business meals, and less than EUR 100 (gross) per person for business meals with a special occasion. (Note: These are not absolute limits). Negative indications include the invitee is involved in an upcoming decision of his company e.g. about the awarding of a mandate, the establishment of a business relationship or otherwise a business decision to the advantage of the bank. | T585: =VLOOKUP($B585,'Gemini RAW'!$A:$Q,3,FALSE) -> rag | U585: =VLOOKUP($B585,'Gemini RAW'!$A:$Q,4,FALSE) -> 4 | V585: =VLOOKUP($B585,'Gemini RAW'!$A:$Q,5,FALSE) -> 5 | W585: =VLOOKUP($B585,'Gemini RAW'!$A:$Q,6,FALSE) -> 4 | X585: =VLOOKUP($B585,'Gemini RAW'!$A:$Q,7,FALSE) -> 4 | Y585: =VLOOKUP($B585,'Gemini RAW'!$A:$Q,8,FALSE) -> 1 | Z585: =VLOOKUP($B585,'Gemini RAW'!$A:$Q,9,FALSE) -> 3.16 | AA585: =VLOOKUP($B585,'Gemini RAW'!$A:$Q,10,FALSE) -> 18 | AB585: =VLOOKUP($B585,'Gemini RAW'!$A:$Q,11,FALSE) -> 0.35843902 | AC585: =VLOOKUP($B585,'Gemini RAW'!$A:$Q,12,FALSE) -> 6 | AD585: =VLOOKUP($B585,'Gemini RAW'!$A:$Q,13,FALSE) -> The response is relevant and generally accurate, providing a detailed explanation of the conditions and limitations surrounding inviting a public official to lunch and paying for it. However, it suffers from a lack of citations, making it difficult to verify the information. Furthermore, it fails to address GDPR compliance and the EU AI Act, which are relevant considerations for an AI system providing this type of information. The absence of an audit trail further reduces its reliability. | AE585: =VLOOKUP($B585,'Gemini RAW'!$A:$Q,14,FALSE) -> FALSE | AF585: =VLOOKUP($B585,'Gemini RAW'!$A:$Q,15,FALSE) -> 0 | AG585: =VLOOKUP($B585,'Gemini RAW'!$A:$Q,16,FALSE) -> 0 | AH585: =VLOOKUP($B585,'Gemini RAW'!$A:$Q,17,FALSE) -> 0
A586: 585 | B586: What is considered “unduly lavish” hospitality? | C586: Based on web search results for 'What is considered “unduly lavish” hospitality?': 1. Corporate Governance Framework - Gifts and hospitality: Oct 29, 2021·You are not permitted to accept hospitality that might generally be regarded as unduly lavish, such as preferential access to cultural or 2. Global Anti-bribery and Corruption Policy - The CFO Center: accept hospitality from a third party that is unduly lavish or extravagant under the circumstances; or. e. threaten or retaliate against another individual 3. Anti-Corruption - The Global Goals: A gift or hospitality will not be appropriate if it is unduly lavish or extravagant, or could be seen as an inducement or reward for any preferential | D586: agentic | E586: 4 | F586: 5 | G586: 3 | H586: 4 | I586: 3 | J586: 3.975 | K586: 19 | L586: 0.21231015 | M586: 1 | N586: The AI response effectively addresses the user query regarding 'unduly lavish' hospitality with relevant information derived from the snippets. However, it lacks explicit citations and could improve in completeness by providing more detailed explanations or examples. Overall, it meets a good standard but has room for enhancement. | O586: TRUE | P586: TRUE | Q586: 393 | R586: 700 | S586: =VLOOKUP($B586,'Gemini RAW'!$A:$Q,2,FALSE) -> Accepting hospitality from a third party that is "unduly lavish or extravagant" is unacceptable. Berenberg-hosted entertainment and hospitality are permissible if the cost does not exceed GBP 500 (gross) per head. Even if the overall cost is below GBP 500, the provision of entertainment and hospitality is only permitted if it is reasonable and proportionate. For a business lunch or dinner, it would generally be considered reasonable and proportionate where the value is less than GBP 100 (gross) per head. Several factors can contribute to determining whether hospitality is "unduly lavish": * **Cost:** Hospitality costing less than EUR 50 (gross) per person is generally considered usual and appropriate for ordinary business meals. For special occasions, the guide cost is EUR 100 (gross) per person. Costs between EUR 100 and EUR 250 (gross) per person may also be usual and appropriate in individual cases. A cost exceeding EUR 250 (brutto) p.P. can be a negative indicator. * **Proportionality:** The format of the invitation and the amount of the benefit should be appropriate to the position or responsibility of the invitee in their company and/or to their financial circumstances. * **Transparency:** The invitation should be made in a transparent manner, using Berenberg's logo. * **Influence:** The hospitality should not be likely to have any influence on any invitee(s) in consideration of their individual circumstances. * **Timing:** Giving or accepting a gift or hospitality during any commercial negotiations or tender process is unacceptable if this could be perceived as intending or likely to influence the outcome. * **Nature of the event:** AFC Compliance may consider hospitality reasonable if it is an all-day event, the guests are high net worth individuals and senior management of listed companies, and the event is only taking place on a limited number of occasions. | T586: =VLOOKUP($B586,'Gemini RAW'!$A:$Q,3,FALSE) -> rag | U586: =VLOOKUP($B586,'Gemini RAW'!$A:$Q,4,FALSE) -> 4 | V586: =VLOOKUP($B586,'Gemini RAW'!$A:$Q,5,FALSE) -> 5 | W586: =VLOOKUP($B586,'Gemini RAW'!$A:$Q,6,FALSE) -> 4 | X586: =VLOOKUP($B586,'Gemini RAW'!$A:$Q,7,FALSE) -> 4 | Y586: =VLOOKUP($B586,'Gemini RAW'!$A:$Q,8,FALSE) -> 1 | Z586: =VLOOKUP($B586,'Gemini RAW'!$A:$Q,9,FALSE) -> 3.16 | AA586: =VLOOKUP($B586,'Gemini RAW'!$A:$Q,10,FALSE) -> 18 | AB586: =VLOOKUP($B586,'Gemini RAW'!$A:$Q,11,FALSE) -> 0.15575629 | AC586: =VLOOKUP($B586,'Gemini RAW'!$A:$Q,12,FALSE) -> 5 | AD586: =VLOOKUP($B586,'Gemini RAW'!$A:$Q,13,FALSE) -> The response is relevant and provides a good overview of what is considered "unduly lavish" hospitality. The factual accuracy is generally good, although some specific figures could benefit from external validation. The clarity and organization are strong. However, the lack of citations is a major weakness, and the response fails to address GDPR compliance, EU AI Act alignment, and audit trail quality. The response is strong in content but weak in source utilization and compliance aspects. | AE586: =VLOOKUP($B586,'Gemini RAW'!$A:$Q,14,FALSE) -> FALSE | AF586: =VLOOKUP($B586,'Gemini RAW'!$A:$Q,15,FALSE) -> 0 | AG586: =VLOOKUP($B586,'Gemini RAW'!$A:$Q,16,FALSE) -> 0 | AH586: =VLOOKUP($B586,'Gemini RAW'!$A:$Q,17,FALSE) -> 0
A587: 586 | B587: Who should I contact if I am unsure whether a gift is permissible? | C587: Based on my search of the Gifts & Entertainment database for 'Who should I contact if I am unsure whether a gift is permissible?': If you are unsure whether a gift is permissible, you should contact Compliance at ComplianceAML@berenberg.de. Sources: 1. #50228 Attachment 05 London Branch Anti-Bribery and Corruption Policy.pdf 2. #50228 Attachment 07 London Branch_GE_Guidance and Practical Scenarios.pdf 3. #50228 Guidelines for the prevention of all forms of corruption.pdf | D587: agentic | E587: 5 | F587: 5 | G587: 4 | H587: 5 | I587: 3 | J587: 4.6375 | K587: 22 | L587: 0.28235294 | M587: 1 | N587: The AI response effectively answers the user's query with accurate and relevant information. However, it could improve by providing more context and better integrating the cited sources to enhance citation quality. | O587: FALSE | S587: =VLOOKUP($B587,'Gemini RAW'!$A:$Q,2,FALSE) -> If you are unsure whether a gift is permissible, please contact ComplianceAML@berenberg.de. You can also contact the Legal department, involving AFC Compliance if necessary. Cases of doubt must always be agreed with AFC Compliance in advance but in any case without delay. If you are in any doubt, in the first instance you should refer to AFC Compliance. | T587: =VLOOKUP($B587,'Gemini RAW'!$A:$Q,3,FALSE) -> rag | U587: =VLOOKUP($B587,'Gemini RAW'!$A:$Q,4,FALSE) -> 5 | V587: =VLOOKUP($B587,'Gemini RAW'!$A:$Q,5,FALSE) -> 5 | W587: =VLOOKUP($B587,'Gemini RAW'!$A:$Q,6,FALSE) -> 5 | X587: =VLOOKUP($B587,'Gemini RAW'!$A:$Q,7,FALSE) -> 5 | Y587: =VLOOKUP($B587,'Gemini RAW'!$A:$Q,8,FALSE) -> 1 | Z587: =VLOOKUP($B587,'Gemini RAW'!$A:$Q,9,FALSE) -> 3.64 | AA587: =VLOOKUP($B587,'Gemini RAW'!$A:$Q,10,FALSE) -> 21 | AB587: =VLOOKUP($B587,'Gemini RAW'!$A:$Q,11,FALSE) -> 0.35002451 | AC587: =VLOOKUP($B587,'Gemini RAW'!$A:$Q,12,FALSE) -> 6 | AD587: =VLOOKUP($B587,'Gemini RAW'!$A:$Q,13,FALSE) -> The response provides a factually accurate, relevant, and complete answer to the user's query. The clarity of the response is excellent. However, the system lacks explicit citations and does not address GDPR compliance, EU AI Act alignment, or audit trail quality. The content quality is high, but the system needs improvement in terms of transparency and regulatory compliance. | AE587: =VLOOKUP($B587,'Gemini RAW'!$A:$Q,14,FALSE) -> FALSE | AF587: =VLOOKUP($B587,'Gemini RAW'!$A:$Q,15,FALSE) -> 0 | AG587: =VLOOKUP($B587,'Gemini RAW'!$A:$Q,16,FALSE) -> 0 | AH587: =VLOOKUP($B587,'Gemini RAW'!$A:$Q,17,FALSE) -> 0
A588: 587 | B588: What happens if I cannot politely refuse a gift that is not allowed? | C588: Based on my search of the Gifts & Entertainment database for 'What happens if I cannot politely refuse a gift that is not allowed?': If you cannot politely refuse a gift that is not allowed, you may accept it, but you should then consult with AFC Compliance and donate the gift without delay, for instance to a charity of the Bank’s choosing or put it to another use in the Bank’s interests. Additionally, you must notify your line manager appropriately. Cases of doubt must always be agreed with AFC Compliance in advance. Sources: 1. #50228 Guidelines for the prevention of all forms of corruption.pdf 2. #50228 Attachment 05 London Branch Anti-Bribery and Corruption Policy.pdf 3. #50228 Guidelines for the prevention of all forms of corruption.pdf | D588: agentic | E588: 4 | F588: 5 | G588: 4 | H588: 4 | I588: 3 | J588: 4.1625 | K588: 20 | L588: 0.26465753 | M588: 1 | N588: The AI response is generally strong in addressing the user's query with relevant and accurate information. However, it lacks explicit grounding in the provided snippets and could improve citation quality by directly linking claims to specific sources. Overall, it meets high academic standards but has room for improvement in citation practices. | O588: FALSE | S588: =VLOOKUP($B588,'Gemini RAW'!$A:$Q,2,FALSE) -> If you cannot politely refuse a gift that is not allowed, the following steps should be taken. **If taxable in Germany:** * Employees must report all gifts received whose value exceeds EUR 20 (gross) without delay for taxation as a “non-cash benefit in kind”. * Use the form “Notification to AFC Compliance and Human Resources regarding the acceptance of taxable benefits in kind (gifts exceeding EUR 20 (gross) or equivalent) by an employee”. * Submit the completed form to AFC Compliance. * AFC Compliance will assess whether the gift can be accepted or rejected, inform the employee, and forward the form to Human Resources. **If located in London:** * If the value of the gift exceeds GBP 50 (gross), you must initially refuse it. * If refusal is not possible, you must inform AFC Compliance to determine the further course of action. * The adequate course of action will generally be to raffle the gift internally and donate the proceeds to a Berenberg charity or donate the gift itself to a Berenberg charity. **General Guidance:** * If refusing a gift may cause significant offense or embarrassment, the gift may be accepted. * In such instances, the gift should be donated without delay, for instance to a charity of the Bank's choosing (e.g. Berenberg Kids) or put to another use in the Bank's interests. * If you accept a gift, you must notify your line manager appropriately. * Cases of doubt must always be agreed with AFC Compliance in advance but in any case without delay. * If the gift is over EUR 20 (gross), provide feedback to the giver that they should refrain from giving gifts in the future. * Employees outside of Germany should report via email to AFC Compliance London and Human Resources London, including the name and address of the gift giver, description and value of the gift, and the employee's name, to determine if a tax deduction is required. | T588: =VLOOKUP($B588,'Gemini RAW'!$A:$Q,3,FALSE) -> rag | U588: =VLOOKUP($B588,'Gemini RAW'!$A:$Q,4,FALSE) -> 5 | V588: =VLOOKUP($B588,'Gemini RAW'!$A:$Q,5,FALSE) -> 5 | W588: =VLOOKUP($B588,'Gemini RAW'!$A:$Q,6,FALSE) -> 4 | X588: =VLOOKUP($B588,'Gemini RAW'!$A:$Q,7,FALSE) -> 5 | Y588: =VLOOKUP($B588,'Gemini RAW'!$A:$Q,8,FALSE) -> 3 | Z588: =VLOOKUP($B588,'Gemini RAW'!$A:$Q,9,FALSE) -> 4.18 | AA588: =VLOOKUP($B588,'Gemini RAW'!$A:$Q,10,FALSE) -> 22 | AB588: =VLOOKUP($B588,'Gemini RAW'!$A:$Q,11,FALSE) -> 0.48498002 | AC588: =VLOOKUP($B588,'Gemini RAW'!$A:$Q,12,FALSE) -> 4 | AD588: =VLOOKUP($B588,'Gemini RAW'!$A:$Q,13,FALSE) -> The response is factually accurate, relevant, and clearly written. It effectively addresses the user's query by providing practical guidance on handling unrefusable gifts. While the response is well-grounded in the provided snippets, the lack of explicit citations is a minor weakness. The response could also be improved by addressing GDPR concerns and providing more detail on risk management and audit trail procedures. | AE588: =VLOOKUP($B588,'Gemini RAW'!$A:$Q,14,FALSE) -> FALSE | AF588: =VLOOKUP($B588,'Gemini RAW'!$A:$Q,15,FALSE) -> 0 | AG588: =VLOOKUP($B588,'Gemini RAW'!$A:$Q,16,FALSE) -> 0 | AH588: =VLOOKUP($B588,'Gemini RAW'!$A:$Q,17,FALSE) -> 0
A589: 588 | B589: What if refusing a gift could damage the client relationship? | C589: Based on my search of the Gifts & Entertainment database for 'What if refusing a gift could damage the client relationship?': In exceptional circumstances where refusing a gift may cause significant offense or embarrassment, the gift may be accepted. However, it should then be donated without delay, for instance to a charity of the Bank’s choosing or put to another use in the Bank’s interests. If you accept a gift, you must notify your line manager appropriately. Cases of doubt must always be agreed with AFC Compliance in advance but without delay. Sources: 1. #50228 Guidelines for the prevention of all forms of corruption.pdf 2. #50228 Attachment 05 London Branch Anti-Bribery and Corruption Policy.pdf 3. #50228 Guidelines for the prevention of all forms of corruption.pdf | D589: agentic | E589: 3 | F589: 4 | G589: 3 | H589: 4 | I589: 2 | J589: 3.325 | K589: 16 | L589: 0.26307692 | M589: 1 | N589: The AI response provides a relevant discussion on the acceptance of gifts in a corporate context, but it lacks strong grounding in the provided snippets and does not fully address the implications of refusing a gift. The clarity of the response is commendable, but the citation quality is inadequate, as it does not effectively link to the source material. | O589: FALSE | S589: =VLOOKUP($B589,'Gemini RAW'!$A:$Q,2,FALSE) -> Refusing a gift may cause significant offense or embarrassment in exceptional circumstances. In such instances, the gift may be accepted. If you accept a gift, you must notify your line manager appropriately. Cases of doubt must always be agreed with AFC Compliance in advance but in any case without delay. If a refusal is not possible, for reasons of politeness, for instance, the following applies. Employees must report all gifts received whose value exceeds EUR 20 (gross), without delay or being asked, for the purpose of taxation as a “non-cash benefit in kind”. This is done using the form “Notification to AFC Compliance and Human Resources regarding the acceptance of taxable benefits in kind (gifts exceeding EUR 20 (gross) or equivalent) by an employee”. This form is to be completed and submitted to AFC Compliance. AFC Compliance will assess whether the gift can be accepted or should be rejected, informs the employee accordingly, and then forwards the form to the Human Resources department. If this is not possible, you must inform AFC Compliance to determine the further course of action. Generally, the adequate course of action will be to raffle the gift internally and donate the proceeds to a Berenberg charity or donate the gift itself to a Berenberg charity. If the value of the gift exceeds GBP 50 (gross), you must initially refuse it. If a refusal is not possible, you must inform AFC Compliance to determine the further course of action. | T589: =VLOOKUP($B589,'Gemini RAW'!$A:$Q,3,FALSE) -> rag | U589: =VLOOKUP($B589,'Gemini RAW'!$A:$Q,4,FALSE) -> 5 | V589: =VLOOKUP($B589,'Gemini RAW'!$A:$Q,5,FALSE) -> 5 | W589: =VLOOKUP($B589,'Gemini RAW'!$A:$Q,6,FALSE) -> 5 | X589: =VLOOKUP($B589,'Gemini RAW'!$A:$Q,7,FALSE) -> 5 | Y589: =VLOOKUP($B589,'Gemini RAW'!$A:$Q,8,FALSE) -> 3 | Z589: =VLOOKUP($B589,'Gemini RAW'!$A:$Q,9,FALSE) -> 3.76 | AA589: =VLOOKUP($B589,'Gemini RAW'!$A:$Q,10,FALSE) -> 23 | AB589: =VLOOKUP($B589,'Gemini RAW'!$A:$Q,11,FALSE) -> 0.46037778 | AC589: =VLOOKUP($B589,'Gemini RAW'!$A:$Q,12,FALSE) -> 4 | AD589: =VLOOKUP($B589,'Gemini RAW'!$A:$Q,13,FALSE) -> The response provides a factually accurate, relevant, and complete answer to the user's query. It is well-written and easy to understand. However, it lacks explicit citations and does not address GDPR compliance, EU AI Act alignment, or audit trail quality. The content is well-grounded in the provided snippets. | AE589: =VLOOKUP($B589,'Gemini RAW'!$A:$Q,14,FALSE) -> FALSE | AF589: =VLOOKUP($B589,'Gemini RAW'!$A:$Q,15,FALSE) -> 0 | AG589: =VLOOKUP($B589,'Gemini RAW'!$A:$Q,16,FALSE) -> 0 | AH589: =VLOOKUP($B589,'Gemini RAW'!$A:$Q,17,FALSE) -> 0
A590: 589 | B590: Do small promotional items (e.g., pens, calendars) count as gifts? | C590: Based on my search of the Gifts & Entertainment database for 'Do small promotional items (e.g., pens, calendars) count as gifts?': Yes, small promotional items such as pens and calendars are considered gifts. However, gifts of nominal value, like Berenberg-themed items, are generally not deemed to have any influence over the recipient and are typically permitted, provided they comply with the applicable rules. Sources: 1. #50228 Guidelines for the prevention of all forms of corruption.pdf 2. #50228 Guidelines for the prevention of all forms of corruption.pdf 3. #50228 Attachment 07 London Branch_GE_Guidance and Practical Scenarios.pdf | D590: agentic | E590: 3 | F590: 4 | G590: 3 | H590: 4 | I590: 2 | J590: 3.325 | K590: 16 | L590: 0.2688 | M590: 1 | N590: The AI response provides a relevant answer to the user's query but lacks strong grounding in the provided snippets. While it is clear and easy to understand, it does not fully address the nuances of the topic, and the citation quality is poor due to lack of specific references to the snippets. | O590: FALSE | S590: =VLOOKUP($B590,'Gemini RAW'!$A:$Q,2,FALSE) -> Small promotional items such as pens and calendars are considered gifts. Berenberg promotional material is generally not deemed to have any influence over the recipient and is typically permitted. The bank maintains an internal list of promotional gifts, most of which bear the Bank's logo, and the same considerations apply to promotional gifts as to other gifts. | T590: =VLOOKUP($B590,'Gemini RAW'!$A:$Q,3,FALSE) -> rag | U590: =VLOOKUP($B590,'Gemini RAW'!$A:$Q,4,FALSE) -> 5 | V590: =VLOOKUP($B590,'Gemini RAW'!$A:$Q,5,FALSE) -> 5 | W590: =VLOOKUP($B590,'Gemini RAW'!$A:$Q,6,FALSE) -> 4 | X590: =VLOOKUP($B590,'Gemini RAW'!$A:$Q,7,FALSE) -> 5 | Y590: =VLOOKUP($B590,'Gemini RAW'!$A:$Q,8,FALSE) -> 3 | Z590: =VLOOKUP($B590,'Gemini RAW'!$A:$Q,9,FALSE) -> 3.62 | AA590: =VLOOKUP($B590,'Gemini RAW'!$A:$Q,10,FALSE) -> 22 | AB590: =VLOOKUP($B590,'Gemini RAW'!$A:$Q,11,FALSE) -> 0.42382933 | AC590: =VLOOKUP($B590,'Gemini RAW'!$A:$Q,12,FALSE) -> 5 | AD590: =VLOOKUP($B590,'Gemini RAW'!$A:$Q,13,FALSE) -> The response provides a factually accurate and relevant answer to the user's question. The clarity is excellent. Completeness is good but could be improved by adding more context. The citation quality is weak due to the lack of explicit citations. The response completely fails to address GDPR, EU AI Act, and audit trail quality, which is understandable given the lack of relevant information in the snippets. | AE590: =VLOOKUP($B590,'Gemini RAW'!$A:$Q,14,FALSE) -> FALSE | AF590: =VLOOKUP($B590,'Gemini RAW'!$A:$Q,15,FALSE) -> 0 | AG590: =VLOOKUP($B590,'Gemini RAW'!$A:$Q,16,FALSE) -> 0 | AH590: =VLOOKUP($B590,'Gemini RAW'!$A:$Q,17,FALSE) -> 0
A591: 590 | B591: Are gifts between employees covered by this policy? | C591: Based on web search results for 'Are gifts between employees covered by this policy?': 1. 5 CFR Part 2635 Subpart C -- Gifts Between Employees - eCFR: This subpart contains standards that prohibit an employee from giving or contributing to a gift to an official superior. 2. [PDF] Ethics Guidance on Gifts Between Employees in Times of Crisis: While some solicitations (such as for an employee making less pay) are not restricted by the Standards, subpart C generally prohibits an employee from soliciting donations for their supervisor in the Federal workplace.23 Employees may solicit for voluntary contributions for their superiors for events that qualify as special, infrequent occasions, as long as they work closely with their ethics officials to address the ethics issues that are specific to the Federal workplace, as discussed above.24 Notably, however, if the affected individual is not the receiving employee (such as when a group of employees would like to collect donations for a supervisor’s sick relative), the employee and ethics official must look to the relationship between the receiving employee and the affected individual to determine first (if the gift was given to the employee’s loved one) if it is restricted by subpart C,25 and second, if the occasion is of sufficient personal significance to the employee to qualify as a special, infrequent occasion.26 For example, if the colleagues of a higher-paid employee whose spouse or child was just diagnosed with a serious illness wish to solicit donations to help with medical expenses, such a solicitation would be appropriate under the special, infrequent occasion exception, as it is an indirect gift that has a clearly significant impact on the employee. 3. Gifts, Honoraria, Travel Payments, and Loans - FPPC: Public officials and employees are subject to certain restrictions related to receiving gifts, honoraria, travel payments, and loans. | D591: agentic | E591: 4 | F591: 5 | G591: 4 | H591: 4 | I591: 3 | J591: 4.1625 | K591: 20 | L591: 0.19169082 | M591: 1 | N591: The AI response effectively addresses the user query with relevant information from the snippets, demonstrating a good understanding of the policy regarding gifts between employees. While it is factually accurate and relevant, there are areas for improvement in completeness and clarity, particularly in explaining exceptions and simplifying language. The lack of explicit citations slightly detracts from the citation quality, but the implicit grounding is adequate. | O591: TRUE | P591: TRUE | Q591: 390 | R591: 1921 | S591: =VLOOKUP($B591,'Gemini RAW'!$A:$Q,2,FALSE) -> Gifts between employees are not explicitly addressed in the provided policies. However, the policies do address gifts given to employees from clients or third parties. In principle, you are not allowed to accept gifts from or give gifts to clients. This does not include gifts to or from clients of up to EUR 20 (gross) or equivalent, provided the client is not a public official. Accepting and giving gifts in the form of cash or cash equivalents is prohibited in all cases. Gifts with a gross value of more than EUR 20 from a (potential) client/business partner to employees must be declined. In London, the value of a gift must not exceed GBP 50 (gross). Where a series of gifts are received during the same calendar year from the same third party, the aggregate value must not exceed GBP 100 (gross). Research Analysts and Corporate Finance employees are never permitted to receive gifts. The offer of non-business related entertainment to Berenberg employees where the third party will not be in attendance is considered a gift. Perishable items, in general, must be shared internally within the office of the London Branch. | T591: =VLOOKUP($B591,'Gemini RAW'!$A:$Q,3,FALSE) -> rag | U591: =VLOOKUP($B591,'Gemini RAW'!$A:$Q,4,FALSE) -> 4 | V591: =VLOOKUP($B591,'Gemini RAW'!$A:$Q,5,FALSE) -> 4 | W591: =VLOOKUP($B591,'Gemini RAW'!$A:$Q,6,FALSE) -> 3 | X591: =VLOOKUP($B591,'Gemini RAW'!$A:$Q,7,FALSE) -> 5 | Y591: =VLOOKUP($B591,'Gemini RAW'!$A:$Q,8,FALSE) -> 1 | Z591: =VLOOKUP($B591,'Gemini RAW'!$A:$Q,9,FALSE) -> 2.96 | AA591: =VLOOKUP($B591,'Gemini RAW'!$A:$Q,10,FALSE) -> 17 | AB591: =VLOOKUP($B591,'Gemini RAW'!$A:$Q,11,FALSE) -> 0.36652641 | AC591: =VLOOKUP($B591,'Gemini RAW'!$A:$Q,12,FALSE) -> 4 | AD591: =VLOOKUP($B591,'Gemini RAW'!$A:$Q,13,FALSE) -> The response is factually accurate and relevant, but incomplete. It correctly identifies that the policy doesn't explicitly address gifts between employees but fails to offer further guidance. The clarity is excellent. However, the response lacks citations and fails to address GDPR, EU AI Act, and audit trail considerations. The response focuses on gifts to employees from clients, which is related but not the primary focus of the query. | AE591: =VLOOKUP($B591,'Gemini RAW'!$A:$Q,14,FALSE) -> FALSE | AF591: =VLOOKUP($B591,'Gemini RAW'!$A:$Q,15,FALSE) -> 0 | AG591: =VLOOKUP($B591,'Gemini RAW'!$A:$Q,16,FALSE) -> 0 | AH591: =VLOOKUP($B591,'Gemini RAW'!$A:$Q,17,FALSE) -> 0
A592: 591 | B592: Can I accept tickets to a sporting event from a business partner? | C592: Based on my search of the Gifts & Entertainment database for 'Can I accept tickets to a sporting event from a business partner?': It depends on the circumstances. Invitations to external events from third parties must be sent to your business address, and you should not accept invitations that extend to family members or close associates if the third party will not be attending. Additionally, the value of the tickets and the frequency of invitations in a calendar year should be considered. If in doubt, you should consult AFC Compliance. Sources: 1. #50228 Attachment 07 London Branch_GE_Guidance and Practical Scenarios.pdf 2. #50228 Attachment 07 London Branch_GE_Guidance and Practical Scenarios.pdf 3. #50228 Attachment 05 London Branch Anti-Bribery and Corruption Policy.pdf | D592: agentic | E592: 4 | F592: 5 | G592: 4 | H592: 4 | I592: 2 | J592: 4.075 | K592: 19 | L592: 0.26465753 | M592: 1 | N592: The AI response effectively addresses the user's query with relevant and mostly accurate information. However, it lacks strong grounding in the provided snippets and does not utilize citations effectively, which detracts from its overall academic rigor. Improvements in citation quality and completeness would enhance the response significantly. | O592: FALSE | S592: =VLOOKUP($B592,'Gemini RAW'!$A:$Q,2,FALSE) -> It may be permissible to accept tickets to a sporting event from a business partner, but several factors need to be considered. Here's a breakdown of the relevant guidelines: * **General permissibility:** Accepting entertainment or hospitality during the normal course of business is permitted, subject to requirements. * **Transparency and Format:** The invitation should be transparent and addressed to your Berenberg business address. Invitations should be sent via official channels, like with the bank logo or a business email. * **Value Limits:** * In London, the true value of the ticket must not exceed GBP 500 (gross) per head. * In general, invitations to pure entertainment or recreational events with a value of EUR 250 (gross) or less per person are admissible if there are no or predominantly no negative indications. The assessment is based on all per-person costs, excluding Berenberg's sponsorship and advertising costs. * **Reasonable and Proportionate:** The nature of the entertainment must be reasonable and proportionate to your position as a Berenberg employee. * **No Family/Close Associates:** The invitation should not be extended to family members or close associates outside of Berenberg. If a ticket is intended for a family member and the business partner will not be in attendance, the tickets may be considered a gift. * **No Reimbursement of Expenses:** You must not accept an offer to reimburse travel and/or accommodation expenses without prior authorization from AFC Compliance. * **Research Analysts:** Research Analysts are generally not permitted to accept any travel or accommodation. If they accept entertainment or attend events hosted by third parties, all associated costs must be borne by Berenberg. * **Potential Conflicts of Interest:** Consider whether you are involved in an upcoming decision that could benefit the business partner, such as awarding a mandate or establishing a new business relationship. This could be a negative indicator. * **Bank's Reputation:** You must not accept any benefits that could bring the Bank into disrepute. * **Gifts vs. Entertainment:** For it to be considered entertainment, the third party must be in attendance. Otherwise, the invitation will be considered a gift. * **AFC Compliance:** If you are unsure whether it is permissible or appropriate to accept the tickets, you should consult AFC Compliance in good time and without delay. AFC Compliance must make a case-by-case assessment of appropriateness. **In your specific situation (Daniel Fuhrmann at Berenberg), you should consider:** * The value of the tickets. * Whether the invitation was extended to your business address. * Whether the business partner will be in attendance. * Whether accepting the tickets could be perceived as influencing any decisions you might make that would benefit the business partner. * Whether accepting the tickets could bring Berenberg into disrepute. If there are any negative indicators or if you are uncertain, you should consult AFC Compliance. | T592: =VLOOKUP($B592,'Gemini RAW'!$A:$Q,3,FALSE) -> rag | U592: =VLOOKUP($B592,'Gemini RAW'!$A:$Q,4,FALSE) -> 4 | V592: =VLOOKUP($B592,'Gemini RAW'!$A:$Q,5,FALSE) -> 5 | W592: =VLOOKUP($B592,'Gemini RAW'!$A:$Q,6,FALSE) -> 4 | X592: =VLOOKUP($B592,'Gemini RAW'!$A:$Q,7,FALSE) -> 5 | Y592: =VLOOKUP($B592,'Gemini RAW'!$A:$Q,8,FALSE) -> 2 | Z592: =VLOOKUP($B592,'Gemini RAW'!$A:$Q,9,FALSE) -> 4.46 | AA592: =VLOOKUP($B592,'Gemini RAW'!$A:$Q,10,FALSE) -> 20 | AB592: =VLOOKUP($B592,'Gemini RAW'!$A:$Q,11,FALSE) -> 0.17877594 | AC592: =VLOOKUP($B592,'Gemini RAW'!$A:$Q,12,FALSE) -> 5 | AD592: =VLOOKUP($B592,'Gemini RAW'!$A:$Q,13,FALSE) -> The response provides a relevant, clear, and mostly complete answer to the user's query. The factual accuracy is generally good, although the specific value limits should be verified. The main weakness is the lack of explicit citations to the source snippets. The response effectively synthesizes information to provide practical guidance. | AE592: =VLOOKUP($B592,'Gemini RAW'!$A:$Q,14,FALSE) -> FALSE | AF592: =VLOOKUP($B592,'Gemini RAW'!$A:$Q,15,FALSE) -> 0 | AG592: =VLOOKUP($B592,'Gemini RAW'!$A:$Q,16,FALSE) -> 0 | AH592: =VLOOKUP($B592,'Gemini RAW'!$A:$Q,17,FALSE) -> 0
A593: 592 | B593: What is the rule if hospitality is offered during ongoing negotiations? | C593: Based on my search of the Gifts & Entertainment database for 'What is the rule if hospitality is offered during ongoing negotiations?': It is not acceptable to give or accept a gift or hospitality during any commercial negotiations or tender process if this could be perceived as intending or likely to influence the outcome. Sources: 1. #50228 Attachment 05 London Branch Anti-Bribery and Corruption Policy.pdf 2. #50228 Attachment 07 London Branch_GE_Guidance and Practical Scenarios.pdf 3. #50228 Guidelines for the prevention of all forms of corruption.pdf | D593: agentic | E593: 4 | F593: 5 | G593: 3 | H593: 4 | I593: 2 | J593: 3.8875 | K593: 18 | L593: 0.27272727 | M593: 1 | N593: The AI response effectively addresses the user's query with relevant and mostly accurate information. However, it falls short in completeness and citation quality, as it does not directly reference the snippets provided, which diminishes the overall grounding of the claims made. Enhancing the response with specific examples and clearer citations would improve its academic rigor. | O593: FALSE | S593: =VLOOKUP($B593,'Gemini RAW'!$A:$Q,2,FALSE) -> During commercial negotiations or a tender process, you must not give or accept a gift or hospitality if it could be perceived as intending or likely to influence the outcome. During the bidding or pitch process for a new transaction, business mandate, product, service or relationship, the receipt of gifts of any value is strictly prohibited. | T593: =VLOOKUP($B593,'Gemini RAW'!$A:$Q,3,FALSE) -> rag | U593: =VLOOKUP($B593,'Gemini RAW'!$A:$Q,4,FALSE) -> 4 | V593: =VLOOKUP($B593,'Gemini RAW'!$A:$Q,5,FALSE) -> 5 | W593: =VLOOKUP($B593,'Gemini RAW'!$A:$Q,6,FALSE) -> 4 | X593: =VLOOKUP($B593,'Gemini RAW'!$A:$Q,7,FALSE) -> 5 | Y593: =VLOOKUP($B593,'Gemini RAW'!$A:$Q,8,FALSE) -> 1 | Z593: =VLOOKUP($B593,'Gemini RAW'!$A:$Q,9,FALSE) -> 4.12 | AA593: =VLOOKUP($B593,'Gemini RAW'!$A:$Q,10,FALSE) -> 19 | AB593: =VLOOKUP($B593,'Gemini RAW'!$A:$Q,11,FALSE) -> 0.10018338 | AC593: =VLOOKUP($B593,'Gemini RAW'!$A:$Q,12,FALSE) -> 8 | AD593: =VLOOKUP($B593,'Gemini RAW'!$A:$Q,13,FALSE) -> The response provides a factually accurate and relevant answer to the user's query. The clarity is excellent. However, the lack of citations is a significant weakness. The response could be improved by providing sources for the information and by being more comprehensive in its coverage of the rule. | AE593: =VLOOKUP($B593,'Gemini RAW'!$A:$Q,14,FALSE) -> FALSE | AF593: =VLOOKUP($B593,'Gemini RAW'!$A:$Q,15,FALSE) -> 0 | AG593: =VLOOKUP($B593,'Gemini RAW'!$A:$Q,16,FALSE) -> 0 | AH593: =VLOOKUP($B593,'Gemini RAW'!$A:$Q,17,FALSE) -> 0
A594: 593 | B594: What are the consequences if I violate the gifts and hospitality policy? | C594: Based on web search results for 'What are the consequences if I violate the gifts and hospitality policy?': 1. Limitations and Restrictions on Gifts, Honoraria, Travel and Loans: Limitations and Restrictions on Gifts, Honoraria, Travel and Loans A Fact Sheet For • Elected State Officers and Candidates for Elective State Office • Members of State Boards and Commissions • Designated Employees of State Government Agencies • State Officials Who Manage Public Investments California Fair Political Practices Commission Toll-free advice line: 1 (866) ASK-FPPC Email advice: advice@fppc.ca.gov Web site: www.fppc.ca.gov February 2019 Introduction The Political Reform Act1 (the “Act”) imposes limits on gifts, prohibits honoraria payments2 , and imposes limits and other restrictions on the receipt of travel payments and personal loans by the following state officials: • Elected state officers, candidates for elective state office, and other state officials specified in Section 87200;3 • Members of state boards and commissions; and • Designated employees of state agencies (i.e., officials and employees of state agencies who file statements of economic interests (Form 700) under their agency’s conflict of interest code). 2. The Ethics of Gifts & Hospitality | Institute of Business Ethics - IBE: The Ethics of Gifts & Hospitality | Institute of Business Ethics - IBE The Act does recognise that corporate gifts and hospitality play an important part in business, and provides guidance for organisations as to what is considered appropriate and what may be construed as a bribe when giving or accepting gifts/hospitality. Companies help prevent their employees giving or accepting inappropriate gifts/hospitality by providing guidance, usually in the company code of ethics (or equivalent document). There are a number of principles for organisations to consider when developing guidance for employees on giving and accepting gifts/hospitality. Business Ethics, Gift and Hospitality Policy – WSP Group They can be included in the code of ethics guidance and/or gifts and hospitality policy. 3. 9. Gifts & Hospitality - Anti-Bribery Guidance: Gifts and hospitality and travel expenses (together called ‘promotional expenses’ in this section) are a high-risk area for bribery and have figured in a large number of FCPA cases. The authorities are unlikely to be interested in nominal value, reasonable gifts, hospitality and expense but guidance from the authorities on what is appropriate under bribery law is broad and does not give the certainty which companies seek. * Promotional expenses are given to public officials and contravene laws such as the UK Bribery Act or the FCPA. The continuing prosecutions of companies for abusing gifts and hospitality shows the risk that local employees may transgress policies in order to win contracts and this may lead to wider bribery and other corruption. | D594: agentic | E594: 3 | F594: 4 | G594: 3 | H594: 3 | I594: 2 | J594: 3.1625 | K594: 15 | L594: 0.18777778 | M594: 1 | N594: The AI response provides some relevant information regarding gifts and hospitality policies but lacks specific details about the consequences of violations, which is essential to fully address the user's query. The clarity and organization of the response could be improved, and the absence of explicit citations detracts from the overall quality of the response. | O594: TRUE | P594: TRUE | Q594: 412 | R594: 2902 | S594: =VLOOKUP($B594,'Gemini RAW'!$A:$Q,2,FALSE) -> Violating the gifts and hospitality policy can lead to potential corruption risks. You must avoid any activity that might appear as a breach of the policy. If you are in doubt about offering or accepting a gift, entertainment, or hospitality invitation, you should consult with AFC Compliance. Specifically, it is unacceptable to offer, promise, give, accept, or solicit an advantage as an inducement for an action which is illegal, unethical or a breach of trust. It is also unacceptable to abuse your position or entrusted power for private gain or induce or influence someone to abuse their position or entrusted power for private gain. If you are offered a bribe, or asked to make one, or if you believe or suspect that any bribery, corruption or other breach of this policy has occurred or may occur, you must refuse it and report it immediately to your manager and AFC Compliance. Reports can be submitted openly or anonymously. The timing of a gift not long before a contract renewal could give rise to an improper performance of duties. In such cases, the Berenberg employee should raise the matter with AFC Compliance. Under the Bribery Act 2010, it is a criminal offense for employees to accept any gift or consideration as an inducement or reward for doing or not doing anything or showing favor or disfavor to any person. | T594: =VLOOKUP($B594,'Gemini RAW'!$A:$Q,3,FALSE) -> rag | U594: =VLOOKUP($B594,'Gemini RAW'!$A:$Q,4,FALSE) -> 5 | V594: =VLOOKUP($B594,'Gemini RAW'!$A:$Q,5,FALSE) -> 5 | W594: =VLOOKUP($B594,'Gemini RAW'!$A:$Q,6,FALSE) -> 4 | X594: =VLOOKUP($B594,'Gemini RAW'!$A:$Q,7,FALSE) -> 5 | Y594: =VLOOKUP($B594,'Gemini RAW'!$A:$Q,8,FALSE) -> 2 | Z594: =VLOOKUP($B594,'Gemini RAW'!$A:$Q,9,FALSE) -> 3.56 | AA594: =VLOOKUP($B594,'Gemini RAW'!$A:$Q,10,FALSE) -> 21 | AB594: =VLOOKUP($B594,'Gemini RAW'!$A:$Q,11,FALSE) -> 0.27288746 | AC594: =VLOOKUP($B594,'Gemini RAW'!$A:$Q,12,FALSE) -> 7 | AD594: =VLOOKUP($B594,'Gemini RAW'!$A:$Q,13,FALSE) -> The response provides a factually accurate and relevant answer to the user's query. The clarity and organization of the response are excellent. However, the lack of explicit citations and the absence of considerations for GDPR, the EU AI Act, and audit trails are significant weaknesses. The response could be more complete by including specific disciplinary actions that might result from a violation. | AE594: =VLOOKUP($B594,'Gemini RAW'!$A:$Q,14,FALSE) -> FALSE | AF594: =VLOOKUP($B594,'Gemini RAW'!$A:$Q,15,FALSE) -> 0 | AG594: =VLOOKUP($B594,'Gemini RAW'!$A:$Q,16,FALSE) -> 0 | AH594: =VLOOKUP($B594,'Gemini RAW'!$A:$Q,17,FALSE) -> 0
A595: 594 | B595: Is pre-approval required for giving gifts to clients? | C595: Based on my search of the Gifts & Entertainment database for 'Is pre-approval required for giving gifts to clients?': Yes, pre-approval is required for giving gifts to clients as per the Policy. If you are unclear or need pre-approval, you should contact Compliance at ComplianceAML@berenberg.de. Sources: 1. #50228 Attachment 07 London Branch_GE_Guidance and Practical Scenarios.pdf 2. #50228 Guidelines for the prevention of all forms of corruption.pdf 3. #50228 Guidelines for the prevention of all forms of corruption.pdf | D595: agentic | E595: 3 | F595: 4 | G595: 3 | H595: 4 | I595: 2 | J595: 3.325 | K595: 16 | L595: 0.28090909 | M595: 1 | N595: The AI response is relevant and clear but lacks sufficient grounding in the provided snippets to fully support its claims. The citation quality is poor, as the references do not effectively substantiate the information presented. Overall, the response meets some academic standards but requires improvement in grounding and citation accuracy. | O595: FALSE | S595: =VLOOKUP($B595,'Gemini RAW'!$A:$Q,2,FALSE) -> Whether pre-approval is required for giving gifts to clients depends on several factors, including the location of the Berenberg employee, the value of the gift, and the specific policies in place. Berenberg maintains an Anti-Bribery and Corruption policy that includes rules governing gifts and entertainment. The London branch has specific guidance that differs from the rules governing all other Berenberg branches. Here's a breakdown: * **London Policy:** If the London Policy applies, pre-approval from AFC Compliance is not required if the gift is under £50.00, assuming it is reasonable, proportionate, and not improper. * **Global Policy:** If the Global Policy applies, the threshold for seeking pre-approval for giving or receiving gifts is €20.00. * **When to contact Compliance:** If you are unclear or pre-approval is required, contact ComplianceAML@berenberg.de. * **General Restrictions:** Gifts may not be given in a personal capacity or in cash form. * **Gifts to family members:** Giving gifts to family members of third parties is generally not permitted. * **Gifts to Public Officials:** Gifts to or from clients of up to EUR 20 are permissible, provided the client is not a public official. * **Gifts over EUR 20:** In principle, gifts with a gross value of more than EUR 20 from a (potential) client/business partner to employees must be declined. * **Reasonable Justification:** The giving of gifts to third parties is generally not permitted unless, in consultation with AFC Compliance and senior management, a reasonable justification is determined and the other conditions of the Policy are met. It is important to note that regardless of the value thresholds or the applicable policy, any gift given must always be reasonable, proportionate, and not improper and meet other specific criteria set out in the respective policies. | T595: =VLOOKUP($B595,'Gemini RAW'!$A:$Q,3,FALSE) -> rag | U595: =VLOOKUP($B595,'Gemini RAW'!$A:$Q,4,FALSE) -> 4 | V595: =VLOOKUP($B595,'Gemini RAW'!$A:$Q,5,FALSE) -> 5 | W595: =VLOOKUP($B595,'Gemini RAW'!$A:$Q,6,FALSE) -> 4 | X595: =VLOOKUP($B595,'Gemini RAW'!$A:$Q,7,FALSE) -> 5 | Y595: =VLOOKUP($B595,'Gemini RAW'!$A:$Q,8,FALSE) -> 2 | Z595: =VLOOKUP($B595,'Gemini RAW'!$A:$Q,9,FALSE) -> 3.34 | AA595: =VLOOKUP($B595,'Gemini RAW'!$A:$Q,10,FALSE) -> 20 | AB595: =VLOOKUP($B595,'Gemini RAW'!$A:$Q,11,FALSE) -> 0.49942977 | AC595: =VLOOKUP($B595,'Gemini RAW'!$A:$Q,12,FALSE) -> 6 | AD595: =VLOOKUP($B595,'Gemini RAW'!$A:$Q,13,FALSE) -> The response provides a relevant and generally accurate answer to the user's query. The content is well-organized and easy to understand. However, the lack of explicit citations is a significant weakness. Furthermore, the response fails to address GDPR compliance, EU AI Act alignment, and audit trail quality, which are important considerations for a comprehensive AI system assessment. The system demonstrates good content generation capabilities but needs improvement in source utilization and adherence to broader regulatory requirements. | AE595: =VLOOKUP($B595,'Gemini RAW'!$A:$Q,14,FALSE) -> FALSE | AF595: =VLOOKUP($B595,'Gemini RAW'!$A:$Q,15,FALSE) -> 0 | AG595: =VLOOKUP($B595,'Gemini RAW'!$A:$Q,16,FALSE) -> 0 | AH595: =VLOOKUP($B595,'Gemini RAW'!$A:$Q,17,FALSE) -> 0
A596: 595 | B596: Can I reimburse a client for hospitality they provided to me? | C596: Web search did not return relevant results. | D596: agentic | E596: 1 | F596: 1 | G596: 1 | H596: 2 | I596: 1 | J596: 1.1625 | K596: 6 | L596: 0.2969697 | M596: 1 | N596: The AI system's response is inadequate as it fails to address the user's query about reimbursing a client for hospitality. It does not provide any relevant information or guidance, and the lack of citations further diminishes its academic quality. The response does not meet any academic standards for factual accuracy, relevance, completeness, or citation quality. | O596: TRUE | P596: TRUE | Q596: 400 | R596: 43 | S596: =VLOOKUP($B596,'Gemini RAW'!$A:$Q,2,FALSE) -> Reimbursing a third party's expenses or accepting an offer to reimburse your expenses will not usually amount to bribery. However, any payment in excess of genuine and reasonable business expenses is never acceptable. You are required to keep a written record of all hospitality and gifts given or received, so that this can be reviewed by AFC Compliance. You must submit all expenses claims relating to hospitality, gifts or payments to third parties and record the reason for expenditure, in accordance with Berenberg's expenses policy. All accounts, invoices, and other records relating to dealings with third parties including suppliers and customers should be prepared with strict accuracy and completeness. Accounts must not be kept "off-book" to facilitate or conceal improper payments. Third party expenses such as travel and/or accommodation may only be paid for/reimbursed by Berenberg where such costs are genuine, reasonable and necessary. Third party expenses for pure client entertainment (such as organized shoots) should not be paid by the Bank as such costs are not considered to be necessary, reasonable or proportionate. Exceptions may be approved by AFC Compliance on a case by case basis. Berenberg-hosted entertainment/events and 'normal course of business' hospitality - such as one-on-one third-party lunches and dinners - are permissible provided that the cost of the entertainment/event or hospitality does not exceed GBP 500 (gross) per head and other requirements are met. Even if the overall cost per head is below GBP 500 (gross), the provision of entertainment and hospitality is only permitted if it is reasonable and proportionate such that it is unlikely to have any influence on any invitee(s) in consideration of their individual circumstances, and does not appear improper. For a business lunch or dinner it would generally be considered to be reasonable and proportionate where the value is less than GBP 100 (gross) per head. Business meals must take place within a usual and appropriate setting. If the hospitality costs less than EUR 50 (gross) per person, the circumstances for the business meal are generally considered to be usual and appropriate. For business meals for a special occasion, the guide cost is EUR 100 (gross) per person. In individual cases, costs of between EUR 100 and EUR 250 (gross) per person may also be usual and appropriate. Employees who accept a gift whose value exceeds EUR 20 (gross) or equivalent in connection with their work for the Bank must notify Compliance London and Human Resources London by e-mail. Employees who are taxable outside Germany and, in connection with their work for the Bank, take part for free in an event without a predominant business character whose value exceeds EUR 20 (gross) or equivalent, must also report this to Human Resources so that the latter can check the extent to which a tax deduction is required. | T596: =VLOOKUP($B596,'Gemini RAW'!$A:$Q,3,FALSE) -> rag | U596: =VLOOKUP($B596,'Gemini RAW'!$A:$Q,4,FALSE) -> 4 | V596: =VLOOKUP($B596,'Gemini RAW'!$A:$Q,5,FALSE) -> 5 | W596: =VLOOKUP($B596,'Gemini RAW'!$A:$Q,6,FALSE) -> 4 | X596: =VLOOKUP($B596,'Gemini RAW'!$A:$Q,7,FALSE) -> 4 | Y596: =VLOOKUP($B596,'Gemini RAW'!$A:$Q,8,FALSE) -> 1 | Z596: =VLOOKUP($B596,'Gemini RAW'!$A:$Q,9,FALSE) -> 3.16 | AA596: =VLOOKUP($B596,'Gemini RAW'!$A:$Q,10,FALSE) -> 18 | AB596: =VLOOKUP($B596,'Gemini RAW'!$A:$Q,11,FALSE) -> 0.33371212 | AC596: =VLOOKUP($B596,'Gemini RAW'!$A:$Q,12,FALSE) -> 3 | AD596: =VLOOKUP($B596,'Gemini RAW'!$A:$Q,13,FALSE) -> The response is relevant and generally accurate, providing useful information about reimbursing hospitality expenses. However, it lacks citations and does not address GDPR compliance, EU AI Act alignment, or audit trail quality. The absence of citations significantly reduces the credibility and verifiability of the information presented. The response would be significantly improved by including citations to the source snippets and addressing the legal and regulatory aspects of expense reimbursement and hospitality. | AE596: =VLOOKUP($B596,'Gemini RAW'!$A:$Q,14,FALSE) -> FALSE | AF596: =VLOOKUP($B596,'Gemini RAW'!$A:$Q,15,FALSE) -> 0 | AG596: =VLOOKUP($B596,'Gemini RAW'!$A:$Q,16,FALSE) -> 0 | AH596: =VLOOKUP($B596,'Gemini RAW'!$A:$Q,17,FALSE) -> 0
A597: 596 | B597: What are the standard procedures for data backup in our company? | C597: Based on my search of the IT Governance database for 'What are the standard procedures for data backup in our company?': The standard procedures for data backup in your company include the following: 1. Copies of data, software, or system images of applications and IT systems are backed up in accordance with availability requirements. 2. The backup method, scope, frequency, and retention period of the data backup are defined. 3. The execution of the data backup is logged and monitored, with any anomalies and deviations followed up in a timely manner. 4. The storage media and backed-up data are protected against unauthorized access and against malicious, technical, and natural threats. 5. Standard operating procedures for restoring backed-up data are defined. 6. The completeness and readability of the storage media and restoration of the backed-up data are tested regularly and on a case-by-case basis. Sources: 1. #50091 Data Backup and Recovery.pdf 2. #50091 Data Backup and Recovery.pdf 3. #50091 Data Backup and Recovery.pdf | D597: agentic | E597: 3 | F597: 4 | G597: 4 | H597: 4 | I597: 2 | J597: 3.5125 | K597: 17 | L597: 0.14019048 | M597: 1 | N597: The AI response effectively addresses the user query with relevant and clear information about data backup procedures. However, the lack of specific grounding in the provided snippet and the poor quality of citations limit the overall academic rigor of the response. Improvements in citation specificity and grounding in the snippet would enhance the response's credibility. | O597: FALSE | S597: =VLOOKUP($B597,'Gemini RAW'!$A:$Q,2,FALSE) -> Copies of data, software, or system images of applications and IT systems are backed up according to availability requirements. The backup method, scope, frequency, and retention period of the data backup are defined. The execution of the data backup is logged and monitored. Anomalies and deviations are followed up in a timely manner. The storage media and backed-up data are protected against unauthorized access and against malicious, technical, and natural threats. Standard operating procedures for restoring backed-up data are defined. The completeness and readability of the storage media and restoration of the backed-up data is tested regularly and on a case-by-case basis. The Linux, UNIX & Storage Team within the Linux, Databases & Communications (LDC) department is responsible for deriving a data backup policy from legal requirements and applying it to existing or newly acquired backup solutions. All participating departments must supportively ensure that this data backup concept can be implemented in accordance with the laws and guidelines described further. The data backup concept comprises two parts: the actual data backup policy, describing legal requirements and defining respective needs, and procedural instructions for individual data backup applications used at Berenberg. The backup concept focuses on securing files, folders, virtual and physical machines, databases, and similar applications. Retention periods for these data range from a few days to several years, depending on requirements. Not included are archiving solutions, in which data is stored long-term in unchangeable, indexed versions within its application context, allowing specific application states to be queried. The procedure for data backups should be described, including the scope, methods, period, duration, and location of data backups. When creating a backup policy, the following points should be clarified or defined with the application owners during the initialization of the data backup using the application-specific information: Backup Object, Source and target environment, Backup type, Backup frequency, Backup schedule, Checking and logging requirements. The backup policy should specify how the backup can be restored in the event of data loss or an emergency, or which recovery procedure should be used. The backup policy indicates whether and, if so, how notifications should be sent, e.g. to monitor the progress of the backup or to point out errors or problems. The backup policy specifies how long backups should be kept in order to enable data recovery if required. The backup policy specifies whether and, if so, at what intervals the backups should be checked and tested to ensure that the data can be successfully restored. The backup policy provides information on how access to the backup data is granted in order to prevent unauthorized access and data loss. The backup policy indicates where backup activities are documented, including the backups performed, the recovery tests and the changes to the backup policy. Specifying the storage location in the backup job ensures that the backup is stored in a secure location. This can be a local SAN storage within the data centers of Berenberg Bank or an external storage location such as a cloud storage. By defining checking and logging requirements in the backup job, it is ensured that the backup is checked and monitored in order to detect problems or errors at an early stage and take measures to rectify them. By specifying the recovery procedures in the backup job ensures that the backup can be successfully restored in the event of data loss or an emergency. By setting notifications in the backup job, relevant people or teams can be informed about the progress of the backup. Backup data must be protected with access controls to prevent unauthorized access. Regularly test the restoration process to ensure that backups can be reliably restored when needed. | T597: =VLOOKUP($B597,'Gemini RAW'!$A:$Q,3,FALSE) -> rag | U597: =VLOOKUP($B597,'Gemini RAW'!$A:$Q,4,FALSE) -> 4 | V597: =VLOOKUP($B597,'Gemini RAW'!$A:$Q,5,FALSE) -> 5 | W597: =VLOOKUP($B597,'Gemini RAW'!$A:$Q,6,FALSE) -> 4 | X597: =VLOOKUP($B597,'Gemini RAW'!$A:$Q,7,FALSE) -> 4 | Y597: =VLOOKUP($B597,'Gemini RAW'!$A:$Q,8,FALSE) -> 2 | Z597: =VLOOKUP($B597,'Gemini RAW'!$A:$Q,9,FALSE) -> 3.78 | AA597: =VLOOKUP($B597,'Gemini RAW'!$A:$Q,10,FALSE) -> 19 | AB597: =VLOOKUP($B597,'Gemini RAW'!$A:$Q,11,FALSE) -> 0.44951004 | AC597: =VLOOKUP($B597,'Gemini RAW'!$A:$Q,12,FALSE) -> 6 | AD597: =VLOOKUP($B597,'Gemini RAW'!$A:$Q,13,FALSE) -> The response provides a relevant and generally accurate overview of data backup procedures. It effectively synthesizes information from the provided snippets, although it lacks explicit citations. The content quality is good, but the citation quality needs improvement. The response also touches on GDPR and EU AI Act considerations, but could benefit from more explicit coverage of these topics. | AE597: =VLOOKUP($B597,'Gemini RAW'!$A:$Q,14,FALSE) -> FALSE | AF597: =VLOOKUP($B597,'Gemini RAW'!$A:$Q,15,FALSE) -> 0 | AG597: =VLOOKUP($B597,'Gemini RAW'!$A:$Q,16,FALSE) -> 0 | AH597: =VLOOKUP($B597,'Gemini RAW'!$A:$Q,17,FALSE) -> 0
A598: 597 | B598: How often are backups performed and where are they stored? | C598: Based on my search of the IT Governance database for 'How often are backups performed and where are they stored?': Backups can be performed daily, weekly, monthly, or at other intervals, depending on the requirements of the system and the company. The storage location for backups is specified in the backup job, ensuring that the backup is saved in a secure storage location. Additionally, the 3-2-1 data backup policy states that at least 3 copies of the data should be kept, with at least 2 copies saved on different media or storage types, and 1 backup copy should be kept at an external storage location (offsite). Sources: 1. #50091 Data Backup and Recovery.pdf 2. #50091 Data Backup and Recovery.pdf 3. #50091 Data Backup and Recovery.pdf | D598: agentic | E598: 4 | F598: 5 | G598: 4 | H598: 4 | I598: 2 | J598: 4.075 | K598: 19 | L598: 0.14196643 | M598: 1 | N598: The AI response effectively addresses the user query with relevant and mostly accurate information regarding backup frequency and storage practices. However, it lacks strong grounding in the provided snippet and has issues with citation quality, which detracts from its overall academic rigor. Improvements in citation diversity and explicit connections to the snippet content would enhance the response significantly. | O598: FALSE | S598: =VLOOKUP($B598,'Gemini RAW'!$A:$Q,2,FALSE) -> Copies of a database backup are made every four hours in separate workflows. RMAN backups are not long-term backups and therefore only have short retention periods. If long-term backups of databases are required, they must be written as a database export to a file system on the client and then backed up to the data domain as a long-term file backup. The backup frequency should be specified when creating a backup policy. This can be daily, weekly, monthly, or at other intervals, depending on the requirements of the system and the company. The backup schedule must also be specified, indicating when the backup is to be performed, which can be a specific time or a defined time window. The 3-2-1 data backup policy is defined as follows: There should be at least 3 copies of the data to be backed up. These copies are divided into 1x original data, 1x initial backup, 1x copy/clone of the backup in the secondary data center. At least 2 copies should be saved on different media or storage types. The storage of the backup is always different from the storage of the original data. One backup copy should be kept at an external storage location (offsite). All data is stored as a copy/clone in two data centers, so one copy is always "offsite" to the primary backup. The storage media and backed-up data are protected against unauthorised access and against malicious, technical and natural threats. The standard retention period at Berenberg Bank is one month. Different retention periods must be requested when setting up the data backup. | T598: =VLOOKUP($B598,'Gemini RAW'!$A:$Q,3,FALSE) -> rag | U598: =VLOOKUP($B598,'Gemini RAW'!$A:$Q,4,FALSE) -> 4 | V598: =VLOOKUP($B598,'Gemini RAW'!$A:$Q,5,FALSE) -> 4 | W598: =VLOOKUP($B598,'Gemini RAW'!$A:$Q,6,FALSE) -> 3 | X598: =VLOOKUP($B598,'Gemini RAW'!$A:$Q,7,FALSE) -> 4 | Y598: =VLOOKUP($B598,'Gemini RAW'!$A:$Q,8,FALSE) -> 1 | Z598: =VLOOKUP($B598,'Gemini RAW'!$A:$Q,9,FALSE) -> 3.4 | AA598: =VLOOKUP($B598,'Gemini RAW'!$A:$Q,10,FALSE) -> 16 | AB598: =VLOOKUP($B598,'Gemini RAW'!$A:$Q,11,FALSE) -> 0.23271531 | AC598: =VLOOKUP($B598,'Gemini RAW'!$A:$Q,12,FALSE) -> 8 | AD598: =VLOOKUP($B598,'Gemini RAW'!$A:$Q,13,FALSE) -> The response provides a reasonably accurate and relevant answer to the user's query, but it lacks completeness and does not provide any citations to the source snippets. The content is generally clear and well-organized. The response touches on GDPR compliance and EU AI Act alignment, but it lacks specific details in these areas. The absence of citations is a significant weakness. | AE598: =VLOOKUP($B598,'Gemini RAW'!$A:$Q,14,FALSE) -> FALSE | AF598: =VLOOKUP($B598,'Gemini RAW'!$A:$Q,15,FALSE) -> 0 | AG598: =VLOOKUP($B598,'Gemini RAW'!$A:$Q,16,FALSE) -> 0 | AH598: =VLOOKUP($B598,'Gemini RAW'!$A:$Q,17,FALSE) -> 0
A599: 598 | B599: What steps should I follow to recover a lost or corrupted file? | C599: Based on web search results for 'What steps should I follow to recover a lost or corrupted file?': 1. What steps can I take to recover a corrupted file? - Quora: Jun 27, 2023·Then the best hope of an answer is to restore from a backup. I.e. get hold of another copy of the file. Then overwrite the corrupted one with ...How to fix corrupted files on my computer - QuoraWhat steps should I take if I discover corrupted files on my PC/Mac?More results from www.quora.com 2. Understanding Corrupted Files: Complete Recovery Methods Guide: What Is A Corrupted File? How Does A File Become Corrupted? Certain software issues may also corrupt a file. This may corrupt the file on which you were currently working. For example, an operating system may only corrupt the text files of a specific extension.Related:Use Of VPN At Work (With Benefits And Steps On Using It) Ways To Recover A File That Is Corrupted If a file gets corrupted, you might be able to change the file format by changing its extension and recover its content. With the advancement in software development, there are many programs available over the internet that can help you restore your files. Tips To Prevent Files From Getting Corrupted Here are some tips you can follow to prevent your files from getting corrupted: 3. Corrupted Files on Windows? Try these 7 Best Fixes - Fortect: Click “System Restore” and follow the prompts to revert your system to a previous state where the file was not corrupted. Perform a Check Disk on the Hard Drive. | D599: agentic | E599: 3 | F599: 4 | G599: 3 | H599: 3 | I599: 2 | J599: 3.1625 | K599: 15 | L599: 0.18271384 | M599: 1 | N599: The AI response provides relevant information regarding file recovery but lacks depth and clarity. It does not effectively utilize the provided snippets, leading to a lower score in citation quality and grounding. Improvements in structure and detail are necessary for a higher evaluation. | O599: TRUE | P599: TRUE | Q599: 284 | R599: 1511 | S599: =VLOOKUP($B599,'Gemini RAW'!$A:$Q,2,FALSE) -> Recovery tests are periodically conducted as part of the #50046 ITSCM policy. Details can be found in the ITSCM policy and the RRP documentation. App owners are responsible for integrity checks, which are documented in the header of each RRP test description. Backup administrators, database administrators and storage administrators participate in ITSCM lifecycle data recovery tests. | T599: =VLOOKUP($B599,'Gemini RAW'!$A:$Q,3,FALSE) -> rag | U599: =VLOOKUP($B599,'Gemini RAW'!$A:$Q,4,FALSE) -> 2 | V599: =VLOOKUP($B599,'Gemini RAW'!$A:$Q,5,FALSE) -> 1 | W599: =VLOOKUP($B599,'Gemini RAW'!$A:$Q,6,FALSE) -> 1 | X599: =VLOOKUP($B599,'Gemini RAW'!$A:$Q,7,FALSE) -> 3 | Y599: =VLOOKUP($B599,'Gemini RAW'!$A:$Q,8,FALSE) -> 1 | Z599: =VLOOKUP($B599,'Gemini RAW'!$A:$Q,9,FALSE) -> 1.46 | AA599: =VLOOKUP($B599,'Gemini RAW'!$A:$Q,10,FALSE) -> 8 | AB599: =VLOOKUP($B599,'Gemini RAW'!$A:$Q,11,FALSE) -> 0.45840873 | AC599: =VLOOKUP($B599,'Gemini RAW'!$A:$Q,12,FALSE) -> 2 | AD599: =VLOOKUP($B599,'Gemini RAW'!$A:$Q,13,FALSE) -> The response is not helpful in answering the user's query. It provides information about recovery tests and responsibilities within an ITSCM policy, but it does not provide the steps required to recover a lost or corrupted file. The response is factually related to data recovery but not directly answering the question. The source utilization is poor, and the citation quality is inadequate. | AE599: =VLOOKUP($B599,'Gemini RAW'!$A:$Q,14,FALSE) -> FALSE | AF599: =VLOOKUP($B599,'Gemini RAW'!$A:$Q,15,FALSE) -> 0 | AG599: =VLOOKUP($B599,'Gemini RAW'!$A:$Q,16,FALSE) -> 0 | AH599: =VLOOKUP($B599,'Gemini RAW'!$A:$Q,17,FALSE) -> 0
